Workbook

Sheet Summary
A1: SeereonOS — Feature Guide cross-reference
A2: Seereon Delivery Board: Feature Guide (Santosh Nayak, 28 Sep 2026) checked against the SeereonOS v6 build
A3: Date | B3: 2 Oct 2026
A5: How to read this workbook
A6: Line-by-line check — every sentence, bullet and table row of the guide, verbatim and in order, with where you see it in the build and a Result (OK / OK — improved / Intentional difference / Different — open).
A7: Guide vs build — one row per Feature Guide item (118). 'In build?' shows Present / Intentional difference / Partial / Missing; 'Where in the build' gives the screen and route; 'Notes' flags improvements and intentional changes.
A8: Your columns — 'Checked by Santosh' (drop-down Yes / No / Query) and 'Comments' on 'Line-by-line check' and 'Guide vs build' are the only cells to fill in. Example: Yes · 'Checked on phone, fine'.
A9: Build feature list — every live feature of SeereonOS: guide features (one per G-ID) plus everything built in addition, with who can use it by default.
A10: Additional features — only the extras, each with one line on why it helps.
A11: Guide screenshots map — each of the 36 guide screenshots (000–035) mapped to the equivalent build screen.
A12: All counts below are live formulas: change a status on 'Guide vs build' and they update.
A14: Line-by-line check (every guide sentence)
A15: Guide lines checked (sentences, bullets, table rows) | B15: =COUNTA('Line-by-line check'!$E$5:$E$267)
A16: OK | B16: =COUNTIF('Line-by-line check'!$H$5:$H$267,"OK")
A17: OK — improved | B17: =COUNTIF('Line-by-line check'!$H$5:$H$267,"OK — improved")
A18: Intentional difference | B18: =COUNTIF('Line-by-line check'!$H$5:$H$267,"Intentional difference")
A19: Different — open | B19: =COUNTIF('Line-by-line check'!$H$5:$H$267,"Different — open")
A20: % matching or better (OK + improved) | B20: =IF(B15=0,0,(B16+B17)/B15)
A21: Checked by Santosh so far (Yes) | B21: =COUNTIF('Line-by-line check'!$J$5:$J$267,"Yes")
A22: Open queries | B22: =COUNTIF('Line-by-line check'!$J$5:$J$267,"Query")
A24: Guide coverage
A25: Guide features (total) | B25: =COUNTA('Guide vs build'!$B$5:$B$122)
A26: Present | B26: =COUNTIF('Guide vs build'!$E$5:$E$122,"Present")
A27: Intentional difference | B27: =COUNTIF('Guide vs build'!$E$5:$E$122,"Intentional difference")
A28: Partial | B28: =COUNTIF('Guide vs build'!$E$5:$E$122,"Partial")
A29: Missing | B29: =COUNTIF('Guide vs build'!$E$5:$E$122,"Missing")
A30: % covered (Present + intentional ÷ total) | B30: =IF(B25=0,0,(B26+B27)/B25)
A31: Checked by Santosh so far (Yes) | B31: =COUNTIF('Guide vs build'!$I$5:$I$122,"Yes")
A32: Open queries | B32: =COUNTIF('Guide vs build'!$I$5:$I$122,"Query")
A34: Coverage by guide section
A35: Guide section | B35: Features | C35: Present / intentional | D35: Partial | E35: Missing | F35: % covered
A36: 1. Roles and views | B36: =COUNTIF('Guide vs build'!$A$5:$A$122,$A36) | C36: =COUNTIFS('Guide vs build'!$A$5:$A$122,$A36,'Guide vs build'!$E$5:$E$122,"Present")+COUNTIFS('Guide vs build'!$A$5:$A$122,$A36,'Guide vs build'!$E$5:$E$122,"Intentional difference") | D36: =COUNTIFS('Guide vs build'!$A$5:$A$122,$A36,'Guide vs build'!$E$5:$E$122,"Partial") | E36: =COUNTIFS('Guide vs build'!$A$5:$A$122,$A36,'Guide vs build'!$E$5:$E$122,"Missing") | F36: =IF(B36=0,0,C36/B36)
A37: 2. CEO dashboard: revenue first | B37: =COUNTIF('Guide vs build'!$A$5:$A$122,$A37) | C37: =COUNTIFS('Guide vs build'!$A$5:$A$122,$A37,'Guide vs build'!$E$5:$E$122,"Present")+COUNTIFS('Guide vs build'!$A$5:$A$122,$A37,'Guide vs build'!$E$5:$E$122,"Intentional difference") | D37: =COUNTIFS('Guide vs build'!$A$5:$A$122,$A37,'Guide vs build'!$E$5:$E$122,"Partial") | E37: =COUNTIFS('Guide vs build'!$A$5:$A$122,$A37,'Guide vs build'!$E$5:$E$122,"Missing") | F37: =IF(B37=0,0,C37/B37)
A38: 3. Projects: list, status, type | B38: =COUNTIF('Guide vs build'!$A$5:$A$122,$A38) | C38: =COUNTIFS('Guide vs build'!$A$5:$A$122,$A38,'Guide vs build'!$E$5:$E$122,"Present")+COUNTIFS('Guide vs build'!$A$5:$A$122,$A38,'Guide vs build'!$E$5:$E$122,"Intentional difference") | D38: =COUNTIFS('Guide vs build'!$A$5:$A$122,$A38,'Guide vs build'!$E$5:$E$122,"Partial") | E38: =COUNTIFS('Guide vs build'!$A$5:$A$122,$A38,'Guide vs build'!$E$5:$E$122,"Missing") | F38: =IF(B38=0,0,C38/B38)
A39: 4. Project page: milestones, tasks and WBS | B39: =COUNTIF('Guide vs build'!$A$5:$A$122,$A39) | C39: =COUNTIFS('Guide vs build'!$A$5:$A$122,$A39,'Guide vs build'!$E$5:$E$122,"Present")+COUNTIFS('Guide vs build'!$A$5:$A$122,$A39,'Guide vs build'!$E$5:$E$122,"Intentional difference") | D39: =COUNTIFS('Guide vs build'!$A$5:$A$122,$A39,'Guide vs build'!$E$5:$E$122,"Partial") | E39: =COUNTIFS('Guide vs build'!$A$5:$A$122,$A39,'Guide vs build'!$E$5:$E$122,"Missing") | F39: =IF(B39=0,0,C39/B39)
A40: 5. Schedule, critical path and change requests | B40: =COUNTIF('Guide vs build'!$A$5:$A$122,$A40) | C40: =COUNTIFS('Guide vs build'!$A$5:$A$122,$A40,'Guide vs build'!$E$5:$E$122,"Present")+COUNTIFS('Guide vs build'!$A$5:$A$122,$A40,'Guide vs build'!$E$5:$E$122,"Intentional difference") | D40: =COUNTIFS('Guide vs build'!$A$5:$A$122,$A40,'Guide vs build'!$E$5:$E$122,"Partial") | E40: =COUNTIFS('Guide vs build'!$A$5:$A$122,$A40,'Guide vs build'!$E$5:$E$122,"Missing") | F40: =IF(B40=0,0,C40/B40)
A41: 6. Costing, allocation and margins | B41: =COUNTIF('Guide vs build'!$A$5:$A$122,$A41) | C41: =COUNTIFS('Guide vs build'!$A$5:$A$122,$A41,'Guide vs build'!$E$5:$E$122,"Present")+COUNTIFS('Guide vs build'!$A$5:$A$122,$A41,'Guide vs build'!$E$5:$E$122,"Intentional difference") | D41: =COUNTIFS('Guide vs build'!$A$5:$A$122,$A41,'Guide vs build'!$E$5:$E$122,"Partial") | E41: =COUNTIFS('Guide vs build'!$A$5:$A$122,$A41,'Guide vs build'!$E$5:$E$122,"Missing") | F41: =IF(B41=0,0,C41/B41)
A42: 7. Tasks: owners, dependencies, backup and threads | B42: =COUNTIF('Guide vs build'!$A$5:$A$122,$A42) | C42: =COUNTIFS('Guide vs build'!$A$5:$A$122,$A42,'Guide vs build'!$E$5:$E$122,"Present")+COUNTIFS('Guide vs build'!$A$5:$A$122,$A42,'Guide vs build'!$E$5:$E$122,"Intentional difference") | D42: =COUNTIFS('Guide vs build'!$A$5:$A$122,$A42,'Guide vs build'!$E$5:$E$122,"Partial") | E42: =COUNTIFS('Guide vs build'!$A$5:$A$122,$A42,'Guide vs build'!$E$5:$E$122,"Missing") | F42: =IF(B42=0,0,C42/B42)
A43: 8. Timesheet and daily update | B43: =COUNTIF('Guide vs build'!$A$5:$A$122,$A43) | C43: =COUNTIFS('Guide vs build'!$A$5:$A$122,$A43,'Guide vs build'!$E$5:$E$122,"Present")+COUNTIFS('Guide vs build'!$A$5:$A$122,$A43,'Guide vs build'!$E$5:$E$122,"Intentional difference") | D43: =COUNTIFS('Guide vs build'!$A$5:$A$122,$A43,'Guide vs build'!$E$5:$E$122,"Partial") | E43: =COUNTIFS('Guide vs build'!$A$5:$A$122,$A43,'Guide vs build'!$E$5:$E$122,"Missing") | F43: =IF(B43=0,0,C43/B43)
A44: 9. Approvals and the manager's approval KPI | B44: =COUNTIF('Guide vs build'!$A$5:$A$122,$A44) | C44: =COUNTIFS('Guide vs build'!$A$5:$A$122,$A44,'Guide vs build'!$E$5:$E$122,"Present")+COUNTIFS('Guide vs build'!$A$5:$A$122,$A44,'Guide vs build'!$E$5:$E$122,"Intentional difference") | D44: =COUNTIFS('Guide vs build'!$A$5:$A$122,$A44,'Guide vs build'!$E$5:$E$122,"Partial") | E44: =COUNTIFS('Guide vs build'!$A$5:$A$122,$A44,'Guide vs build'!$E$5:$E$122,"Missing") | F44: =IF(B44=0,0,C44/B44)
A45: 10. Payroll: pay for approved days | B45: =COUNTIF('Guide vs build'!$A$5:$A$122,$A45) | C45: =COUNTIFS('Guide vs build'!$A$5:$A$122,$A45,'Guide vs build'!$E$5:$E$122,"Present")+COUNTIFS('Guide vs build'!$A$5:$A$122,$A45,'Guide vs build'!$E$5:$E$122,"Intentional difference") | D45: =COUNTIFS('Guide vs build'!$A$5:$A$122,$A45,'Guide vs build'!$E$5:$E$122,"Partial") | E45: =COUNTIFS('Guide vs build'!$A$5:$A$122,$A45,'Guide vs build'!$E$5:$E$122,"Missing") | F45: =IF(B45=0,0,C45/B45)
A46: 11. Sales: leads, pipeline and the activity trail | B46: =COUNTIF('Guide vs build'!$A$5:$A$122,$A46) | C46: =COUNTIFS('Guide vs build'!$A$5:$A$122,$A46,'Guide vs build'!$E$5:$E$122,"Present")+COUNTIFS('Guide vs build'!$A$5:$A$122,$A46,'Guide vs build'!$E$5:$E$122,"Intentional difference") | D46: =COUNTIFS('Guide vs build'!$A$5:$A$122,$A46,'Guide vs build'!$E$5:$E$122,"Partial") | E46: =COUNTIFS('Guide vs build'!$A$5:$A$122,$A46,'Guide vs build'!$E$5:$E$122,"Missing") | F46: =IF(B46=0,0,C46/B46)
A47: 12. Sales cost, performance and pay | B47: =COUNTIF('Guide vs build'!$A$5:$A$122,$A47) | C47: =COUNTIFS('Guide vs build'!$A$5:$A$122,$A47,'Guide vs build'!$E$5:$E$122,"Present")+COUNTIFS('Guide vs build'!$A$5:$A$122,$A47,'Guide vs build'!$E$5:$E$122,"Intentional difference") | D47: =COUNTIFS('Guide vs build'!$A$5:$A$122,$A47,'Guide vs build'!$E$5:$E$122,"Partial") | E47: =COUNTIFS('Guide vs build'!$A$5:$A$122,$A47,'Guide vs build'!$E$5:$E$122,"Missing") | F47: =IF(B47=0,0,C47/B47)
... A52: 17. Rules and KPI definitions | B52: =COUNTIF('Guide vs build'!$A$5:$A$122,$A52) | C52: =COUNTIFS('Guide vs build'!$A$5:$A$122,$A52,'Guide vs build'!$E$5:$E$122,"Present")+COUNTIFS('Guide vs build'!$A$5:$A$122,$A52,'Guide vs build'!$E$5:$E$122,"Intentional difference") | D52: =COUNTIFS('Guide vs build'!$A$5:$A$122,$A52,'Guide vs build'!$E$5:$E$122,"Partial") | E52: =COUNTIFS('Guide vs build'!$A$5:$A$122,$A52,'Guide vs build'!$E$5:$E$122,"Missing") | F52: =IF(B52=0,0,C52/B52)
A53: Total | B53: =SUM(B36:B52) | C53: =SUM(C36:C52) | D53: =SUM(D36:D52) | E53: =SUM(E36:E52) | F53: =IF(B53=0,0,C53/B53)
A55: Build features
A56: Build features (total, all live) | B56: =COUNTA('Build feature list'!$C$5:$C$271)
A57: From the Feature Guide | B57: =COUNTIF('Build feature list'!$F$5:$F$271,"Feature Guide*")
A58: Additional to the guide | B58: =COUNTIF('Build feature list'!$F$5:$F$271,"Additional*")
A59: of which v1 base | B59: =COUNTIF('Build feature list'!$F$5:$F$271,"Additional (v1 base)")
A60: of which v3 business processes | B60: =COUNTIF('Build feature list'!$F$5:$F$271,"Additional (v3 business processes)")
A61: of which v4 access & controls | B61: =COUNTIF('Build feature list'!$F$5:$F$271,"Additional (v4 access & controls)")
A62: of which v5 parity extras | B62: =COUNTIF('Build feature list'!$F$5:$F$271,"Additional (v5 parity extras)")
A63: of which v7 workflows, documents & invoicing | B63: =COUNTIF('Build feature list'!$F$5:$F$271,"Additional (v7 workflows, documents & invoicing)")
A65: Features by area
A66: Area | B66: All features | C66: From guide | D66: Additional
A67: Dashboards | B67: =COUNTIF('Build feature list'!$B$5:$B$271,$A67) | C67: =COUNTIFS('Build feature list'!$B$5:$B$271,$A67,'Build feature list'!$F$5:$F$271,"Feature Guide*") | D67: =COUNTIFS('Build feature list'!$B$5:$B$271,$A67,'Build feature list'!$F$5:$F$271,"Additional*")
A68: Projects & delivery | B68: =COUNTIF('Build feature list'!$B$5:$B$271,$A68) | C68: =COUNTIFS('Build feature list'!$B$5:$B$271,$A68,'Build feature list'!$F$5:$F$271,"Feature Guide*") | D68: =COUNTIFS('Build feature list'!$B$5:$B$271,$A68,'Build feature list'!$F$5:$F$271,"Additional*")
A69: Tasks | B69: =COUNTIF('Build feature list'!$B$5:$B$271,$A69) | C69: =COUNTIFS('Build feature list'!$B$5:$B$271,$A69,'Build feature list'!$F$5:$F$271,"Feature Guide*") | D69: =COUNTIFS('Build feature list'!$B$5:$B$271,$A69,'Build feature list'!$F$5:$F$271,"Additional*")
A70: Time & attendance | B70: =COUNTIF('Build feature list'!$B$5:$B$271,$A70) | C70: =COUNTIFS('Build feature list'!$B$5:$B$271,$A70,'Build feature list'!$F$5:$F$271,"Feature Guide*") | D70: =COUNTIFS('Build feature list'!$B$5:$B$271,$A70,'Build feature list'!$F$5:$F$271,"Additional*")
A71: Approvals & governance | B71: =COUNTIF('Build feature list'!$B$5:$B$271,$A71) | C71: =COUNTIFS('Build feature list'!$B$5:$B$271,$A71,'Build feature list'!$F$5:$F$271,"Feature Guide*") | D71: =COUNTIFS('Build feature list'!$B$5:$B$271,$A71,'Build feature list'!$F$5:$F$271,"Additional*")
A72: Payroll | B72: =COUNTIF('Build feature list'!$B$5:$B$271,$A72) | C72: =COUNTIFS('Build feature list'!$B$5:$B$271,$A72,'Build feature list'!$F$5:$F$271,"Feature Guide*") | D72: =COUNTIFS('Build feature list'!$B$5:$B$271,$A72,'Build feature list'!$F$5:$F$271,"Additional*")
A73: Sales | B73: =COUNTIF('Build feature list'!$B$5:$B$271,$A73) | C73: =COUNTIFS('Build feature list'!$B$5:$B$271,$A73,'Build feature list'!$F$5:$F$271,"Feature Guide*") | D73: =COUNTIFS('Build feature list'!$B$5:$B$271,$A73,'Build feature list'!$F$5:$F$271,"Additional*")
A74: Clients & contracts | B74: =COUNTIF('Build feature list'!$B$5:$B$271,$A74) | C74: =COUNTIFS('Build feature list'!$B$5:$B$271,$A74,'Build feature list'!$F$5:$F$271,"Feature Guide*") | D74: =COUNTIFS('Build feature list'!$B$5:$B$271,$A74,'Build feature list'!$F$5:$F$271,"Additional*")
A75: Finance | B75: =COUNTIF('Build feature list'!$B$5:$B$271,$A75) | C75: =COUNTIFS('Build feature list'!$B$5:$B$271,$A75,'Build feature list'!$F$5:$F$271,"Feature Guide*") | D75: =COUNTIFS('Build feature list'!$B$5:$B$271,$A75,'Build feature list'!$F$5:$F$271,"Additional*")
A76: Spend & procurement | B76: =COUNTIF('Build feature list'!$B$5:$B$271,$A76) | C76: =COUNTIFS('Build feature list'!$B$5:$B$271,$A76,'Build feature list'!$F$5:$F$271,"Feature Guide*") | D76: =COUNTIFS('Build feature list'!$B$5:$B$271,$A76,'Build feature list'!$F$5:$F$271,"Additional*")
A77: Revenue assurance | B77: =COUNTIF('Build feature list'!$B$5:$B$271,$A77) | C77: =COUNTIFS('Build feature list'!$B$5:$B$271,$A77,'Build feature list'!$F$5:$F$271,"Feature Guide*") | D77: =COUNTIFS('Build feature list'!$B$5:$B$271,$A77,'Build feature list'!$F$5:$F$271,"Additional*")
A78: People & HR | B78: =COUNTIF('Build feature list'!$B$5:$B$271,$A78) | C78: =COUNTIFS('Build feature list'!$B$5:$B$271,$A78,'Build feature list'!$F$5:$F$271,"Feature Guide*") | D78: =COUNTIFS('Build feature list'!$B$5:$B$271,$A78,'Build feature list'!$F$5:$F$271,"Additional*")
... A87: Platform & UX | B87: =COUNTIF('Build feature list'!$B$5:$B$271,$A87) | C87: =COUNTIFS('Build feature list'!$B$5:$B$271,$A87,'Build feature list'!$F$5:$F$271,"Feature Guide*") | D87: =COUNTIFS('Build feature list'!$B$5:$B$271,$A87,'Build feature list'!$F$5:$F$271,"Additional*")
A88: Total | B88: =SUM(B67:B87) | C88: =SUM(C67:C87) | D88: =SUM(D67:D87)
A90: Intentional differences vs the guide
A91: Difference | B91: What it means
A92: View as offers the 9 configurable roles | B92: The guide had 5 fixed roles; View as now lists Administrator, CEO, CTO, Project Manager, HR Manager, HR Executive, Sales Manager, Sales Executive and Employee. It stays read-only (G1.03).
A93: HR Manager role can prepare payroll and see the ledger | B93: The guide said payroll is CEO only. The HR Manager prepares; the CEO finalises through maker-checker (G1.05, G10.01).
A94: Task Remove with hours logged becomes Cancel | B94: Tasks with time booked are cancelled, not deleted, so actual hours and cost stay in margins and payroll (G5.03).
A95: One-project delegations hand over task follow-ups only | B95: Timesheet approvals move only with an all-projects delegation (G9.05, G16.05).
A96: Deduct-unapproved-days is a company setting | B96: Off by default for new tenants, as the guide says; switched on for Seereon (G10.08).
A97: Sunday column shown only if it is a working day | B97: Mon–Sat as in the guide; Sunday appears only when the company calendar makes it a working day (G8.01).
A98: Weekly score adds Timesheet and Early warning | B98: Alongside the guide's on-time delivery, effort accuracy, daily updates and Friday demo (+ approval KPI for managers) (G15.05).
A99: Cost loading removed | B99: The guide text defines cost per hour = CTC ÷ (working days in the month × minimum hours) with no loading; loading appeared only in prototype screenshots, so it was removed to follow the text (G13.04, G3.11, G6.02).
A100: 'All milestones' allocation option removed | B100: Follows the guide's 'all four are required': every allocation row names one milestone (G6.01).
A102: Sources: guide text (docs/Seereon-Delivery-Board-Feature-Guide.pdf); checklist docs/feature-guide-checklist.md; verified v5 mapping; v6 line-by-line checks (§6 costing, §7 tasks, §8–9 timesheet/approvals), v6 audit of §1–5 and §10–17 and the v6 fix reports (money/insights/rules, settings/payroll/leave, projects/sales), spot-checked in code; src/app/nav.ts, src/app/routes.tsx, src/domain/permissionCatalog.ts, README.md, CONVENTIONS.md; docs/SeereonOS-Business-Process-Catalogue.xlsx.

Sheet Line-by-line check
A1: Feature Guide — line-by-line check
A2: Every sentence, bullet and table row of the Feature Guide (28 Sep 2026), in order, against SeereonOS v6 (2 Oct 2026). Fill in 'Checked by Santosh' (Yes / No / Query) and 'Comments'.
A4: # | B4: Guide section | C4: Page | D4: Type | E4: Guide text (verbatim) | F4: G-ID(s) | G4: Where you see it in the build (menu › screen › section / column / button) | H4: Result | I4: Notes | J4: Checked by Santosh | K4: Comments
A5: 1 | B5: Introduction | C5: 1 | D5: Title | E5: Seereon Delivery Board: Feature Guide | F5: — | G5: Product is now SeereonOS; the guide's screens live in the left menu (Dashboard … Rules) | H5: OK — improved | I5: Renamed from Seereon Delivery Board to SeereonOS.
A6: 2 | B6: Introduction | C6: 1 | D6: Title | E6: Santosh Nayak · 28 Sep 2026 | F6: — | G6: — | H6: OK | I6: Guide author and date (reference only).
A7: 3 | B7: Introduction | C7: 1 | D7: Sentence | E7: This guide explains every feature of the board in plain words, one screen at a time, for the whole team: developers, the project manager, sales and new joiners. | F7: — | G7: Whole app | H7: OK | I7: Intro sentence; no feature.
A8: 4 | B8: Introduction | C8: 1 | D8: Sentence | E8: The screenshots come from the working prototype with dummy data. | F8: — | G8: Demo data in the build mirrors the prototype (Seereon tenant: EduReon, SeerHR, same people) | H8: OK
A9: 5 | B9: Introduction | C9: 1 | D9: Sentence | E9: The SaaS build keeps the same screens and rules; the Technical Design has the build detail. | F9: — | G9: Same screens and rules; build detail in specs/ (Technical Design) | H9: OK
A10: 6 | B10: 1. Roles and views | C10: 1 | D10: Heading | E10: 1. Roles and views | F10: G1.01–G1.06 | G10: Top bar + left menu + Dashboard (/home) | H10: OK
A11: 7 | B11: 1. Roles and views | C11: 1 | D11: Sentence | E11: Everyone uses the same board, but each person sees only what their role needs. | F11: G1.02, G1.05 | G11: One login; menu, buttons and data follow the person's permissions | H11: OK
A12: 8 | B12: 1. Roles and views | C12: 1 | D12: Sentence | E12: There are five roles: CEO (admin), project manager, sales, operations and employee. | F12: G1.02, G1.05 | G12: Admin › Organisation setup › Roles & permissions (/setup/roles): 9 default roles | H12: Intentional difference | I12: The five guide roles are kept as the five dashboard views; access comes from 9 configurable roles (Administrator, CEO, CTO, Project Manager, HR Manager, HR Executive, Sales Manager, Sales Executive, Employee).
A13: 9 | B13: 1. Roles and views | C13: 1 | D13: Screenshot caption | E13: Header with the week switcher, tabs, View as control and the five dashboard views | F13: G1.01–G1.04 | G13: Top bar (week switcher, View as) + left menu + Dashboard view switch | H13: OK | I13: Screenshot 000.
A14: 10 | B14: 1. Roles and views | C14: 1 | D14: Bullet | E14: Header: the company name, the week being viewed (use the arrows to move between weeks), and the tabs you are allowed to open. | F14: G1.01, G1.02 | G14: Top bar: company name, week switcher ‹ › with 'This week'; v7 grouped left menu shows only allowed items: Dashboard, My work › Timesheet & log, Projects & WBS (All projects, Milestones & billing, WBS, Schedule & critical path, Change requests, Resource allocation, Costing & margin, Client view, Import WBS), Tasks (All tasks, Timesheet approvals), Finance (Payroll, Ledger, Profit & loss, Profit margins), Company (Weekly scorecard, Insights, Operations, Rules), Admin › Team & settings | H14: OK — improved | I14: v6: menu names now match the guide's tabs. Week switcher also drives Tasks.
A15: 11 | B15: 1. Roles and views | C15: 1 | D15: Bullet | E15: View as (admin only): the CEO can switch to any role to check exactly what that person sees. | F15: G1.03 | G15: Top bar › View as (CEO / Administrator) | H15: Intentional difference | I15: View as offers the 9 configurable roles instead of 5 fixed ones.
A16: 12 | B16: 1. Roles and views | C16: 1 | D16: Bullet (cont.) | E16: In the SaaS version this mode is read-only, so nothing can be changed by accident. | F16: G1.03 | G16: Top bar › View as — banner 'Viewing as X — read-only'; every write refused | H16: OK
A17: 13 | B17: 1. Roles and views | C17: 1 | D17: Bullet | E17: Dashboard views: CEO, Project manager, Sales, Operations and Employee. | F17: G1.04 | G17: Dashboard (/home) — switch CEO · Project manager · Sales · Operations · Employee | H17: OK
A18: 14 | B18: 1. Roles and views | C18: 1 | D18: Bullet (cont.) | E18: A salesperson lands on Sales; an employee lands on Employee and cannot open the others. | F18: G1.04 | G18: Dashboard (/home): sales roles land on Sales; Employee lands on Employee with no switch | H18: OK
A19: 15 | B19: 1. Roles and views | C19: 1 | D19: Table row | E19: Role table — columns: Role | Lands on | Can change | Cannot see | F19: G1.05 | G19: Admin › Organisation setup › Roles & permissions (/setup/roles) | H19: OK | I19: Table header row.
A20: 16 | B20: 1. Roles and views | C20: 1 | D20: Table row | E20: CEO (admin) | CEO dashboard | Everything, including settings, rates and payroll | Nothing hidden | F20: G1.05 | G20: CEO role: all permissions; lands on Dashboard › CEO | H20: OK
A21: 17 | B21: 1. Roles and views | C21: 1 | D21: Table row | E21: Project manager | Project manager view | Own projects, tasks, allocation; approves team timesheets | Salaries, payroll, company finance (margins only if granted) | F21: G1.05 | G21: Project Manager role: own projects, tasks, allocation, approves team timesheets; no salaries / payroll / finance; margins only with the extra 'See project margins' grant | H21: OK | I21: v6: the PM demo user no longer has margins by default.
A22: 18 | B22: 1. Roles and views | C22: 1 | D22: Table row | E22: Sales | Sales view | Own leads and deals | Other people’s pay, project costs | F22: G1.05 | G22: Sales Manager / Sales Executive roles: own deals; Compensation shows own pay only; project costs refused | H22: OK
A23: 19 | B23: 1. Roles and views | C23: 1 | D23: Table row | E23: Operations | Operations view | Ops register, openings, leave entries | Salaries unless granted, margins | F23: G1.05 | G23: HR Manager / HR Executive roles: Operations, Openings, Leave › Record leave; margins refused | H23: Intentional difference | I23: HR Manager can also prepare payroll and see the ledger (CEO finalises via maker-checker).
A24: 20 | B24: 1. Roles and views | C24: 1 | D24: Table row | E24: Employee | Employee view | Own tasks’ status, own timesheet, comments | Other people’s timesheets, money | F24: G1.05 | G24: Employee role: own tasks' status, own timesheet, comments; no money, no other timesheets | H24: OK
A25: 21 | B25: 1. Roles and views | C25: 2 | D25: Screenshot caption | E25: Employee view: tasks tagged to me, my week at a glance | F25: G1.06 | G25: Dashboard › Employee (/home) | H25: OK | I25: Screenshot 001.
A26: 22 | B26: 1. Roles and views | C26: 2 | D26: Sentence | E26: The employee view shows only that person’s world: tasks where they were mentioned or tagged, tasks they are covering for a colleague on leave, and their own delivery numbers for the week. | F26: G1.06 | G26: Dashboard › Employee: 'Tagged you', 'Covering', week score, on-time, effort ratio, utilisation, overdue, average lateness | H26: OK | I26: Seed comments fixed in v6 (Tagged you shows the right EduReon task).
A27: 23 | B27: 2. CEO dashboard: revenue first | C27: 2 | D27: Heading | E27: 2. CEO dashboard: revenue first | F27: G2.01–G2.08 | G27: Dashboard › CEO › Overview (/home) | H27: OK
A28: 24 | B28: 2. CEO dashboard: revenue first | C28: 2 | D28: Sentence | E28: The CEO lands on revenue, because that is the number that decides everything else. | F28: G2.01 | G28: CEO lands on Dashboard › CEO › Overview, revenue cards first | H28: OK
A29: 25 | B29: 2. CEO dashboard: revenue first | C29: 2 | D29: Sentence | E29: The Overview shows this month, this quarter and this financial year (April to March) side by side. | F29: G2.02 | G29: Dashboard › CEO › Overview (/home) — 'Revenue and earnings': This month / This quarter / This financial year (Apr–Mar) | H29: OK
A30: 26 | B30: 2. CEO dashboard: revenue first | C30: 3 | D30: Screenshot caption | E30: Revenue and earnings: month, quarter and year, with the 12-month chart and revenue ahead | F30: G2.01–G2.05 | G30: Dashboard › CEO › Overview (/home) — 'Revenue and earnings', 'Monthly revenue, last 12 months', 'Revenue ahead' | H30: OK | I30: Screenshot 002.
A31: 27 | B31: 2. CEO dashboard: revenue first | C31: 3 | D31: Bullet | E31: Top four numbers: revenue this month, this quarter, this financial year, and net earnings for the year. | F31: G2.01 | G31: Dashboard › CEO › Overview (/home) — top four tiles: revenue month, quarter, FY, net earnings FY | H31: OK | I31: v6: month and quarter count only income up to today.
A32: 28 | B32: 2. CEO dashboard: revenue first | C32: 3 | D32: Bullet (cont.) | E32: The arrow shows the change against the previous period. | F32: G2.01 | G32: Dashboard › CEO › Overview (/home) — change arrow on each tile vs previous period | H32: OK
A33: 29 | B33: 2. CEO dashboard: revenue first | C33: 3 | D33: Bullet | E33: Period table: for each period, revenue billed, cash collected, total costs (salaries plus expenses), net earnings, net margin, and the change in revenue. | F33: G2.02 | G33: Dashboard › CEO › Overview (/home) — period table: Revenue billed, Collected, Costs, Net earnings, Net margin, Revenue change | H33: OK | I33: v6: costs use one salary basis, so the dashboard equals the P&L.
A34: 30 | B34: 2. CEO dashboard: revenue first | C34: 3 | D34: Bullet | E34: 12-month chart: billed and collected side by side, so a gap between invoicing and cash shows at a glance. | F34: G2.03 | G34: Dashboard › CEO › Overview (/home) — 'Monthly revenue, last 12 months' (billed vs collected, table toggle) | H34: OK | I34: No future months.
A35: 31 | B35: 2. CEO dashboard: revenue first | C35: 3 | D35: Bullet | E35: Where revenue came from: split by stream (SAP consulting, products, services, subscriptions, AMS). | F35: G2.04 | G35: Dashboard › CEO › Overview (/home) — 'Where revenue came from, this financial year': SAP consulting, Products, Services, Subscriptions, AMS | H35: OK | I35: v6: stream names now match the guide everywhere (dashboard, P&L).
A36: 32 | B36: 2. CEO dashboard: revenue first | C36: 3 | D36: Bullet | E36: Revenue ahead: milestones due but not yet invoiced, plus the weighted sales pipeline. | F36: G2.05 | G36: Dashboard › CEO › Overview (/home) — 'Revenue ahead': milestones billable 30/60/90 days + weighted pipeline | H36: OK
A37: 33 | B37: 2. CEO dashboard: revenue first | C37: 4 | D37: Screenshot caption | E37: Delivery and milestone cash: health of all projects and money due in 30 days | F37: G2.06, G2.07 | G37: Dashboard › CEO › Overview (/home) — 'Delivery' and 'Milestones and cash' | H37: OK | I37: Screenshot 003.
A38: 34 | B38: 2. CEO dashboard: revenue first | C38: 4 | D38: Sentence | E38: Below revenue, Delivery shows how many milestones were hit on time, the schedule performance index (SPI: above 1.0 means ahead of plan), average lateness and overdue tasks. | F38: G2.06 | G38: Dashboard › CEO › Overview (/home) — 'Delivery': Milestones hit on time, SPI, Average lateness, Overdue tasks (+ CPI, utilisation, projects in red, forecast to breach, done in 4 weeks, team score) | H38: OK — improved | I38: v6: added average lateness and overdue tasks as worded in the guide.
A39: 35 | B39: 2. CEO dashboard: revenue first | C39: 4 | D39: Sentence | E39: Milestones and cash lists milestones due in the next 30 days with their billing value, so the CEO sees which delivery dates carry money. | F39: G2.07 | G39: Dashboard › CEO › Overview (/home) — 'Milestones and cash': due in the next 30 days with deadline, forecast, status, billing | H39: OK
A40: 36 | B40: 3. Projects: list, status, type | C40: 4 | D40: Heading | E40: 3. Projects: list, status, type | F40: G3.01–G3.11 | G40: Projects & WBS › All projects (/projects) | H40: OK | I40: Menu group 'Projects & WBS' as in the guide (v7: project areas also reachable as submenus).
A41: 37 | B41: 3. Projects: list, status, type | C41: 4 | D41: Sentence | E41: The Projects tab opens on a list of all projects. | F41: G3.01 | G41: Projects & WBS › All projects (/projects) — list of all projects the person may see | H41: OK
A42: 38 | B42: 3. Projects: list, status, type | C42: 4 | D42: Sentence | E42: Click a row to open that project; click it again to close it. | F42: G3.05 | G42: Projects & WBS › All projects (/projects) — click a row to expand it inline; click again to close | H42: OK
A43: 39 | B43: 3. Projects: list, status, type | C43: 4 | D43: Screenshot caption | E43: Projects list with a filter chip for each status and the Create project button | F43: G3.01, G3.07 | G43: Projects & WBS › All projects (/projects) — status chips + '+ Create project' | H43: OK | I43: Screenshot 004.
A44: 40 | B44: 3. Projects: list, status, type | C44: 5 | D44: Bullet | E44: Status chips: All, Initiated, Active, On hold, NPA, Completed, Closed, each with a count. | F44: G3.01 | G44: Projects & WBS › All projects (/projects) — chips All / Initiated / Active / On hold / NPA / Completed / Closed with counts | H44: OK
A45: 41 | B45: 3. Projects: list, status, type | C45: 5 | D45: Bullet (cont.) | E45: Click one to see only those projects. | F45: G3.01 | G45: Projects & WBS › All projects (/projects) — clicking a chip filters the list | H45: OK
A46: 42 | B46: 3. Projects: list, status, type | C46: 5 | D46: Bullet | E46: Status column: shows health (On track, At risk, Off track) and a dropdown to change the status right from the list. | F46: G3.02 | G46: Projects & WBS › All projects (/projects) — 'Status' column: health badge + status dropdown | H46: OK
A47: 43 | B47: 3. Projects: list, status, type | C47: 5 | D47: Bullet (cont.) | E47: Moving to On hold, NPA (non-performing asset: a client not paying or not engaging) or Closed asks for a reason; every change is kept in the project’s status history. | F47: G3.03 | G47: Projects & WBS › All projects (/projects) — reason dialog for On hold / NPA / Closed; project › Activity tab › Status history | H47: OK
A48: 44 | B48: 3. Projects: list, status, type | C48: 5 | D48: Bullet | E48: Columns: project manager, commercial model (fixed price, time and material), type, progress (% and tasks done), planned end, forecast end (red when late), next milestone, contract value and projected margin. | F48: G3.04 | G48: Projects & WBS › All projects (/projects) — columns PM, Model (Fixed price / Time & material), Type, Progress (% and x/y), Planned end, Forecast end (red '+Nd late'), Next milestone, Contract, Projected margin | H48: OK — improved | I48: v6: all columns fit at 1280 px+; one label 'Fixed price' everywhere. Projected margin only with the margins permission.
A49: 45 | B49: 3. Projects: list, status, type | C49: 5 | D49: Table row | E49: Status table — columns: Status | Means | F49: G3.02 | G49: Projects & WBS › All projects (/projects) — 'What the statuses mean' popover next to the chips | H49: OK — improved | I49: v6: added; meanings also shown in the status dropdown and reason dialog.
A50: 46 | B50: 3. Projects: list, status, type | C50: 5 | D50: Table row | E50: Initiated | Signed or agreed, work not started | F50: G3.02 | G50: Projects & WBS › All projects (/projects) — popover row 'Initiated' | H50: OK | I50: Verbatim.
A51: 47 | B51: 3. Projects: list, status, type | C51: 5 | D51: Table row | E51: Active | Work in progress | F51: G3.02 | G51: Projects & WBS › All projects (/projects) — popover row 'Active' | H51: OK | I51: Verbatim.
A52: 48 | B52: 3. Projects: list, status, type | C52: 5 | D52: Table row | E52: On hold | Paused; reason required | F52: G3.02, G3.03 | G52: Projects & WBS › All projects (/projects) — popover row 'On hold'; reason required | H52: OK
A53: 49 | B53: 3. Projects: list, status, type | C53: 5 | D53: Table row | E53: NPA | Client not paying or not responding; reason required | F53: G3.02, G3.03 | G53: Projects & WBS › All projects (/projects) — popover row 'NPA'; reason required | H53: OK
A54: 50 | B54: 3. Projects: list, status, type | C54: 5 | D54: Table row | E54: Completed | All work delivered, awaiting closure or final payment | F54: G3.02 | G54: Projects & WBS › All projects (/projects) — popover row 'Completed' | H54: OK
A55: 51 | B55: 3. Projects: list, status, type | C55: 5 | D55: Table row | E55: Closed | Commercially closed; reason required | F55: G3.02, G3.03 | G55: Projects & WBS › All projects (/projects) — popover row 'Closed'; reason required | H55: OK
A56: 52 | B56: 3. Projects: list, status, type | C56: 5 | D56: Sentence | E56: Project types: Product, Service, SaaS, AMS (annual maintenance support). | F56: G3.06 | G56: Projects & WBS › All projects (/projects) — Type filter and Create form: Product / Service / SaaS / AMS | H56: OK
A57: 53 | B57: 3. Projects: list, status, type | C57: 6 | D57: Screenshot caption | E57: Create project form: name, client, manager, dates, type, model, milestones and costing | F57: G3.07–G3.10 | G57: Projects & WBS › All projects (/projects) › '+ Create project' form | H57: OK | I57: Screenshot 005.
A58: 54 | B58: 3. Projects: list, status, type | C58: 6 | D58: Sentence | E58: + Create project opens the form: name, client, project manager, start and planned end, type, commercial model, priority, milestones with billing amounts, documents, and the costing plan. | F58: G3.07–G3.10 | G58: Projects & WBS › All projects (/projects) › '+ Create project': name, client, PM, start, planned end (calendar line), type, model, priority, 'Auto milestone setup' (name | amount per line), Documents (20 MB each), Project cost calculator | H58: OK
A59: 55 | B59: 3. Projects: list, status, type | C59: 6 | D59: Sentence | E59: The project code is generated automatically. | F59: G3.07 | G59: Projects & WBS › All projects (/projects) › '+ Create project' — 'Project code PRJ-0NN is assigned automatically' | H59: OK
A60: 56 | B60: 4. Project page: milestones, tasks and WBS | C60: 6 | D60: Heading | E60: 4. Project page: milestones, tasks and WBS | F60: G4.01–G4.10 | G60: Projects & WBS › All projects › project › WBS tab (/projects/:id/wbs); direct: Projects & WBS › Milestones & billing / WBS | H60: OK
A61: 57 | B61: 4. Project page: milestones, tasks and WBS | C61: 6 | D61: Sentence | E61: A project is broken into milestones, and milestones into tasks. | F61: G4.01 | G61: Projects & WBS › All projects › project › WBS tab (/projects/:id/wbs); direct: Projects & WBS › Milestones & billing / WBS — milestones with their tasks | H61: OK
A62: 58 | B62: 4. Project page: milestones, tasks and WBS | C62: 6 | D62: Sentence | E62: That structure is the WBS (work breakdown structure). | F62: G4.09 | G62: Projects & WBS › All projects › project › WBS tab (/projects/:id/wbs); direct: Projects & WBS › Milestones & billing / WBS — 'Work breakdown structure' table | H62: OK
A63: 59 | B63: 4. Project page: milestones, tasks and WBS | C63: 7 | D63: Screenshot caption | E63: Milestones M1 to M5 with progress, deadline, status, billing, Edit and Delete | F63: G4.01–G4.08 | G63: Projects & WBS › All projects › project › WBS tab (/projects/:id/wbs); direct: Projects & WBS › Milestones & billing / WBS — Milestones table (progress, deadline, status, billing, Edit, Delete) | H63: OK | I63: Screenshot 006.
A64: 60 | B64: 4. Project page: milestones, tasks and WBS | C64: 7 | D64: Bullet | E64: Automatic numbers: milestones are numbered M1, M2, M3 in order of creation; tasks inside M2 are 2.1, 2.2, 2.3. | F64: G4.01 | G64: Projects & WBS › All projects › project › WBS tab (/projects/:id/wbs); direct: Projects & WBS › Milestones & billing / WBS — M1, M2… in creation order; tasks 2.1, 2.2… | H64: OK
A65: 61 | B65: 4. Project page: milestones, tasks and WBS | C65: 7 | D65: Bullet (cont.) | E65: Numbers never change and are never reused, so “task 3.4” means the same thing in every conversation. | F65: G4.01 | G65: Projects & WBS › All projects › project › WBS tab (/projects/:id/wbs); direct: Projects & WBS › Milestones & billing / WBS — numbers fixed for good | H65: OK — improved | I65: v6: deleting a milestone or moving a task keeps the task's number (e.g. 4.1 stays 4.1 under 'No milestone').
A66: 62 | B66: 4. Project page: milestones, tasks and WBS | C66: 7 | D66: Bullet | E66: Deadline and end: a milestone’s deadline is the target end of its last task. | F66: G4.02 | G66: Projects & WBS › All projects › project › WBS tab (/projects/:id/wbs); direct: Projects & WBS › Milestones & billing / WBS — Milestones › Deadline = target end of the last task (automatic) | H66: OK
A67: 63 | B67: 4. Project page: milestones, tasks and WBS | C67: 7 | D67: Bullet (cont.) | E67: The baseline shows the original date; red text shows the slip (for example +5d). | F67: G4.02 | G67: Projects & WBS › All projects › project › WBS tab (/projects/:id/wbs); direct: Projects & WBS › Milestones & billing / WBS — Deadline cell: baseline date under it, red slip '+5d' | H67: OK
A68: 64 | B68: 4. Project page: milestones, tasks and WBS | C68: 7 | D68: Bullet | E68: Status: Achieved on time, Achieved late, On track, At risk. | F68: G4.03 | G68: Projects & WBS › All projects › project › WBS tab (/projects/:id/wbs); direct: Projects & WBS › Milestones & billing / WBS — Milestones › Status: Achieved on time / Achieved late / On track / At risk (+ Not started, Overdue) | H68: OK
A69: 65 | B69: 4. Project page: milestones, tasks and WBS | C69: 7 | D69: Bullet | E69: Billing: each milestone carries an amount and a billing state (Not due, Invoiced, Paid). | F69: G4.05 | G69: Projects & WBS › All projects › project › WBS tab (/projects/:id/wbs); direct: Projects & WBS › Milestones & billing / WBS — Milestones › Billing amount + Not due / Invoiced / Paid | H69: OK
A70: 66 | B70: 4. Project page: milestones, tasks and WBS | C70: 7 | D70: Bullet (cont.) | E70: The line below totals paid, invoiced-but-unpaid and achieved-but-not-invoiced. | F70: G4.05 | G70: Projects & WBS › All projects › project › WBS tab (/projects/:id/wbs); direct: Projects & WBS › Milestones & billing / WBS — billing summary line under the table | H70: OK
A71: 67 | B71: 4. Project page: milestones, tasks and WBS | C71: 7 | D71: Bullet | E71: Edit and Delete: change a milestone’s name, dates or billing amount. | F71: G4.06 | G71: Projects & WBS › All projects › project › WBS tab (/projects/:id/wbs); direct: Projects & WBS › Milestones & billing / WBS — Milestone › Edit: name, billing amount; dates while the milestone has no tasks | H71: OK | I71: Once a milestone has tasks its dates follow its last task (the guide's own deadline rule).
A72: 68 | B72: 4. Project page: milestones, tasks and WBS | C72: 7 | D72: Bullet (cont.) | E72: A milestone that has been invoiced cannot be deleted. | F72: G4.06 | G72: Projects & WBS › All projects › project › WBS tab (/projects/:id/wbs); direct: Projects & WBS › Milestones & billing / WBS — Delete locked on invoiced milestones | H72: OK
A73: 69 | B73: 4. Project page: milestones, tasks and WBS | C73: 7 | D73: Bullet (cont.) | E73: Deleting one moves its tasks to “No milestone”. | F73: G4.06 | G73: Projects & WBS › All projects › project › WBS tab (/projects/:id/wbs); direct: Projects & WBS › Milestones & billing / WBS — Delete moves tasks to the 'No milestone' group | H73: OK
A74: 70 | B74: 4. Project page: milestones, tasks and WBS | C74: 7 | D74: Bullet | E74: Auto-cleanup: a milestone with no tasks for 7 days is removed automatically, unless it has been invoiced. | F74: G4.07 | G74: Projects & WBS › All projects › project › WBS tab (/projects/:id/wbs); direct: Projects & WBS › Milestones & billing / WBS — 'no tasks: removed {date}' on empty milestones; auto-removed after 7 days unless invoiced | H74: OK
A75: 71 | B75: 4. Project page: milestones, tasks and WBS | C75: 7 | D75: Bullet | E75: Add milestone: type a name and optional billing amount at the bottom. | F75: G4.08 | G75: Projects & WBS › All projects › project › WBS tab (/projects/:id/wbs); direct: Projects & WBS › Milestones & billing / WBS — inline 'Add milestone' row (name + optional billing amount) | H75: OK
A76: 72 | B76: 4. Project page: milestones, tasks and WBS | C76: 8 | D76: Screenshot caption | E76: Work breakdown structure: tasks grouped by milestone, with owner, effort, dates and a + Task button per milestone | F76: G4.09 | G76: Projects & WBS › All projects › project › WBS tab (/projects/:id/wbs); direct: Projects & WBS › Milestones & billing / WBS — Work breakdown structure with '+ Task' per milestone | H76: OK | I76: Screenshot 007.
A77: 73 | B77: 4. Project page: milestones, tasks and WBS | C77: 8 | D77: Sentence | E77: The Work breakdown structure lists every task under its milestone with its number, owner, effort (estimated vs actual hours), start and planned end, and float (spare days before it delays the project). | F77: G4.09 | G77: Projects & WBS › All projects › project › WBS tab (/projects/:id/wbs); direct: Projects & WBS › Milestones & billing / WBS — columns WBS no., Task, Owner, Effort est/actual, Start, Target end, End, Float to milestone with 'project: Nd' underneath | H77: OK | I77: v6: float cell now also shows 'project: Nd' = working days the task can slip before it delays the project end (the guide's definition); column note explains both.
A78: 74 | B78: 4. Project page: milestones, tasks and WBS | C78: 8 | D78: Sentence | E78: + Task on each milestone adds a task straight into it. | F78: G4.09 | G78: Projects & WBS › All projects › project › WBS tab (/projects/:id/wbs); direct: Projects & WBS › Milestones & billing / WBS — '+ Task' button on each milestone row | H78: OK
A79: 75 | B79: 4. Project page: milestones, tasks and WBS | C79: 8 | D79: Sentence | E79: WBS import: instead of typing, paste rows from a spreadsheet or upload a CSV with the columns Milestone, Task, Owner, Estimated hours, Start, End, Complexity, Depends on, Milestone billing. | F79: G4.10 | G79: Projects & WBS › Import WBS (/delivery/import) or project › Import WBS (/projects/:id/import) — paste or CSV with the 9 columns | H79: OK
A80: 76 | B80: 4. Project page: milestones, tasks and WBS | C80: 8 | D80: Sentence | E80: Download template gives the exact format. | F80: G4.10 | G80: Import WBS — 'Download template' (wbs-template.csv) | H80: OK
A81: 77 | B81: 4. Project page: milestones, tasks and WBS | C81: 8 | D81: Sentence | E81: Preview shows every row and flags errors (unknown owner, bad date, unknown dependency) before anything is saved; the import then saves all rows or none. | F81: G4.10 | G81: Import WBS — preview with row errors (unknown owner, bad date, unknown dependency); saves all or none | H81: OK
A82: 78 | B82: 5. Schedule, critical path and change requests | C82: 9 | D82: Heading | E82: 5. Schedule, critical path and change requests | F82: G5.01–G5.04 | G82: Projects & WBS › All projects › project › Schedule tab (/projects/:id/schedule); direct: Projects & WBS › Schedule & critical path; Projects & WBS › All projects › project › Changes tab (/projects/:id/changes); direct: Projects & WBS › Change requests | H82: OK
A83: 79 | B83: 5. Schedule, critical path and change requests | C83: 9 | D83: Screenshot caption | E83: Schedule: a Gantt chart of tasks by milestone, with today’s line, the baseline and critical dates | F83: G5.01 | G83: Projects & WBS › All projects › project › Schedule tab (/projects/:id/schedule); direct: Projects & WBS › Schedule & critical path — Gantt | H83: OK | I83: Screenshot 008.
A84: 80 | B84: 5. Schedule, critical path and change requests | C84: 9 | D84: Sentence | E84: The Schedule is a Gantt chart: one bar per task, grouped by milestone, placed by date. | F84: G5.01 | G84: Projects & WBS › All projects › project › Schedule tab (/projects/:id/schedule); direct: Projects & WBS › Schedule & critical path — one bar per task, grouped by milestone | H84: OK
A85: 81 | B85: 5. Schedule, critical path and change requests | C85: 9 | D85: Sentence | E85: Critical tasks are red; milestones are marked on their dates; the dashed line is today. | F85: G5.01 | G85: Projects & WBS › All projects › project › Schedule tab (/projects/:id/schedule); direct: Projects & WBS › Schedule & critical path — critical bars red, milestone diamonds, dashed today line, baseline | H85: OK
A86: 82 | B86: 5. Schedule, critical path and change requests | C86: 9 | D86: Sentence | E86: The critical path is the longest chain of dependent tasks to the project end: any delay on it delays the whole project, so those tasks get the most attention. | F86: G5.02 | G86: Projects & WBS › All projects › project › Schedule tab (/projects/:id/schedule); direct: Projects & WBS › Schedule & critical path — 'Critical path: 3.2 › 4.1 › … Ends {date}' | H86: OK | I86: Rules › Critical path now says 'to the project end'.
A87: 83 | B87: 5. Schedule, critical path and change requests | C87: 10 | D87: Screenshot caption | E87: Critical path and breach risks, with actions to update progress, flag, reassign or comment | F87: G5.03 | G87: Projects & WBS › All projects › project › Schedule tab (/projects/:id/schedule); direct: Projects & WBS › Schedule & critical path — 'Critical path and breach risks' | H87: OK | I87: Screenshot 009.
A88: 84 | B88: 5. Schedule, critical path and change requests | C88: 10 | D88: Sentence | E88: The project manager’s Critical path and breach risks list shows each at-risk task, why it is at risk (waiting for another task, falling behind its estimate), and one-click actions: update progress, flag, reassign, or open the thread. | F88: G5.03 | G88: Projects & WBS › All projects › project › Schedule tab (/projects/:id/schedule); direct: Projects & WBS › Schedule & critical path and Dashboard › Project manager — risk list: waiting on / blocks with owners, forecast vs target; Update progress, Flag slip, Reassign, Details and comments (n) | H88: OK — improved | I88: v6: 'Breached' count is the same in the KPI strip and the list. Extra 'Remove' becomes Cancel when hours are logged (intentional).
A89: 85 | B89: 5. Schedule, critical path and change requests | C89: 11 | D89: Screenshot caption | E89: Change requests: raise, approve or reject, with effort and value | F89: G5.04 | G89: Projects & WBS › All projects › project › Changes tab (/projects/:id/changes); direct: Projects & WBS › Change requests | H89: OK | I89: Screenshot 010.
A90: 86 | B90: 5. Schedule, critical path and change requests | C90: 11 | D90: Sentence | E90: Change requests record anything the client adds after signing: title, effort in hours and value. | F90: G5.04 | G90: Projects & WBS › All projects › project › Changes tab (/projects/:id/changes); direct: Projects & WBS › Change requests — Raise change request: title, effort hours, billable value (+ requested by, impact days, note, proposed tasks) | H90: OK
A91: 87 | B91: 5. Schedule, critical path and change requests | C91: 11 | D91: Sentence | E91: Approving one adds its value to the contract and can add its tasks to the WBS. | F91: G5.04 | G91: Projects & WBS › All projects › project › Changes tab (/projects/:id/changes); direct: Projects & WBS › Change requests — Approve (contract goes from X to Y); 'Add its tasks to the WBS' | H91: OK — improved | I91: v6: added tasks start today (or a chosen start) and set the new milestone's deadline.
A92: 88 | B92: 5. Schedule, critical path and change requests | C92: 11 | D92: Sentence | E92: Nothing enters the plan without an approved change request, which protects the margin. | F92: G5.04 | G92: Projects & WBS › All projects › project › Changes tab (/projects/:id/changes); direct: Projects & WBS › Change requests — proposed tasks enter the WBS only after approval | H92: OK
A93: 89 | B93: 6. Costing, allocation and margins | C93: 11 | D93: Heading | E93: 6. Costing, allocation and margins | F93: G6.01–G6.11 | G93: Projects & WBS › All projects › project › Costing & margin tab (/projects/:id/costing); direct: Projects & WBS › Costing & margin | H93: OK | I93: v6: tab renamed from 'Money' to 'Costing & margin'; /money and /margins redirect.
A94: 90 | B94: 6. Costing, allocation and margins | C94: 11 | D94: Sentence | E94: Every project has a cost as well as a price. | F94: G6.03 | G94: Projects & WBS › All projects › project › Costing & margin tab (/projects/:id/costing); direct: Projects & WBS › Costing & margin — 'Costing and margin': Revenue (price) vs Cost | H94: OK
A95: 91 | B95: 6. Costing, allocation and margins | C95: 11 | D95: Sentence | E95: The board works out cost from the people on it and their hourly rate. | F95: G6.02, G6.08 | G95: Projects & WBS › All projects › project › Costing & margin tab (/projects/:id/costing); direct: Projects & WBS › Costing & margin — cost = allocated hours × cost per hour; actual = approved hours × cost per hour | H95: OK — improved | I95: v6: cost loading removed; cost comes only from people and their hourly rate.
A96: 92 | B96: 6. Costing, allocation and margins | C96: 12 | D96: Screenshot caption | E96: Costing and margin: planned, projected and actual; what moved the margin; milestone variance; resources allocated vs logged | F96: G6.03–G6.08 | G96: Projects & WBS › All projects › project › Costing & margin tab (/projects/:id/costing); direct: Projects & WBS › Costing & margin — sections in guide order | H96: OK | I96: Screenshot 011.
A97: 93 | B97: 6. Costing, allocation and margins | C97: 12 | D97: Sentence | E97: Resource allocation by milestone. | F97: G6.01 | G97: Projects & WBS › All projects › project › Costing & margin tab (/projects/:id/costing); direct: Projects & WBS › Costing & margin — 'Resource allocation by milestone' (also Team & allocation tab) | H97: OK — improved | I97: v6: section added to the Costing & margin tab.
A98: 94 | B98: 6. Costing, allocation and margins | C98: 12 | D98: Sentence | E98: Each resource row names a person, the milestone (M1, M2, shown by code), the % of their time, and a from and to date. | F98: G6.01 | G98: Projects & WBS › All projects › project › Costing & margin tab (/projects/:id/costing); direct: Projects & WBS › Costing & margin — allocation rows: Person, Milestone * (M1 code + name), % of time *, From *, To *, working days, hours, cost | H98: OK
A99: 95 | B99: 6. Costing, allocation and margins | C99: 12 | D99: Sentence | E99: All four are required, so cost always lands on a milestone and a period. | F99: G6.01 | G99: Projects & WBS › All projects › project › Costing & margin tab (/projects/:id/costing); direct: Projects & WBS › Costing & margin — allocation dialog: all four fields required ('Choose the milestone (M1, M2…)'); server 422 ALLOC_INVALID | H99: OK | I99: v6: the 'All milestones' option was removed to follow 'all four are required' (listed under intentional differences vs the earlier build).
A100: 96 | B100: 6. Costing, allocation and margins | C100: 13 | D100: Sentence | E100: Cost per hour = monthly salary (CTC) ÷ (working days in the month × minimum hours per day). | F100: G6.02 | G100: Projects & WBS › All projects › project › Costing & margin tab (/projects/:id/costing); direct: Projects & WBS › Costing & margin — formula box under the allocation table; Admin › Team & settings › Cost rates | H100: OK — improved | I100: v6: one formula everywhere: CTC ÷ (working days in the month × minimum hours).
A101: 97 | B101: 6. Costing, allocation and margins | C101: 13 | D101: Sentence | E101: Example: ₹60,000 ÷ (22 × 9) = ₹303 per hour. | F101: G6.02 | G101: Projects & WBS › All projects › project › Costing & margin tab (/projects/:id/costing); direct: Projects & WBS › Costing & margin — example '₹60,000 ÷ (22 × 9) = ₹303' shown; also Rules › Cost per hour | H101: OK
...

Sheet Guide vs build
A1: Feature Guide vs SeereonOS build
A2: One row per Feature Guide item (checklist G1.01–G17.02). Fill in 'Checked by Santosh' (Yes / No / Query) and 'Comments' — the only columns to edit.
A4: Guide section | B4: ID | C4: Guide feature (checklist wording) | D4: Guide page / screenshot reference | E4: In build? | F4: Where in the build (screen / route) | G4: API endpoint | H4: Notes / improvements | I4: Checked by Santosh | J4: Comments
A5: 1. Roles and views | B5: G1.01 | C5: Header: company name, week switcher (prev/next week arrows, "This week" label) that drives the week shown on dashboards/timesheet/scorecard | D5: §1 Roles and views · p.1 · screenshot 000 | E5: Present | F5: Top bar (every page) + left menu — Top bar: company name, week switcher ‹ 28 Sept – 2 Oct › with 'This week'; drives Dashboard, Tasks, Timesheet & log, Weekly scorecard, Pipeline. Menu names now match the guide tabs: Dashboard, Projects & WBS, Tasks, Timesheet & log, Weekly scorecard, Insights, Client view, Team & settings, Rules | G5: ?week= on GET /dashboards/ceo, /dashboards/pm, /dashboards/employee, /scorecard, /timesheets/:week, /sales/summary | H5: v6: menu renamed to the guide's tab names.
A6: 1. Roles and views | B6: G1.02 | C6: Tabs visible per role | D6: §1 Roles and views · p.1 · screenshot 000 | E6: Present | F6: Left menu (v7 groups with submenus), More sheet, phone tab bar — Left menu, More sheet and phone tab bar filtered by permission, using the guide's tab names; every route guarded | G6: GET /me (permissions) | H6: Roles are configurable permissions (9 default roles).
A7: 1. Roles and views | B7: G1.03 | C7: View as (admin): switch to any role, read-only | D7: §1 Roles and views · p.1 · screenshot 000 | E7: Present | F7: Top bar › View as — View as (top bar and More sheet) lists the 9 configurable roles; banner 'Viewing as X — read-only' | G7: GET /roles; X-View-As header; writes refused 403 VIEW_AS_READ_ONLY | H7: Intentional difference: View as offers the 9 configurable roles (guide had 5 fixed roles); read-only as the guide says.
A8: 1. Roles and views | B8: G1.04 | C8: Five dashboard views CEO / PM / Sales / Operations / Employee; each role lands on its own; employee cannot open others; CEO can switch between the 5 dashboards (segmented switch) and CEO dashboard has sub-tabs Overview / Projects / Sales / Finance / Operations | D8: §1 Roles and views · p.1 · screenshot 000 | E8: Present | F8: Dashboard (/home) — Home /home: each person lands on own view; switch CEO · Project manager · Sales · Operations · Employee for people allowed several; CEO sub-tabs Overview / Projects / Sales / Finance / Operations | G8: GET /dashboards/ceo|pm|sales|ops|employee (403 without permission) |
A9: 1. Roles and views | B9: G1.05 | C9: Role matrix: PM sees own projects, tasks, allocation, approves team timesheets, no salaries/payroll/finance (margins only if granted); Sales own leads; Ops register, openings, leave entries; Employee own tasks' status, own timesheet, comments | D9: §1 Roles and views · p.1 · text only (no screenshot) | E9: Present | F9: Admin › Organisation setup › Roles & permissions (/setup/roles) — Default roles: Project Manager = own projects, tasks, allocation, approves team timesheets, no salaries/payroll/finance, margins only with an extra grant; Sales own deals; HR Manager / HR Executive = ops register, openings, leave entries; Employee self-service | G9: permission catalogue; server scoping | H9: Intentional difference: HR Manager can prepare payroll and see the ledger (CEO finalises via maker-checker). Project Manager sees own projects only.
A10: 1. Roles and views | B10: G1.06 | C10: Employee view: person picker (for CEO/PM), "Tagged you" list (mention comments with Open task), "Covering" tasks for colleagues on leave, own numbers: this week's score, on-time delivery, effort ratio, utilisation next 10 working days, + more (open tasks, avg lateness, overdue, etc.) | D10: §1 Roles and views · p.2 · screenshot 001 | E10: Present | F10: Dashboard › Employee (/home) — Employee view (Home → Employee): person picker for CEO/PM; "Tagged you" with Open task; "Covering"; week score, on-time, effort ratio, utilisation next 10 days, open, overdue, average lateness, forecast to breach | G10: GET /dashboards/employee?user=&week=; GET /tasks/mentions |
A11: 2. CEO dashboard: revenue first | B11: G2.01 | C11: Top 4: revenue this month, quarter, FY (Apr–Mar), net earnings FY, each with change arrow vs previous period | D11: §2 CEO dashboard: revenue first · p.3 · screenshot 002 | E11: Present | F11: Dashboard › CEO › Overview (/home) — CEO Overview "Revenue and earnings": revenue month / quarter / FY and net earnings FY, each with change arrow | G11: GET /dashboards/ceo | | H11: v6: month and quarter count only income to date.
A12: 2. CEO dashboard: revenue first | B12: G2.02 | C12: Period table: billed, collected, costs (salaries + expenses), net earnings, net margin, revenue change for month/quarter/FY | D12: §2 CEO dashboard: revenue first · p.3 · screenshot 002 | E12: Present | F12: Dashboard › CEO › Overview (/home) — CEO Overview fixed table This month / This quarter / This FY: billed, collected, costs (salaries + expenses), net earnings, net margin, revenue change | G12: GET /dashboards/ceo | H12: v6: one salary basis, so the dashboard and the P&L agree.
A13: 2. CEO dashboard: revenue first | B13: G2.03 | C13: 12-month chart billed vs collected | D13: §2 CEO dashboard: revenue first · p.3 · screenshot 002 | E13: Present | F13: Dashboard › CEO › Overview (/home) — "Monthly revenue, last 12 months" billed vs collected chart (+ table toggle, export) | G13: GET /dashboards/ceo |
A14: 2. CEO dashboard: revenue first | B14: G2.04 | C14: Revenue by stream (SAP consulting, project milestones/products, services, subscriptions/AMC, AMS) with % share | D14: §2 CEO dashboard: revenue first · p.3 · screenshot 002 | E14: Present | F14: Dashboard › CEO › Overview (/home) — 'Where revenue came from, this financial year': SAP consulting, Products, Services, Subscriptions, AMS with ₹ and % (same names on the P&L) | G14: GET /dashboards/ceo | | H14: v6: stream names match the guide.
A15: 2. CEO dashboard: revenue first | B15: G2.05 | C15: Revenue ahead: milestones billable in 30/60/90 days + weighted sales pipeline | D15: §2 CEO dashboard: revenue first · p.3 · screenshot 002 | E15: Present | F15: Dashboard › CEO › Overview (/home) — "Revenue ahead": milestones billable in 30 / 60 / 90 days + weighted sales pipeline | G15: GET /dashboards/ceo |
A16: 2. CEO dashboard: revenue first | B16: G2.06 | C16: Delivery KPIs: on-time delivery, avg SPI, avg CPI, utilisation next 10 days, active projects in red, open tasks already breached, tasks forecast to breach, tasks done last 4 weeks (vs previous 4), team weekly score | D16: §2 CEO dashboard: revenue first · p.4 · screenshot 003 | E16: Present | F16: Dashboard › CEO › Overview (/home) — 'Delivery': milestones hit on time, SPI, average lateness, overdue tasks, plus CPI, utilisation next 10 days, projects in red, forecast to breach, done last 4 weeks, team weekly score | G16: GET /dashboards/ceo | | H16: v6: added average lateness and overdue tasks.
A17: 2. CEO dashboard: revenue first | B17: G2.07 | C17: Milestones and cash: milestones achieved on time %, achieved-not-invoiced ₹, invoiced-awaiting-payment ₹, billable next 30 days; table of milestones due in 30 days with deadline, forecast, status, billing | D17: §2 CEO dashboard: revenue first · p.4 · screenshot 003 | E17: Present | F17: Dashboard › CEO › Overview (/home) — "Milestones and cash": milestones on time %, achieved not invoiced ₹, invoiced awaiting payment ₹, billable next 30 days; table due in 30 days with deadline, forecast (red when late), status, billing | G17: GET /dashboards/ceo |
A18: 2. CEO dashboard: revenue first | B18: G2.08 | C18: Footnote definitions of revenue / costs / net earnings | D18: §2 CEO dashboard: revenue first · p.3 · screenshot 002 | E18: Present | F18: Dashboard › CEO › Overview (/home) — Footnote defining revenue, costs, net earnings (also in exports) | G18: — |
A19: 3. Projects: list, status, type | B19: G3.01 | C19: Status chips All/Initiated/Active/On hold/NPA/Completed/Closed with counts, filter | D19: §3 Projects: list, status, type · p.4 · screenshot 004 | E19: Present | F19: Projects & WBS › All projects (/projects) — Projects /projects: status chips All / Initiated / Active / On hold / NPA / Completed / Closed with counts | G19: GET /projects |
A20: 3. Projects: list, status, type | B20: G3.02 | C20: Status/health column: health badge (On track/At risk/Off track) + inline status dropdown | D20: §3 Projects: list, status, type · p.4 · screenshot 004 | E20: Present | F20: Projects & WBS › All projects (/projects) — Status column: health badge + inline status dropdown; 'What the statuses mean' popover next to the chips and meanings in the dropdown and reason dialog | G20: POST /projects/:id/status | | H20: v6: status meanings popover added.
A21: 3. Projects: list, status, type | B21: G3.03 | C21: Moving to On hold / NPA / Closed requires reason; status history kept | D21: §3 Projects: list, status, type · p.4 · screenshot 004 | E21: Present | F21: Projects & WBS › All projects (/projects) — Reason required for On hold / NPA / Closed; status history in project Activity tab | G21: POST /projects/:id/status (422 if no reason); GET /projects/:id/activity |
A22: 3. Projects: list, status, type | B22: G3.04 | C22: Columns: PM, commercial model (Fixed / T&M), type, progress (% and x/y tasks), planned end, forecast end (red when late, "+Nd late"/"Nd early"), next milestone (Mx date name), contract value, projected margin | D22: §3 Projects: list, status, type · p.4 · screenshot 004 | E22: Present | F22: Projects & WBS › All projects (/projects) — Columns PM, model ('Fixed price' / 'Time & material') + type, progress, planned end, forecast end, next milestone, contract, projected margin — all fit at 1280 px+ without scrolling | G22: GET /projects (row) | | H22: v6: columns fit without scrolling; 'Fixed price' everywhere.
A23: 3. Projects: list, status, type | B23: G3.05 | C23: Expand row inline (click again to close) | D23: §3 Projects: list, status, type · p.4 · screenshot 004 | E23: Present | F23: Projects & WBS › All projects (/projects) — Row expands inline (click again closes): milestones, PM, dates, open tasks, critical risks, Open project / Client view | G23: GET /projects/:id/summary |
A24: 3. Projects: list, status, type | B24: G3.06 | C24: Project types Product / Service / SaaS / AMS | D24: §3 Projects: list, status, type · p.4 · screenshot 004 | E24: Present | F24: Projects & WBS › All projects (/projects) — Types Product / Service / SaaS / AMS | G24: POST /projects |
A25: 3. Projects: list, status, type | B25: G3.07 | C25: Create project form: name, client, PM, start, planned end, working-days/weekends/holidays summary for the date range, type, commercial model, priority (1..n with labels), auto project code | D25: §3 Projects: list, status, type · p.6 · screenshot 005 | E25: Present | F25: Projects & WBS › Create project (/projects/new) — Create project: name, client, PM, start, planned end, calendar line (calendar days, weekends, holidays named, working days), type, commercial model, priority 1–5 with labels, auto code shown | G25: GET /projects/next-code; POST /projects/costing/preview; POST /projects |
A26: 3. Projects: list, status, type | B26: G3.08 | C26: AUTO MILESTONE SETUP in create form: milestones one per line "name | billing amount" → M1..Mn created in order with billing amounts | D26: §3 Projects: list, status, type · p.6 · screenshot 005 | E26: Present | F26: Projects & WBS › Create project (/projects/new) — AUTO MILESTONE SETUP: "one per line, name | G26: amount" textarea → live M1..Mn preview (bad amounts / duplicates flagged, 3L / 75K shorthand) or "Edit as rows"; deadlines auto-spread over working days until tasks exist | H26: POST /projects (milestones[]) |
A27: 3. Projects: list, status, type | B27: G3.09 | C27: Documents upload in create form (PDF, images, text, CSV up to 20 MB each) | D27: §3 Projects: list, status, type · p.6 · screenshot 005 | E27: Present | F27: Projects & WBS › Create project (/projects/new) — Documents in create form: PDF, images, text, CSV, 20 MB each, multiple → project Documents | G27: POST /projects (documents[]) |
A28: 3. Projects: list, status, type | B28: G3.10 | C28: PROJECT COST CALCULATOR in create form (editors only): Resources rows (resource, milestone or All, alloc %, from*, to* default to milestone dates, working days, man-days, cost/day, cost, remove), same person multiple rows; Additional costs (category, description, amount); Maintenance/support cost; Contingency % of resources+additional; Markup %; Project price (computed both ways); planned margin; totals | D28: §3 Projects: list, status, type · p.6 · screenshot 005 | E28: Present | F28: Projects & WBS › Create project (/projects/new); Projects & WBS › All projects › project › Costing & margin (/projects/:id/costing); direct: Projects & WBS › Costing & margin — Project cost calculator in the create form and on the Costing & margin tab: resources (person, milestone, %, from/to, working days, hours, cost/day, cost), additional costs, maintenance, contingency %, markup ⇄ price, totals and planned margin; cost per hour = CTC ÷ (working days in the month × minimum hours) | G28: POST /projects/costing/preview; POST /projects; PUT /projects/:id/costing | | H28: v6: cost loading removed.
A29: 3. Projects: list, status, type | B29: G3.11 | C29: Cost per day = CTC ÷ average working days per month × (1 + cost loading %); cost loading set in Finance | D29: §3 Projects: list, status, type · p.6 · screenshot 005 | E29: Present | F29: Projects & WBS › Create project (/projects/new) (Project cost calculator); Admin › Team & settings › Cost rates (/settings/cost-rates) — Cost per day = minimum hours × cost per hour, where cost per hour = CTC ÷ (working days in the month × minimum hours); shown in the calculator and on Cost rates | G29: GET /costing/rates; POST /projects/costing/preview | H29: v6: formula changed to the guide's cost per hour; cost loading removed.
A30: 4. Project page: milestones, tasks and WBS | B30: G4.01 | C30: Milestones numbered M1.. in creation order; tasks 2.1, 2.2; numbers never change / never reused | D30: §4 Project page: milestones, tasks and WBS · p.7 · screenshot 006 | E30: Present | F30: Projects & WBS › All projects › project › WBS (/projects/:id/wbs); direct: Projects & WBS › Milestones & billing / WBS — M1.. and 1.1, 1.2 numbering from sequences; a task keeps its number when its milestone is deleted or it moves (4.1 stays 4.1 under 'No milestone') | G30: POST /projects/:id/milestones; POST /projects/:id/tasks | | H30: v6: task numbers survive milestone deletion.
A31: 4. Project page: milestones, tasks and WBS | B31: G4.02 | C31: Milestone deadline = target end of its last task (auto); baseline date shown; slip shown in red (+5d) | D31: §4 Project page: milestones, tasks and WBS · p.7 · screenshot 006 | E31: Present | F31: Projects & WBS › All projects › project › WBS (/projects/:id/wbs); direct: Projects & WBS › Milestones & billing / WBS — Milestone deadline = target end of its last task (automatic), baseline under it, red slip "+Nd"; provisional until tasks exist | G31: syncMilestoneDates; PATCH /milestones/:id refuses manual dates once tasks exist |
A32: 4. Project page: milestones, tasks and WBS | B32: G4.03 | C32: Milestone status: Achieved on time / Achieved late / On track / At risk; End column (actual achieved or forecast) | D32: §4 Project page: milestones, tasks and WBS · p.7 · screenshot 006 | E32: Present | F32: Projects & WBS › All projects › project › WBS (/projects/:id/wbs); direct: Projects & WBS › Milestones & billing / WBS — Milestones table: Status (Achieved on time / Achieved late / On track / At risk, + Overdue / Not started) and End (achieved or forecast) | G32: GET /projects/:id |
A33: 4. Project page: milestones, tasks and WBS | B33: G4.04 | C33: Milestone progress bar %, task count | D33: §4 Project page: milestones, tasks and WBS · p.7 · screenshot 006 | E33: Present | F33: Projects & WBS › All projects › project › WBS (/projects/:id/wbs); direct: Projects & WBS › Milestones & billing / WBS — Progress bar % + N tasks | G33: GET /projects/:id |
A34: 4. Project page: milestones, tasks and WBS | B34: G4.05 | C34: Billing per milestone: amount + state dropdown (Not due / Invoiced / Paid); summary line paid / invoiced-unpaid / achieved-not-invoiced of total | D34: §4 Project page: milestones, tasks and WBS · p.7 · screenshot 006 | E34: Present | F34: Projects & WBS › All projects › project › WBS (/projects/:id/wbs); direct: Projects & WBS › Milestones & billing / WBS — Billing amount + Not due / Invoiced / Paid dropdown (raises invoice / records payment); summary "paid / invoiced and unpaid / achieved not invoiced of total" | G34: POST /milestones/:id/invoice; POST /invoices/:id/payments |
A35: 4. Project page: milestones, tasks and WBS | B35: G4.06 | C35: Edit milestone (name, dates, amount); Delete blocked if invoiced; deleting moves tasks to "No milestone" | D35: §4 Project page: milestones, tasks and WBS · p.7 · screenshot 006 | E35: Present | F35: Projects & WBS › All projects › project › WBS (/projects/:id/wbs); direct: Projects & WBS › Milestones & billing / WBS — Edit (name, amount; dates locked once tasks exist), Delete blocked when invoiced, tasks move to "No milestone" | G35: PATCH / DELETE /milestones/:id | | H35: Dates follow the last task once a milestone has tasks (editable while it has none).
A36: 4. Project page: milestones, tasks and WBS | B36: G4.07 | C36: Auto-cleanup: milestone with no tasks for 7 days removed automatically unless invoiced | D36: §4 Project page: milestones, tasks and WBS · p.7 · screenshot 006 | E36: Present | F36: Projects & WBS › All projects › project › WBS (/projects/:id/wbs); direct: Projects & WBS › Milestones & billing / WBS — Auto-cleanup of milestones with no tasks for 7 days unless invoiced ("no tasks: removed {date}") | G36: sweepMilestones on project, list and dashboard reads; setting projects.empty_milestone_days |
A37: 4. Project page: milestones, tasks and WBS | B37: G4.08 | C37: Add milestone inline: name + optional billing amount | D37: §4 Project page: milestones, tasks and WBS · p.7 · screenshot 006 | E37: Present | F37: Projects & WBS › All projects › project › WBS (/projects/:id/wbs); direct: Projects & WBS › Milestones & billing / WBS — Inline add: name + optional billing amount, no dates needed | G37: POST /projects/:id/milestones |
A38: 4. Project page: milestones, tasks and WBS | B38: G4.09 | C38: WBS table: milestone rows with rollups (done %, effort est/actual, start, target end, end) and +Task per milestone; task rows: number, title, "after x.y" dependencies, owner, done %, effort est/actual, start plan/actual, target end (with revisions), end actual/forecast (green/red), float to milestone; critical tasks marked | D38: §4 Project page: milestones, tasks and WBS · p.8 · screenshot 007 | E38: Present | F38: Projects & WBS › All projects › project › WBS (/projects/:id/wbs); direct: Projects & WBS › Milestones & billing / WBS — WBS table: milestone rollups + '+ Task'; task rows WBS no., title, 'after x.y', owner, stage, done %, effort est/actual, start plan/actual, target end (rev), end actual/forecast, float to milestone with 'project: Nd' (float to project end) underneath; critical rows red | G38: GET /projects/:id | | H38: v6: float cell shows float to milestone plus 'project: Nd' (working days before the project end slips, as the guide defines float).
A39: 4. Project page: milestones, tasks and WBS | B39: G4.10 | C39: WBS import: paste rows or upload CSV (Milestone, Task, Owner, Estimated hours, Start, End, Complexity, Depends on, Milestone billing); template download; preview with row errors (unknown owner, bad date, unknown dependency); all-or-nothing save | D39: §4 Project page: milestones, tasks and WBS · p.6 · text only (no screenshot) | E39: Present | F39: Projects & WBS › Import WBS (/delivery/import); project › Import WBS (/projects/:id/import) — WBS import: paste / CSV, template download, preview with row errors, all-or-nothing | G39: POST /projects/:id/import?mode=preview|commit |
A40: 5. Schedule, critical path and change requests | B40: G5.01 | C40: Gantt: bar per task grouped by milestone, planned vs actual/forecast bars, critical in red, milestone deadline and forecast diamonds, today line, baseline | D40: §5 Schedule, critical path and change requests · p.9 · screenshot 008 | E40: Present | F40: Projects & WBS › All projects › project › Schedule (/projects/:id/schedule); direct: Projects & WBS › Schedule & critical path — Schedule tab Gantt: bars by milestone, planned vs actual/forecast, critical red, deadline & forecast diamonds, today line, baselines, zoom; scrolls inside its card on phones | G40: GET /projects/:id/schedule |
A41: 5. Schedule, critical path and change requests | B41: G5.02 | C41: Critical path text summary (chain with dates, end date) | D41: §5 Schedule, critical path and change requests · p.9 · screenshot 008 | E41: Present | F41: Projects & WBS › All projects › project › Schedule (/projects/:id/schedule); direct: Projects & WBS › Schedule & critical path — "Critical path: 1.1 (dates) › 1.2 … Ends {date}" | G41: GET /projects/:id/schedule |
A42: 5. Schedule, critical path and change requests | B42: G5.03 | C42: Critical path and breach risks list: each at-risk task with status, risk badges (Breached / High risk / Critical), project/milestone/owner/complexity/est/logged/backup, planned vs actual, waiting on / blocks with owners and dates, forecast vs target; actions: status dropdown, Update progress, Flag slip, Reassign, Details and comments (count), Remove | D42: §5 Schedule, critical path and change requests · p.10 · screenshot 009 | E42: Present | F42: Projects & WBS › All projects › project › Schedule (/projects/:id/schedule); direct: Projects & WBS › Schedule & critical path; Dashboard › Project manager — 'Critical path and breach risks' list (Schedule tab and PM dashboard): Breached / High risk / Critical badges (Breached count equals the KPI strip), waiting on / blocks with owners, forecast vs target; stage dropdown, Update progress, Flag slip, Reassign, Details and comments (n), Remove (Cancel when hours are logged) | G42: GET /delivery/risks; POST /tasks/:id/stage|progress|flag-slip|cancel | | H42: Intentional difference: Remove on a task with logged hours becomes Cancel. v6: Breached count consistent.
A43: 5. Schedule, critical path and change requests | B43: G5.04 | C43: Change requests: KPIs raised, awaiting decision, approved extra effort hours, scope growth vs baseline %; CR rows (CR-n title, status, requested by, date, effort, working-days impact, billable value, note); Approve / Reject; approved CR adds value to contract and "Add its tasks to the WBS"; raise CR form | D43: §5 Schedule, critical path and change requests · p.11 · screenshot 010 | E43: Present | F43: Projects & WBS › All projects › project › Changes (/projects/:id/changes); direct: Projects & WBS › Change requests — Changes tab: KPIs, CR-n rows, Approve (adds value to contract) / Reject with reason, 'Add its tasks to the WBS' (tasks start today or a chosen start; the new milestone's deadline follows its last task), raise form | G43: /projects/:id/change-requests; /change-requests/:id/decision|add-tasks | | H43: v6: CR tasks start today.
A44: 6. Costing, allocation and margins | B44: G6.01 | C44: Resource allocation by milestone (person, milestone or All, %, from, to all required) | D44: §6 Costing, allocation and margins · p.12 · screenshot 011 | E44: Present | F44: Projects & WBS › All projects › project › Costing & margin (/projects/:id/costing); direct: Projects & WBS › Costing & margin (Resource allocation by milestone); Team & allocation tab — 'Resource allocation by milestone' section on Costing & margin (and Team & allocation tab): Person, Milestone * (M1 code), % of time *, From *, To * — all required, no 'All milestones' option; server 422 ALLOC_INVALID | G44: POST/PATCH/DELETE /allocations (422 ALLOC_INVALID without milestone); PUT /projects/:id/costing | H44: v6: section added to the Costing & margin tab; 'All milestones' option removed to follow 'all four are required'.
A45: 6. Costing, allocation and margins | B45: G6.02 | C45: Cost per hour = CTC ÷ (working days × min hours) example | D45: §6 Costing, allocation and margins · p.11 · text only (no screenshot) | E45: Present | F45: Projects & WBS › All projects › project › Costing & margin (/projects/:id/costing); direct: Projects & WBS › Costing & margin; Admin › Team & settings › Cost rates; Rules — Cost per hour = CTC ÷ (working days in the month × minimum hours) everywhere (calculator, Costing & margin, Cost rates, Team, Rules); example ₹60,000 ÷ (22 × 9) = ₹303; cost loading removed | G45: GET /cost-rates; GET /costing/rates | H45: v6: cost per hour everywhere; cost loading removed.
A46: 6. Costing, allocation and margins | B46: G6.03 | C46: Costing & margin table: Planned / Projected / Actual to date for revenue, cost, profit, margin (projected revenue incl CRs, actual earned = contract × % complete) | D46: §6 Costing, allocation and margins · p.12 · screenshot 011 | E46: Present | F46: Projects & WBS › All projects › project › Costing & margin (/projects/:id/costing); direct: Projects & WBS › Costing & margin — Costing & margin › 'Costing and margin': Planned / Projected / Actual × revenue, cost, profit, margin, markup, with the guide's 'Three margins' legend (Revenue used / Cost used / Answers). Actual = invoiced amount vs approved hours only | G46: GET /projects/:id/money | | H46: v6: Actual margin = invoiced amount vs approved hours only (was earned value).
A47: 6. Costing, allocation and margins | B47: G6.04 | C47: Margin vs markup shown side by side | D47: §6 Costing, allocation and margins · p.12 · screenshot 011 | E47: Present | F47: Projects & WBS › All projects › project › Costing & margin (/projects/:id/costing); direct: Projects & WBS › Costing & margin — Costing & margin › 'Margin vs markup': guide text and the ₹1,00,000 / ₹1,50,000 example; margin and markup side by side | G47: GET /projects/:id/money |
A48: 6. Costing, allocation and margins | B48: G6.05 | C48: Effort ratio per task, milestone, project; >1.2 flagged | D48: §6 Costing, allocation and margins · p.12 · screenshot 011 | E48: Present | F48: Projects & WBS › All projects › project › Costing & margin (/projects/:id/costing); direct: Projects & WBS › Costing & margin — Costing & margin › 'Effort ratio' = actual ÷ estimated hours per project, milestone and task; above 1.2 flagged red 'Over 1.2' | G48: GET /projects/:id/money | | H48: v6: effort ratio = actual ÷ estimated (was actual ÷ earned).
A49: 6. Costing, allocation and margins | B49: G6.06 | C49: What moved the margin: planned profit, approved CRs, breach cost (people held on late milestones), early-finish saving, projected profit; contingency note (released at close) | D49: §6 Costing, allocation and margins · p.12 · screenshot 011 | E49: Present | F49: Projects & WBS › All projects › project › Costing & margin (/projects/:id/costing); direct: Projects & WBS › Costing & margin — Costing & margin › 'What moved the margin': planned profit → approved CRs, extra hours on late milestones, breach cost, early-finish saving, hours vs allocation → projected profit (adds up exactly); contingency note | G49: GET /projects/:id/money |
A50: 6. Costing, allocation and margins | B50: G6.07 | C50: Milestone variance: deadline, forecast/actual, slip (working days), planned cost, projected cost, change | D50: §6 Costing, allocation and margins · p.12 · screenshot 011 | E50: Present | F50: Projects & WBS › All projects › project › Costing & margin (/projects/:id/costing); direct: Projects & WBS › Costing & margin — Costing & margin › 'Milestone variance': deadline, forecast/actual, slip, planned cost, projected cost, change | G50: GET /projects/:id/money |
A51: 6. Costing, allocation and margins | B51: G6.08 | C51: Resources: allocated vs logged (allocated man-days, allocated to date, logged days to date, allocation used %, planned cost; "unplanned" for people who logged without allocation) | D51: §6 Costing, allocation and margins · p.12 · screenshot 011 | E51: Present | F51: Projects & WBS › All projects › project › Costing & margin (/projects/:id/costing); direct: Projects & WBS › Costing & margin — Costing & margin › 'Resources: allocated vs logged' in hours: planned hours, planned to date, logged (approved) hours, allocation used %, man-days (secondary), planned cost; 'unplanned' rows | G51: GET /projects/:id/money | | H51: v6: shown in hours (was man-days).
A52: 6. Costing, allocation and margins | B52: G6.09 | C52: Planned costing summary (calendar days, weekend days, holidays, working days, total man-days, resource count) + editable resource rows on the project | D52: §6 Costing, allocation and margins · p.12 · screenshot 011 | E52: Present | F52: Projects & WBS › All projects › project › Costing & margin (/projects/:id/costing); direct: Projects & WBS › Costing & margin — Costing & margin › 'Planned costing': calendar, weekend, holiday and working days, hours, resources + editable calculator | G52: GET/PUT /projects/:id/costing
A53: 6. Costing, allocation and margins | B53: G6.10 | C53: CEO profit-margins table across projects: contract, planned margin, projected margin (+pts), actual to date, projected profit, cost to date, projected cost; KPIs contract value, projected gross profit, projected gross margin, actual margin to date; drill into project | D53: §6 Costing, allocation and margins · p.13 · screenshot 012 | E53: Present | F53: Finance › Profit margins (/finance/margins); Projects & WBS › Costing & margin (All projects); Dashboard › CEO › Projects — Finance › Profit margins and Dashboard › CEO › Projects card share one table (contract, planned, projected ±pts, actual = invoiced vs approved hours, projected profit, cost to date, projected cost); row opens the Costing & margin tab | G53: GET /finance/margins |
A54: 6. Costing, allocation and margins | B54: G6.11 | C54: Margins visible only to CEO and margin-permission holders | D54: §6 Costing, allocation and margins · p.13 · screenshot 012 | E54: Present | F54: Finance › Profit margins; Projects & WBS › All projects › project › Costing & margin (/projects/:id/costing); direct: Projects & WBS › Costing & margin — Costing & margin tab and Profit margins only with 'See project margins' (CEO by default); server returns null / 403 otherwise | G54: server checks | | H54: v6: the PM demo user no longer has margins by default.
A55: 7. Tasks: owners, dependencies, backup and threads | B55: G7.01 | C55: Tasks tab with filters by person, project, status | D55: §7 Tasks: owners, dependencies, backup and threads · p.13 · text only (no screenshot) | E55: Present | F55: Tasks › All tasks (/tasks) — Tasks › All tasks (/tasks, page title 'Tasks') for everyone: filters Person, Project, Status (+ Stage sub-filter, search); chips All / Mine / Covering / Tagged me / Overdue / Blocked. v7 (CEO point 5): employees see only tasks they own, cover, back up, review or are tagged on; tasks.view_all (CEO, admin, PM, HR, sales manager) sees every task and filters by employee | G55: GET /tasks | H55: v6: Tasks tab for everyone (was managers only).
A56: 7. Tasks: owners, dependencies, backup and threads | B56: G7.02 | C56: One owner + optional backup; on owner's leave days the task appears in backup's "Covering" list and backup can log time | D56: §7 Tasks: owners, dependencies, backup and threads · p.13 · text only (no screenshot) | E56: Present | F56: Tasks › All tasks (/tasks; task page /tasks/:id) — Row shows owner + backup; task page 'Owner and backup'; Covering chip for the backup when the owner is on leave; 'Log time' opens Timesheet & log with the task row | G56: GET /tasks/:id | H56: v6: full task page /tasks/:id.
A57: 7. Tasks: owners, dependencies, backup and threads | B57: G7.03 | C57: Estimated hours, start, due, complexity (low/medium/high/very high) feeding estimation accuracy | D57: §7 Tasks: owners, dependencies, backup and threads · p.13 · text only (no screenshot) | E57: Present | F57: Tasks › All tasks (/tasks; task page /tasks/:id) — Est. / actual, Start · due, Complexity Low / Medium / High (Very high as an extra) with estimate hint and link to Insights › Estimation accuracy | G57: PATCH /tasks/:id; GET /tasks/estimate-hint |
A58: 7. Tasks: owners, dependencies, backup and threads | B58: G7.04 | C58: Status: New, Selected for development, In development, Unit testing, Functional testing, UAT, Waiting for feedback, On hold, Blocked, Completed (guide summary To do / In progress / Blocked / In review / Done); moving to testing stage raises progress to ≥60/75/90%; progress % | D58: §7 Tasks: owners, dependencies, backup and threads · p.13 · text only (no screenshot) | E58: Present | F58: Tasks › All tasks (/tasks; task page /tasks/:id) — Status To do / In progress / Blocked / In review / Done with 10 detailed stages and progress % underneath; testing stages raise progress to 60 / 75 / 90% | G58: POST /tasks/:id/stage |
A59: 7. Tasks: owners, dependencies, backup and threads | B59: G7.05 | C59: Depends on: cannot start while a dependency is open; names blocking task and owner | D59: §7 Tasks: owners, dependencies, backup and threads · p.13 · text only (no screenshot) | E59: Present | F59: Tasks › All tasks (/tasks; task page /tasks/:id) — 'Depends on' with Add dependency (loops blocked); red 'Blocked by 1.2 — owner Jagannath Nayak'; start refused naming the blocking task and owner | G59: PUT /tasks/:id/dependencies; 409 TASK_BLOCKED / DEP_CYCLE
A60: 7. Tasks: owners, dependencies, backup and threads | B60: G7.06 | C60: Thread comments with @mentions → notification + "Tagged you" on dashboard | D60: §7 Tasks: owners, dependencies, backup and threads · p.13 · text only (no screenshot) | E60: Present | F60: Tasks › All tasks (/tasks; task page /tasks/:id) › Thread; Dashboard › Employee (Tagged you) — Task page 'Thread' with @ autocomplete → notification + 'Tagged you' on Dashboard › Employee and Tasks chip 'Tagged me' | G60: POST /tasks/:id/comments; GET /tasks/mentions |
A61: 7. Tasks: owners, dependencies, backup and threads | B61: G7.07 | C61: Task kind tag e.g. Bug | D61: §7 Tasks: owners, dependencies, backup and threads · p.8 · screenshot 007 | E61: Present | F61: Tasks › All tasks (/tasks; task page /tasks/:id) — Tag badge (Bug, Feature …) on rows and the task page | G61: PATCH /tasks/:id |
A62: 8. Timesheet and daily update | B62: G8.01 | C62: Weekly timesheet Mon–Sat for header week; holidays/weekly offs greyed and labelled | D62: §8 Timesheet and daily update · p.14 · screenshot 013 | E62: Present | F62: My work › Timesheet & log (/timesheet) — Timesheet & log › 'Timesheet' card: Mon–Sat for the header week (Sunday only if a working day); holidays / weekly offs greyed and labelled | G62: GET /timesheets/:week | | H62: Intentional difference: Sunday column shown only if it is a working day.
A63: 8. Timesheet and daily update | B63: G8.02 | C63: Always one empty row; pick task/activity (+ project for activities) + note; new empty row appears; rows with no hours disappear; sections Tasks / Activities | D63: §8 Timesheet and daily update · p.14 · screenshot 013 | E63: Present | F63: My work › Timesheet & log (/timesheet) — Tasks / Activities sections; always one empty row; zero-hour rows removed (also copied rows left at 0 h) | G63: PUT /timesheets/:week |
A64: 8. Timesheet and daily update | B64: G8.03 | C64: Day total vs minimum (9h) with short days highlighted; week summary "logged / target to date / %" | D64: §8 Timesheet and daily update · p.14 · screenshot 013 | E64: Present | F64: My work › Timesheet & log (/timesheet) — Day totals "of 9h", short days red; "This week: Xh logged. Target to date Yh … Z%" | G64: GET /timesheets/:week |
A65: 8. Timesheet and daily update | B65: G8.04 | C65: Quick rows: + Leave or holiday (full day marks leave; half day allowed), + Lunch, tea and stand-up, Copy rows from last week | D65: §8 Timesheet and daily update · p.14 · screenshot 013 | E65: Present | F65: My work › Timesheet & log (/timesheet) — "+ Leave or holiday" (type incl. optional holiday, full/half day), "+ Lunch, tea and stand-up", "Copy rows from last week" | G65: PUT /timesheets/:week; POST /timesheets/:week/copy-previous |
A66: 8. Timesheet and daily update | B66: G8.05 | C66: Save draft; Submit for approval → read-only | D66: §8 Timesheet and daily update · p.14 · screenshot 013 | E66: Present | F66: My work › Timesheet & log (/timesheet) — Save draft; Submit for approval → read-only | G66: PUT / POST submit |
A67: 8. Timesheet and daily update | B67: G8.06 | C67: Weekly lock banner with deadline; locks when week ends; unlock only by manager/CEO for N days after request with reason | D67: §8 Timesheet and daily update · p.14 · screenshot 013 | E67: Present | F67: My work › Timesheet & log (/timesheet) — Banner "submit by Sun, 4 Oct… locks"; lock at week end; unlock request with reason; manager/CEO unlock for N days | G67: /timesheets/:week/unlock-request; /approvals/:id/unlock |
A68: 8. Timesheet and daily update | B68: G8.07 | C68: Task hours become actual hours and cost | D68: §8 Timesheet and daily update · p.14 · screenshot 013 | E68: Present | F68: My work › Timesheet & log (/timesheet) — Task hours become actual hours and cost (WBS, margins, payroll) | G68: taskActuals / costedEntries |
A69: 8. Timesheet and daily update | B69: G8.08 | C69: End-of-day update: date, what I finished, proof link (required), blockers | D69: §8 Timesheet and daily update · p.15 · screenshot 014 | E69: Present | F69: My work › Timesheet & log (/timesheet) › End-of-day update — Timesheet & log › 'End-of-day update' below the timesheet: Date, What I finished, Proof link (required), Blockers; /daily opens this section | G69: POST /daily | H69: v6: End-of-day update moved onto Timesheet & log.
A70: 8. Timesheet and daily update | B70: G8.09 | C70: Friday demo: showed working software checkbox + what was demoed | D70: §8 Timesheet and daily update · p.15 · screenshot 014 | E70: Present | F70: My work › Timesheet & log (/timesheet) › Friday demo — Timesheet & log › 'Friday demo': Showed working software to the team + What was demoed | G70: POST /daily/demo | | H70: v6: Friday demo moved onto Timesheet & log.
A71: 9. Approvals and the manager's approval KPI | B71: G9.01 | C71: Submitted weeks go to reports-to manager; 2 working-day deadline (setting) | D71: §9 Approvals and the manager's approval KPI · p.16 · screenshot 015 | E71: Present | F71: Tasks › Timesheet approvals (/approvals) — Submitted week → reports-to manager; deadline setting (2 working days) | G71: submitWeek; GET /approvals |
A72: 9. Approvals and the manager's approval KPI | B72: G9.02 | C72: KPI strip: approvals on time last 30 days %, approval lapses (negative KPI), overdue now, waiting within deadline | D72: §9 Approvals and the manager's approval KPI · p.16 · screenshot 015 | E72: Present | F72: Tasks › Timesheet approvals (/approvals) — Approvals KPI strip: on time last 30 days %, approval lapses (negative KPI), overdue now, waiting within deadline | G72: GET /approvals (kpi) |
A73: 9. Approvals and the manager's approval KPI | B73: G9.03 | C73: Waiting list: person, submitted date, week, hours by day (short days red), total + short-day count, due by (overdue red), Approve, Reject with reason inline | D73: §9 Approvals and the manager's approval KPI · p.16 · screenshot 015 | E73: Present | F73: Tasks › Timesheet approvals (/approvals) — Waiting list: person, submitted, week, hours by day (short red), total + short days, due by (overdue red), Approve, inline reject reason | G73: GET /approvals; POST approve / reject |
A74: 9. Approvals and the manager's approval KPI | B74: G9.04 | C74: My team's timesheets: 4 weeks per person coloured by status (Approved/Submitted/Locked/Draft), Unlock action | D74: §9 Approvals and the manager's approval KPI · p.16 · screenshot 015 | E74: Present | F74: Tasks › Timesheet approvals (/approvals) — My team's timesheets: 4 weeks per person, status chips, Unlock | G74: GET /approvals/team; POST unlock |
A75: 9. Approvals and the manager's approval KPI | B75: G9.05 | C75: Delegation of approvals for a date range; delegate's approvals count to delegate's KPI | D75: §9 Approvals and the manager's approval KPI · p.29 · screenshot 034 | E75: Present | F75: Admin › Team & settings › Delegations (/settings/delegations) — Delegations for a date range; approvals credited to the delegate's KPI | G75: /delegations; approvalKpis | H75: Intentional difference: one-project delegations hand over task follow-ups only.
A76: 9. Approvals and the manager's approval KPI | B76: G9.06 | C76: Top person (no manager) auto-approved | D76: §9 Approvals and the manager's approval KPI · p.16 · screenshot 015 | E76: Present | F76: My work › Timesheet & log (/timesheet) (auto-approved on submit) — Top person auto-approved | G76: submitWeek |
A77: 10. Payroll: pay for approved days | B77: G10.01 | C77: Month picker + Calculate/Recalculate | D77: §10 Payroll: pay for approved days · p.17 · screenshot 016 | E77: Present | F77: Finance › Payroll (/payroll) — Payroll /payroll: month picker, Calculate / Recalculate | G77: /payroll/run; /payroll/:id/recompute | | H77: Intentional difference: payroll is open to the HR Manager role too (prepare); CEO finalises.
A78: 10. Payroll: pay for approved days | B78: G10.02 | C78: KPIs: monthly CTC all staff, deductions (unapproved days, LWP days), sales variable earned, net payable | D78: §10 Payroll: pay for approved days · p.17 · screenshot 016 | E78: Present | F78: Finance › Payroll (/payroll) — KPIs: monthly CTC all staff, deductions (pending + not approved + LWP days), sales variable earned, net payable | G78: GET /payroll/:id |
A79: 10. Payroll: pay for approved days | B79: G10.03 | C79: Per person: working days, approved, pending, not approved, LWP, CTC, base, deduction, variable, net payable, approver name / self-approves | D79: §10 Payroll: pay for approved days · p.17 · screenshot 016 | E79: Present | F79: Finance › Payroll (/payroll) — Per person: approver / self-approves, working days, approved, pending, not approved, LWP, CTC / base, deduction, variable, net payable — all columns fit at 1440 px | G79: GET /payroll/:id |
A80: 10. Payroll: pay for approved days | B80: G10.04 | C80: Deduction = base ÷ working days × (unapproved + LWP) | D80: §10 Payroll: pay for approved days · p.17 · screenshot 016 | E80: Present | F80: Finance › Payroll (/payroll) — Deduction = base ÷ working days × (pending + not approved + LWP days), as the guide's 'unapproved days'; footnote and payslip use the guide's wording | G80: computeLines | | H80: v6: pending days deducted as the guide says.
A81: 10. Payroll: pay for approved days | B81: G10.05 | C81: Sales variable only when month target met | D81: §10 Payroll: pay for approved days · p.17 · screenshot 016 | E81: Present | F81: Finance › Payroll (/payroll) — Sales variable only when the month's target is met | G81: salesCompensation |
A82: 10. Payroll: pay for approved days | B82: G10.06 | C82: Flag people with unsubmitted/unapproved weeks before paying | D82: §10 Payroll: pay for approved days · p.17 · screenshot 016 | E82: Present | F82: Finance › Payroll (/payroll) — 'Chase before you pay' list incl. 'N pending days deducted — chase first'; deactivated people excluded | G82: GET /payroll/:id | | H82: v6: pending weeks counted; deactivated people excluded.
A83: 10. Payroll: pay for approved days | B83: G10.07 | C83: CSV export for bank/accountant | D83: §10 Payroll: pay for approved days · p.17 · screenshot 016 | E83: Present | F83: Finance › Payroll (/payroll) — CSV for the bank (name, employee code, net pay) + full CSV / Excel / PDF | G83: client export |
A84: 10. Payroll: pay for approved days | B84: G10.08 | C84: Deduct-unapproved-days is a company setting (off by default for new tenants); PF/ESI/TDS out of scope | D84: §10 Payroll: pay for approved days · p.16 · text only (no screenshot) | E84: Present | F84: Admin › Team & settings › Company & rules › Pay — Deduct unapproved days is a company setting, off for new companies; PF / ESI / TDS out of scope | G84: settings | | H84: Company setting, off for new tenants; on for Seereon.
A85: 11. Sales: leads, pipeline and the activity trail | B85: G11.01 | C85: New lead form: opportunity, company/school, contact, phone, email, product, source (referral, BNI, website, cold call, event, partner), owner, stage, one-time value, recurring ₹/month, expected close, next step + by date, how the lead came in | D85: §11 Sales: leads, pipeline and the activity trail · p.18 · screenshot 017 | E85: Present | F85: Sales › Pipeline (/sales) — New lead form with every field incl. how the lead came in / first conversation | G85: POST /sales/deals |
A86: 11. Sales: leads, pipeline and the activity trail | B86: G11.02 | C86: Pipeline KPIs: open pipeline (n deals), weighted pipeline, won this quarter (n), forecast to close this quarter, win rate last 180 days, avg deal size (won), median sales cycle, recurring revenue won per month, new leads this month, activities this week, follow-ups overdue, deals no activity 14 days | D86: §11 Sales: leads, pipeline and the activity trail · p.18 · screenshot 018 | E86: Present | F86: Sales › Pipeline (/sales) — Pipeline KPIs incl. open value, weighted, win rate, 'Average days to close' (+ median) and the other guide KPIs | G86: GET /sales/summary | | H86: v6: 'Average days to close' added.
A87: 11. Sales: leads, pipeline and the activity trail | B87: G11.03 | C87: Funnel by stage Lead/Qualified/Demo done/Proposal sent/Negotiation/Won (+Lost) with value and count | D87: §11 Sales: leads, pipeline and the activity trail · p.18 · screenshot 018 | E87: Present | F87: Sales › Pipeline (/sales) — Funnel Lead / Qualified / Demo / Proposal / Negotiation / Won / Lost with ₹ and counts (same stage names everywhere) | G87: GET /sales/summary | | H87: v6: stage names Demo / Proposal as in the guide.
A88: 11. Sales: leads, pipeline and the activity trail | B88: G11.04 | C88: Lost requires reason; Won records date and can create project | D88: §11 Sales: leads, pipeline and the activity trail · p.18 · screenshot 018 | E88: Present | F88: Sales › Pipeline (/sales) — Lost needs a reason; Won records the date (history 'Qualified → Won') and offers Create project | G88: POST /sales/deals/:id/stage; /create-project | | H88: v6: stage history fixed.
A89: 11. Sales: leads, pipeline and the activity trail | B89: G11.05 | C89: Activity log last 30 days filterable by person: date, who, deal (+company), what (email/WhatsApp/call/stage/meeting/new lead), detail | D89: §11 Sales: leads, pipeline and the activity trail · p.19 · screenshot 019 | E89: Present | F89: Sales › Activity log (/sales/activity) — Activity log /sales/activity: 7 / 30 / 90 days, person filter, date, who, deal, what (incl. WhatsApp, stage changes, new lead), detail; export | G89: GET /sales/activity |
A90: 11. Sales: leads, pipeline and the activity trail | B90: G11.06 | C90: Stale deal flag after 14 days without activity | D90: §11 Sales: leads, pipeline and the activity trail · p.18 · screenshot 018 | E90: Present | F90: Sales › Pipeline (/sales) — Stale flag after 14 days (setting) + notification | G90: GET /sales/deals |
A91: 11. Sales: leads, pipeline and the activity trail | B91: G11.07 | C91: Every deal traceable: created by, stage history, activities | D91: §11 Sales: leads, pipeline and the activity trail · p.19 · screenshot 019 | E91: Present | F91: Sales › Pipeline › deal page (/sales/:id) — Deal page: created by, stage history and activities timeline | G91: GET /sales/deals/:id |
A92: 12. Sales cost, performance and pay | B92: G12.01 | C92: Month / Quarter / Year switch + period picker | D92: §12 Sales cost, performance and pay · p.20 · screenshot 020 | E92: Present | F92: Sales › Compensation (/sales/compensation) — Month / Quarter / Year switch + period picker (Compensation and Performance) | G92: GET /sales/compensation; /sales/performance |
A93: 12. Sales cost, performance and pay | B93: G12.02 | C93: KPIs: sales salaries (people), deals closed, closed ÷ salary cost %, payout (base + variable earned) | D93: §12 Sales cost, performance and pay · p.20 · screenshot 020 | E93: Present | F93: Sales › Compensation (/sales/compensation) — KPIs: Sales cost (= base + variable earned), deals closed, ₹ of sales per ₹1 of sales cost (×), payout | G93: GET /sales/compensation | | H93: v6: sales cost = base + variable earned (was CTC).
A94: 12. Sales cost, performance and pay | B94: G12.03 | C94: Per salesperson: CTC in period, variable % (editable), monthly target (editable, default CTC), target in period, closed (deals won listed), achieved %, variable earned, payout, Save; Team total row | D94: §12 Sales cost, performance and pay · p.20 · screenshot 020 | E94: Present | F94: Sales › Compensation (/sales/compensation) — Per salesperson: CTC in period, variable % and monthly target (defaults to CTC) editable with Save (maker-checked), target, closed deals listed, achieved %, variable earned, sales cost; Team row | G94: GET /sales/compensation; POST /cost-rates | | H94: Variable % and target edits go through maker-checker. v6: target defaults to CTC (seed fixed).
A95: 12. Sales cost, performance and pay | B95: G12.04 | C95: Variable only at 100% target (month by month; quarter/year = sum of monthly) | D95: §12 Sales cost, performance and pay · p.20 · screenshot 020 | E95: Present | F95: Sales › Compensation (/sales/compensation) — Variable month by month at 100% of target; quarter / year = sum of monthly payouts | G95: compFor |
A96: 12. Sales cost, performance and pay | B96: G12.05 | C96: Trend by month: sales salary cost, payout, deals closed, closed ÷ salary | D96: §12 Sales cost, performance and pay · p.20 · screenshot 020 | E96: Present | F96: Sales › Compensation (/sales/compensation) — Trend by month: sales cost (base + variable earned) against deals closed | G96: GET /sales/compensation |
A97: 12. Sales cost, performance and pay | B97: G12.06 | C97: Deal value = one-time + 12 × recurring | D97: §12 Sales cost, performance and pay · p.20 · screenshot 020 | E97: Present | F97: Sales › Compensation (/sales/compensation) — Deal value = one-time + 12 × monthly recurring everywhere (pipeline, targets, payroll, dashboards) | G97: dealValue() |
A98: 12. Sales cost, performance and pay | B98: G12.07 | C98: Salesperson performance table: activities, calls, meetings, demos, proposals, new leads, won (value), lost, win rate, avg deal, sales cycle, open pipeline | D98: §12 Sales cost, performance and pay · p.21 · screenshot 021 | E98: Present | F98: Sales › Performance (/sales/performance) — Salesperson performance: activities, calls, meetings, demos, proposals, new leads, won, lost, win rate, avg deal, cycle, open pipeline | G98: GET /sales/performance |
A99: 12. Sales cost, performance and pay | B99: G12.08 | C99: Last 6 months per person: activities, new leads, deals closed bar, target, achieved, variable earned | D99: §12 Sales cost, performance and pay · p.21 · screenshot 021 | E99: Present | F99: Sales › Performance (/sales/performance) — Last 6 months per person: activities, new leads, deals closed, target, achieved, variable | G99: GET /sales/performance |
A100: 13. Finance: P&L and ledger | B100: G13.01 | C100: Monthly P&L last 6 months: billed, collected, payroll, other costs, net | D100: §13 Finance: P&L and ledger · p.21 · screenshot 022 | E100: Present | F100: Finance › Profit & loss (/finance/pnl) — Finance › Profit & loss opens with 'Monthly P&L, last 6 months' (billed, collected, payroll, other costs, net); current month to date only | G100: GET /finance/pnl | | H100: v6: monthly table moved to the top.
A101: 13. Finance: P&L and ledger | B101: G13.02 | C101: Ledger: income/expense entries outside milestones with category, amount, recurring monthly until end date, status (received / awaiting payment), Remove, Add entry | D101: §13 Finance: P&L and ledger · p.22 · screenshot 023 | E101: Present | F101: Finance › Ledger (/finance/ledger) — Ledger: income / expense entries, recurring monthly until end date, status, Remove, Add an entry | G101: /finance/ledger |
...

Sheet Build feature list
A1: SeereonOS build — complete feature list
A2: Every live feature in the build. Source = Feature Guide (with G-ID) or Additional (layer it came from). Planned catalogue processes are not listed. Default roles: Administrator, CEO, CTO, Project Manager, HR Manager, HR Executive, Sales Manager, Sales Executive, Employee.
A4: # | B4: Area | C4: Feature | D4: Screen / route | E4: Who can use it (default roles) | F4: Source | G4: Process catalogue IDs | H4: Status
A5: 1 | B5: Dashboards | C5: Five role dashboards with CEO switch and sub-tabs | D5: Dashboard (/home) | E5: Everyone (own data) | F5: Feature Guide (G1.04) | G5: ANA-01, ANA-03 | H5: Live
A6: 2 | B6: Dashboards | C6: Employee view: Tagged you, Covering, own numbers | D6: Dashboard › Employee (/home) | E6: Everyone (own data) | F6: Feature Guide (G1.06) | G6: ANA-05 | H6: Live
A7: 3 | B7: Dashboards | C7: Top 4 revenue and net earnings tiles | D7: Dashboard › CEO › Overview (/home) | E7: Administrator, CEO | F7: Feature Guide (G2.01) | H7: Live
A8: 4 | B8: Dashboards | C8: Period table: billed, collected, costs, net, margin | D8: Dashboard › CEO › Overview (/home) | E8: Administrator, CEO | F8: Feature Guide (G2.02) | H8: Live
A9: 5 | B9: Dashboards | C9: 12-month billed vs collected chart | D9: Dashboard › CEO › Overview (/home) | E9: Administrator, CEO | F9: Feature Guide (G2.03) | H9: Live
A10: 6 | B10: Dashboards | C10: Revenue by stream with % share | D10: Dashboard › CEO › Overview (/home) | E10: Administrator, CEO | F10: Feature Guide (G2.04) | H10: Live
A11: 7 | B11: Dashboards | C11: Revenue ahead (30/60/90 days + weighted pipeline) | D11: Dashboard › CEO › Overview (/home) | E11: Administrator, CEO | F11: Feature Guide (G2.05) | H11: Live
A12: 8 | B12: Dashboards | C12: Delivery KPIs (on-time, SPI, CPI, utilisation…) | D12: Dashboard › CEO › Overview (/home) | E12: Administrator, CEO | F12: Feature Guide (G2.06) | H12: Live
A13: 9 | B13: Dashboards | C13: Milestones and cash | D13: Dashboard › CEO › Overview (/home) | E13: Administrator, CEO | F13: Feature Guide (G2.07) | H13: Live
A14: 10 | B14: Dashboards | C14: Footnote definitions of revenue, costs, net earnings | D14: Dashboard › CEO › Overview (/home) | E14: Administrator, CEO | F14: Feature Guide (G2.08) | H14: Live
A15: 11 | B15: Dashboards | C15: PM delivery control KPIs | D15: Dashboard › Project manager (/home) | E15: Administrator, CEO, CTO, Project Manager | F15: Feature Guide (G14.01) | G15: ANA-02 | H15: Live
A16: 12 | B16: Dashboards | C16: Task pipeline chart | D16: Dashboard › Project manager (/home) | E16: Administrator, CEO, CTO, Project Manager | F16: Feature Guide (G14.02) | H16: Live
A17: 13 | B17: Dashboards | C17: Resource load next 10 working days | D17: Dashboard › Project manager (/home) | E17: Administrator, CEO, CTO, Project Manager | F17: Feature Guide (G14.03) | H17: Live
A18: 14 | B18: Dashboards | C18: HR & operations home: on leave today, compliance calendar (60 days), openings, payroll | D18: /home → Operations | E18: Administrator, CEO, HR Manager, HR Executive | F18: Additional (v1 base) | G18: ANA-04 | H18: Live
A19: 15 | B19: Dashboards | C19: Persona-based home: CTO, HR and other default roles land on the right dashboard | D19: /home | E19: Everyone (own data) | F19: Additional (v4 access & controls) | G19: ACC-09 | H19: Live
A20: 16 | B20: Projects & delivery | C20: Project status chips with counts | D20: Projects & WBS › All projects (/projects) | E20: All roles (own projects); full: Administrator, CEO, CTO, HR Manager | F20: Feature Guide (G3.01) | H20: Live
A21: 17 | B21: Projects & delivery | C21: Health badge and inline status dropdown | D21: Projects & WBS › All projects (/projects) | E21: Administrator, CEO, CTO, Project Manager | F21: Feature Guide (G3.02) | H21: Live
A22: 18 | B22: Projects & delivery | C22: Reason required for On hold / NPA / Closed; status history | D22: Projects & WBS › All projects (/projects) | E22: Administrator, CEO, CTO, Project Manager | F22: Feature Guide (G3.03) | G22: DEL-07, DEL-11 | H22: Live
A23: 19 | B23: Projects & delivery | C23: Projects list columns (PM, model, progress, forecast, margin…) | D23: Projects & WBS › All projects (/projects) | E23: All roles (own projects); full: Administrator, CEO, CTO, HR Manager | F23: Feature Guide (G3.04) | H23: Live
A24: 20 | B24: Projects & delivery | C24: Inline row expand | D24: Projects & WBS › All projects (/projects) | E24: All roles (own projects); full: Administrator, CEO, CTO, HR Manager | F24: Feature Guide (G3.05) | H24: Live
A25: 21 | B25: Projects & delivery | C25: Project types Product / Service / SaaS / AMS | D25: Projects & WBS › All projects (/projects) | E25: Administrator, CEO, CTO, Project Manager | F25: Feature Guide (G3.06) | H25: Live
A26: 22 | B26: Projects & delivery | C26: Create project form with calendar summary and auto code | D26: Projects & WBS › Create project (/projects/new) | E26: Administrator, CEO, CTO, Project Manager | F26: Feature Guide (G3.07) | G26: DEL-01 | H26: Live
A27: 23 | B27: Projects & delivery | C27: Auto milestone setup (name | amount per line) | D27: Projects & WBS › Create project (/projects/new) | E27: Administrator, CEO, CTO, Project Manager | F27: Feature Guide (G3.08) | H27: Live
A28: 24 | B28: Projects & delivery | C28: Documents upload in create form | D28: Projects & WBS › Create project (/projects/new) | E28: Administrator, CEO, CTO, Project Manager | F28: Feature Guide (G3.09) | H28: Live
A29: 25 | B29: Projects & delivery | C29: Project cost calculator | D29: Projects & WBS › Create project (/projects/new); Projects & WBS › All projects › project › Costing & margin (/projects/:id/costing); direct: Projects & WBS › Costing & margin | E29: Administrator, CEO, CTO, Project Manager | F29: Feature Guide (G3.10) | H29: Live
A30: 26 | B30: Projects & delivery | C30: Cost per day from cost per hour | D30: Projects & WBS › Create project (/projects/new) (Project cost calculator); Admin › Team & settings › Cost rates (/settings/cost-rates) | E30: Administrator, CEO | F30: Feature Guide (G3.11) | H30: Live
A31: 27 | B31: Projects & delivery | C31: Permanent milestone and task numbering | D31: Projects & WBS › All projects › project › WBS (/projects/:id/wbs); direct: Projects & WBS › Milestones & billing / WBS | E31: Edit: Administrator, CEO, CTO, Project Manager; view: project team | F31: Feature Guide (G4.01) | H31: Live
A32: 28 | B32: Projects & delivery | C32: Milestone deadline from last task, baseline and slip | D32: Projects & WBS › All projects › project › WBS (/projects/:id/wbs); direct: Projects & WBS › Milestones & billing / WBS | E32: Edit: Administrator, CEO, CTO, Project Manager; view: project team | F32: Feature Guide (G4.02) | G32: DEL-02 | H32: Live
A33: 29 | B33: Projects & delivery | C33: Milestone status and End column | D33: Projects & WBS › All projects › project › WBS (/projects/:id/wbs); direct: Projects & WBS › Milestones & billing / WBS | E33: Edit: Administrator, CEO, CTO, Project Manager; view: project team | F33: Feature Guide (G4.03) | H33: Live
A34: 30 | B34: Projects & delivery | C34: Milestone progress bar and task count | D34: Projects & WBS › All projects › project › WBS (/projects/:id/wbs); direct: Projects & WBS › Milestones & billing / WBS | E34: Edit: Administrator, CEO, CTO, Project Manager; view: project team | F34: Feature Guide (G4.04) | H34: Live
A35: 31 | B35: Projects & delivery | C35: Milestone billing state and billing summary | D35: Projects & WBS › All projects › project › WBS (/projects/:id/wbs); direct: Projects & WBS › Milestones & billing / WBS | E35: Edit: Administrator, CEO, CTO, Project Manager; view: project team | F35: Feature Guide (G4.05) | G35: FIN-01 | H35: Live
A36: 32 | B36: Projects & delivery | C36: Edit / delete milestone (blocked if invoiced) | D36: Projects & WBS › All projects › project › WBS (/projects/:id/wbs); direct: Projects & WBS › Milestones & billing / WBS | E36: Edit: Administrator, CEO, CTO, Project Manager; view: project team | F36: Feature Guide (G4.06) | H36: Live
A37: 33 | B37: Projects & delivery | C37: Auto-cleanup of empty milestones after 7 days | D37: Projects & WBS › All projects › project › WBS (/projects/:id/wbs); direct: Projects & WBS › Milestones & billing / WBS | E37: Edit: Administrator, CEO, CTO, Project Manager; view: project team | F37: Feature Guide (G4.07) | H37: Live
A38: 34 | B38: Projects & delivery | C38: Inline add milestone | D38: Projects & WBS › All projects › project › WBS (/projects/:id/wbs); direct: Projects & WBS › Milestones & billing / WBS | E38: Edit: Administrator, CEO, CTO, Project Manager; view: project team | F38: Feature Guide (G4.08) | H38: Live
A39: 35 | B39: Projects & delivery | C39: WBS table with rollups, dependencies, float, critical rows | D39: Projects & WBS › All projects › project › WBS (/projects/:id/wbs); direct: Projects & WBS › Milestones & billing / WBS | E39: Edit: Administrator, CEO, CTO, Project Manager; view: project team | F39: Feature Guide (G4.09) | G39: DEL-03 | H39: Live
A40: 36 | B40: Projects & delivery | C40: WBS import (paste / CSV) with preview | D40: Projects & WBS › Import WBS (/delivery/import); project › Import WBS (/projects/:id/import) | E40: Edit: Administrator, CEO, CTO, Project Manager; view: project team | F40: Feature Guide (G4.10) | G40: DEL-04 | H40: Live
A41: 37 | B41: Projects & delivery | C41: Gantt chart | D41: Projects & WBS › All projects › project › Schedule (/projects/:id/schedule); direct: Projects & WBS › Schedule & critical path | E41: All roles (project team); full: Administrator, CEO, CTO, HR Manager | F41: Feature Guide (G5.01) | G41: DEL-06 | H41: Live
A42: 38 | B42: Projects & delivery | C42: Critical path text summary | D42: Projects & WBS › All projects › project › Schedule (/projects/:id/schedule); direct: Projects & WBS › Schedule & critical path | E42: All roles (project team); full: Administrator, CEO, CTO, HR Manager | F42: Feature Guide (G5.02) | H42: Live
A43: 39 | B43: Projects & delivery | C43: Critical path and breach risks list with actions | D43: Projects & WBS › All projects › project › Schedule (/projects/:id/schedule); direct: Projects & WBS › Schedule & critical path; Dashboard › Project manager | E43: Administrator, CEO, CTO, Project Manager | F43: Feature Guide (G5.03) | H43: Live
A44: 40 | B44: Projects & delivery | C44: Change requests with KPIs, approve / reject, add tasks to WBS | D44: Projects & WBS › All projects › project › Changes (/projects/:id/changes); direct: Projects & WBS › Change requests | E44: Administrator, CEO, CTO, Project Manager | F44: Feature Guide (G5.04) | G44: DEL-08 | H44: Live
A45: 41 | B45: Projects & delivery | C45: Resource allocation by milestone | D45: Projects & WBS › All projects › project › Costing & margin (/projects/:id/costing); direct: Projects & WBS › Costing & margin (Resource allocation by milestone); Team & allocation tab | E45: Administrator, CEO, CTO, Project Manager | F45: Feature Guide (G6.01) | G45: DEL-05 | H45: Live
A46: 42 | B46: Projects & delivery | C46: Cost per hour formula | D46: Projects & WBS › All projects › project › Costing & margin (/projects/:id/costing); direct: Projects & WBS › Costing & margin; Admin › Team & settings › Cost rates; Rules | E46: Administrator, CEO, HR Manager | F46: Feature Guide (G6.02) | G46: ORG-03 | H46: Live
A47: 43 | B47: Projects & delivery | C47: Costing & margin: planned / projected / actual | D47: Projects & WBS › All projects › project › Costing & margin (/projects/:id/costing); direct: Projects & WBS › Costing & margin | E47: Administrator, CEO, CTO | F47: Feature Guide (G6.03) | G47: DEL-09 | H47: Live
A48: 44 | B48: Projects & delivery | C48: Margin vs markup side by side | D48: Projects & WBS › All projects › project › Costing & margin (/projects/:id/costing); direct: Projects & WBS › Costing & margin | E48: Administrator, CEO, CTO | F48: Feature Guide (G6.04) | H48: Live
A49: 45 | B49: Projects & delivery | C49: Effort ratio per task, milestone, project | D49: Projects & WBS › All projects › project › Costing & margin (/projects/:id/costing); direct: Projects & WBS › Costing & margin | E49: Administrator, CEO, CTO | F49: Feature Guide (G6.05) | H49: Live
A50: 46 | B50: Projects & delivery | C50: What moved the margin | D50: Projects & WBS › All projects › project › Costing & margin (/projects/:id/costing); direct: Projects & WBS › Costing & margin | E50: Administrator, CEO, CTO | F50: Feature Guide (G6.06) | H50: Live
A51: 47 | B51: Projects & delivery | C51: Milestone variance | D51: Projects & WBS › All projects › project › Costing & margin (/projects/:id/costing); direct: Projects & WBS › Costing & margin | E51: Administrator, CEO, CTO | F51: Feature Guide (G6.07) | H51: Live
A52: 48 | B52: Projects & delivery | C52: Resources: allocated vs logged | D52: Projects & WBS › All projects › project › Costing & margin (/projects/:id/costing); direct: Projects & WBS › Costing & margin | E52: Administrator, CEO, CTO | F52: Feature Guide (G6.08) | H52: Live
A53: 49 | B53: Projects & delivery | C53: Planned costing summary with editable resources | D53: Projects & WBS › All projects › project › Costing & margin (/projects/:id/costing); direct: Projects & WBS › Costing & margin | E53: Administrator, CEO, CTO | F53: Feature Guide (G6.09) | H53: Live
A54: 50 | B54: Projects & delivery | C54: Margins visible only with margin permission | D54: Finance › Profit margins; Projects & WBS › All projects › project › Costing & margin (/projects/:id/costing); direct: Projects & WBS › Costing & margin | E54: Administrator, CEO, CTO | F54: Feature Guide (G6.11) | H54: Live
A55: 51 | B55: Projects & delivery | C55: Client view report | D55: Projects & WBS › Client view (/client-view; /projects/:id/client-view) | E55: Administrator, CEO, CTO, Project Manager, HR Manager | F55: Feature Guide (G15.06) | G55: DEL-10 | H55: Live
A56: 52 | B56: Projects & delivery | C56: Project Overview and Activity tabs (status history and audit per project) | D56: /projects/:id; /projects/:id/activity | E56: All roles (project team); full: Administrator, CEO, CTO, HR Manager | F56: Additional (v1 base) | G56: DEL-07 | H56: Live
A57: 53 | B57: Projects & delivery | C57: Hand a project over to another project manager | D57: /projects/:id | E57: Administrator, CEO, CTO | F57: Additional (v4 access & controls) | H57: Live
A58: 54 | B58: Projects & delivery | C58: Margin-floor warning in the project cost calculator | D58: /projects → New project; /projects/:id/money | E58: Administrator, CEO, CTO, Project Manager | F58: Additional (v5 parity extras) | H58: Live
A59: 55 | B59: Projects & delivery | C59: Milestone billing shorthand (3L / 75K) and 'Edit as rows' in auto milestone setup | D59: /projects → New project | E59: Administrator, CEO, CTO, Project Manager | F59: Additional (v5 parity extras) | H59: Live
A60: 56 | B60: Projects & delivery | C60: Gantt zoom levels | D60: /projects/:id/schedule | E60: All roles (project team); full: Administrator, CEO, CTO, HR Manager | F60: Additional (v5 parity extras) | H60: Live
A61: 57 | B61: Projects & delivery | C61: Staffing openings | D61: /openings | E61: Administrator, CEO, CTO, Project Manager, HR Manager, HR Executive | F61: Additional (v1 base) | G61: HR-01 | H61: Live
A62: 58 | B62: Projects & delivery | C62: Project areas without opening a project: Milestones & billing, WBS, Schedule, Change requests, Resource allocation, Costing & margin, Project documents, Client view, Import WBS | D62: /delivery/* | E62: Everyone (own data) | F62: Additional (v7 workflows, documents & invoicing) | H62: Live
A63: 59 | B63: Projects & delivery | C63: Standalone project cost calculator for prospective projects (saved estimates, roles with assumed CTC, scenarios, compare) | D63: /projects/cost-calculator | E63: Administrator, CEO, CTO, Project Manager, Sales Manager | F63: Additional (v7 workflows, documents & invoicing) | H63: Live
A64: 60 | B64: Projects & delivery | C64: Estimate PDFs (internal costing, client quote) and Convert to project | D64: /projects/cost-calculator/:id | E64: Administrator, CEO, CTO, Project Manager, Sales Manager | F64: Additional (v7 workflows, documents & invoicing) | H64: Live
A65: 61 | B65: Tasks | C65: All tasks with filters | D65: Tasks › All tasks (/tasks) | E65: Everyone (own data) | F65: Feature Guide (G7.01) | H65: Live
A66: 62 | B66: Tasks | C66: Owner + backup; Covering on leave days | D66: Tasks › All tasks (/tasks; task page /tasks/:id) | E66: Edit: Administrator, CEO, CTO, Project Manager; view: task owner / backup | F66: Feature Guide (G7.02) | G66: TSK-02 | H66: Live
A67: 63 | B67: Tasks | C67: Estimate, dates and complexity | D67: Tasks › All tasks (/tasks; task page /tasks/:id) | E67: Edit: Administrator, CEO, CTO, Project Manager; view: task owner / backup | F67: Feature Guide (G7.03) | H67: Live
A68: 64 | B68: Tasks | C68: Ten task stages with progress % | D68: Tasks › All tasks (/tasks; task page /tasks/:id) | E68: Edit: Administrator, CEO, CTO, Project Manager; view: task owner / backup | F68: Feature Guide (G7.04) | H68: Live
A69: 65 | B69: Tasks | C69: Task dependencies block start | D69: Tasks › All tasks (/tasks; task page /tasks/:id) | E69: Edit: Administrator, CEO, CTO, Project Manager; view: task owner / backup | F69: Feature Guide (G7.05) | H69: Live
A70: 66 | B70: Tasks | C70: Comment threads with @mentions | D70: Tasks › All tasks (/tasks; task page /tasks/:id) › Thread; Dashboard › Employee (Tagged you) | E70: Edit: Administrator, CEO, CTO, Project Manager; view: task owner / backup | F70: Feature Guide (G7.06) | G70: TSK-03 | H70: Live
A71: 67 | B71: Tasks | C71: Task kind tags (e.g. Bug) | D71: Tasks › All tasks (/tasks; task page /tasks/:id) | E71: Edit: Administrator, CEO, CTO, Project Manager; view: task owner / backup | F71: Feature Guide (G7.07) | H71: Live
A72: 68 | B72: Tasks | C72: My tasks page | D72: /my-tasks | E72: Everyone (own data) | F72: Additional (v1 base) | G72: TSK-02 | H72: Live
A73: 69 | B73: Tasks | C73: Manager assigns general tasks to reports (General & admin project) | D73: /team-tasks?tab=assign | E73: Administrator, CEO, CTO, Project Manager, HR Manager, Sales Manager | F73: Additional (v3 business processes) | G73: TSK-01 | H73: Live
A74: 70 | B74: Tasks | C74: Submit task for review with note and proof link | D74: Task drawer → Submit for review | E74: Everyone (own data) | F74: Additional (v3 business processes) | G74: TSK-04 | H74: Live
A75: 71 | B75: Tasks | C75: Delay reason captured when a task is late | D75: Task drawer → Submit for review | E75: Everyone (own data) | F75: Additional (v3 business processes) | G75: TSK-05 | H75: Live
A76: 72 | B76: Tasks | C76: Approve task with quality rating (1–5) | D76: /inbox; /team-tasks?tab=review; task drawer | E76: Administrator, CEO, CTO, Project Manager, HR Manager, Sales Manager | F76: Additional (v3 business processes) | G76: TSK-06 | H76: Live
A77: 73 | B77: Tasks | C77: Send back with reason (review rounds) | D77: /inbox; task drawer | E77: Administrator, CEO, CTO, Project Manager, HR Manager, Sales Manager | F77: Additional (v3 business processes) | G77: TSK-07 | H77: Live
A78: 74 | B78: Tasks | C78: Reschedule a task with reason (target revisions) | D78: Task drawer | E78: Administrator, CEO, CTO, Project Manager | F78: Additional (v3 business processes) | G78: TSK-08 | H78: Live
A79: 75 | B79: Tasks | C79: Timeliness: early / on time / late in working days | D79: Computed (task lists, performance, appraisals) | E79: Everyone (own data) | F79: Additional (v3 business processes) | G79: TSK-09 | H79: Live
A80: 76 | B80: Tasks | C80: Team task monitoring and review queue | D80: /team-tasks?tab=team; /team-tasks?tab=review | E80: Administrator, CEO, CTO, Project Manager, HR Manager, Sales Manager | F80: Additional (v3 business processes) | G80: TSK-10 | H80: Live
A81: 77 | B81: Tasks | C81: Team and company delivery performance (by person / project) | D81: /team-tasks?tab=performance; /home | E81: Administrator, CEO, CTO, Project Manager, HR Manager | F81: Additional (v3 business processes) | G81: TSK-11 | H81: Live
A82: 78 | B82: Tasks | C82: Extra task tags: Feature, Improvement, Documentation, Support, Meeting | D82: Task drawer; /tasks filter | E82: Administrator, CEO, CTO, Project Manager | F82: Additional (v5 parity extras) | H82: Live
A83: 79 | B83: Tasks | C83: Task visibility: employees see own/covering/reviewer tasks; managers, HR, admins and CXOs see all with employee filter and By-employee view | D83: /tasks | E83: Administrator, CEO, CTO, Project Manager, HR Manager, HR Executive, Sales Manager | F83: Additional (v7 workflows, documents & invoicing) | H83: Live
A84: 80 | B84: Tasks | C84: Create task everywhere with full fields (reviewer, concerned manager, project, milestone, start/end, priority, depends on, watchers, acceptance criteria, attachments, recurrence) | D84: /tasks/new; Tasks; My tasks; Team tasks; WBS; dashboards | E84: Everyone (own data) | F84: Additional (v7 workflows, documents & invoicing) | H84: Live
A85: 81 | B85: Time & attendance | C85: Weekly timesheet Mon–Sat for header week | D85: My work › Timesheet & log (/timesheet) | E85: Everyone (own data) | F85: Feature Guide (G8.01) | G85: TIM-01 | H85: Live
A86: 82 | B86: Time & attendance | C86: Tasks / Activities rows, always one empty row | D86: My work › Timesheet & log (/timesheet) | E86: Everyone (own data) | F86: Feature Guide (G8.02) | H86: Live
A87: 83 | B87: Time & attendance | C87: Day totals vs 9h minimum; week summary | D87: My work › Timesheet & log (/timesheet) | E87: Everyone (own data) | F87: Feature Guide (G8.03) | H87: Live
A88: 84 | B88: Time & attendance | C88: Quick rows: leave, lunch/tea/stand-up, copy last week | D88: My work › Timesheet & log (/timesheet) | E88: Everyone (own data) | F88: Feature Guide (G8.04) | H88: Live
A89: 85 | B89: Time & attendance | C89: Save draft; submit for approval | D89: My work › Timesheet & log (/timesheet) | E89: Everyone (own data) | F89: Feature Guide (G8.05) | G89: TIM-02 | H89: Live
A90: 86 | B90: Time & attendance | C90: Weekly lock and unlock request | D90: My work › Timesheet & log (/timesheet) | E90: Everyone (own week); unlock: managers / CEO via approvals | F90: Feature Guide (G8.06) | G90: TIM-04 | H90: Live
A91: 87 | B91: Time & attendance | C91: Task hours become actual hours and cost | D91: My work › Timesheet & log (/timesheet) | E91: Everyone (own data) | F91: Feature Guide (G8.07) | H91: Live
A92: 88 | B92: Time & attendance | C92: End-of-day update with proof link | D92: My work › Timesheet & log (/timesheet) › End-of-day update | E92: Everyone (own data) | F92: Feature Guide (G8.08) | G92: TIM-05 | H92: Live
A93: 89 | B93: Time & attendance | C93: Friday demo | D93: My work › Timesheet & log (/timesheet) › Friday demo | E93: Everyone (own data) | F93: Feature Guide (G8.09) | H93: Live
A94: 90 | B94: Time & attendance | C94: Leave recording and leave taken this FY | D94: Admin › Team & settings › Leave (/leave?tab=hr) | E94: Administrator, CEO, HR Manager, HR Executive | F94: Feature Guide (G16.04) | G94: TIM-09 | H94: Live
A95: 91 | B95: Time & attendance | C95: Apply for leave (employee self-service) | D95: /leave | E95: Everyone (own data) | F95: Additional (v3 business processes) | G95: TIM-06 | H95: Live
A96: 92 | B96: Time & attendance | C96: Approve, reject or cancel leave | D96: /leave; /inbox | E96: Administrator, CEO, CTO, Project Manager, HR Manager, Sales Manager | F96: Additional (v3 business processes) | G96: TIM-07 | H96: Live
A97: 93 | B97: Time & attendance | C97: Leave policy and balances | D97: /leave (Policy) | E97: Administrator, CEO, HR Manager | F97: Additional (v3 business processes) | G97: TIM-08 | H97: Live
A98: 94 | B98: Time & attendance | C98: Team page: workload, timesheets and availability of reports | D98: /team | E98: Administrator, CEO, CTO, Project Manager, HR Manager, Sales Manager | F98: Additional (v1 base) | H98: Live
A99: 95 | B99: Approvals & governance | C99: Submitted weeks to reports-to manager with deadline | D99: Tasks › Timesheet approvals (/approvals) | E99: Administrator, CEO, CTO, Project Manager, HR Manager, HR Executive, Sales Manager | F99: Feature Guide (G9.01) | G99: TIM-03 | H99: Live
A100: 96 | B100: Approvals & governance | C100: Approval KPI strip | D100: Tasks › Timesheet approvals (/approvals) | E100: Administrator, CEO, CTO, Project Manager, HR Manager, HR Executive, Sales Manager | F100: Feature Guide (G9.02) | H100: Live
A101: 97 | B101: Approvals & governance | C101: Waiting list with approve / reject | D101: Tasks › Timesheet approvals (/approvals) | E101: Administrator, CEO, CTO, Project Manager, HR Manager, HR Executive, Sales Manager | F101: Feature Guide (G9.03) | H101: Live
...

Sheet Additional features
A1: Built in addition to the Feature Guide
A2: Features in SeereonOS that the Feature Guide does not ask for (same rows as 'Additional' on the Build feature list).
A4: # | B4: Area | C4: Feature | D4: Screen / route | E4: Who can use it (default roles) | F4: Added in | G4: Process catalogue IDs | H4: Why it helps
A5: 1 | B5: Dashboards | C5: HR & operations home: on leave today, compliance calendar (60 days), openings, payroll | D5: /home → Operations | E5: Administrator, CEO, HR Manager, HR Executive | F5: v1 base | G5: ANA-04 | H5: HR sees today's people picture and upcoming statutory dates.
A6: 2 | B6: Dashboards | C6: Persona-based home: CTO, HR and other default roles land on the right dashboard | D6: /home | E6: Everyone (own data) | F6: v4 access & controls | G6: ACC-09 | H6: Every role opens to the dashboard that fits its job.
A7: 3 | B7: Projects & delivery | C7: Project Overview and Activity tabs (status history and audit per project) | D7: /projects/:id; /projects/:id/activity | E7: All roles (project team); full: Administrator, CEO, CTO, HR Manager | F7: v1 base | G7: DEL-07 | H7: Full project history in one place.
A8: 4 | B8: Projects & delivery | C8: Hand a project over to another project manager | D8: /projects/:id | E8: Administrator, CEO, CTO | F8: v4 access & controls | H8: Leadership can reassign projects cleanly.
A9: 5 | B9: Projects & delivery | C9: Margin-floor warning in the project cost calculator | D9: /projects → New project; /projects/:id/money | E9: Administrator, CEO, CTO, Project Manager | F9: v5 parity extras | H9: Stops under-priced projects before they are signed.
A10: 6 | B10: Projects & delivery | C10: Milestone billing shorthand (3L / 75K) and 'Edit as rows' in auto milestone setup | D10: /projects → New project | E10: Administrator, CEO, CTO, Project Manager | F10: v5 parity extras | H10: Faster project set-up with fewer typing errors.
A11: 7 | B11: Projects & delivery | C11: Gantt zoom levels | D11: /projects/:id/schedule | E11: All roles (project team); full: Administrator, CEO, CTO, HR Manager | F11: v5 parity extras | H11: Read long projects by week or month.
A12: 8 | B12: Projects & delivery | C12: Staffing openings | D12: /openings | E12: Administrator, CEO, CTO, Project Manager, HR Manager, HR Executive | F12: v1 base | G12: HR-01 | H12: Links hiring needs to projects.
A13: 9 | B13: Projects & delivery | C13: Project areas without opening a project: Milestones & billing, WBS, Schedule, Change requests, Resource allocation, Costing & margin, Project documents, Client view, Import WBS | D13: /delivery/* | E13: Everyone (own data) | F13: v7 workflows, documents & invoicing | H13: Cross-project overviews plus a project picker that shows the same project tabs.
A14: 10 | B14: Projects & delivery | C14: Standalone project cost calculator for prospective projects (saved estimates, roles with assumed CTC, scenarios, compare) | D14: /projects/cost-calculator | E14: Administrator, CEO, CTO, Project Manager, Sales Manager | F14: v7 workflows, documents & invoicing | H14: Price and margin can be worked out before a deal is won.
A15: 11 | B15: Projects & delivery | C15: Estimate PDFs (internal costing, client quote) and Convert to project | D15: /projects/cost-calculator/:id | E15: Administrator, CEO, CTO, Project Manager, Sales Manager | F15: v7 workflows, documents & invoicing | H15: A won estimate becomes a project with its milestones, resources and costing plan.
A16: 12 | B16: Tasks | C16: My tasks page | D16: /my-tasks | E16: Everyone (own data) | F16: v1 base | G16: TSK-02 | H16: Each person sees exactly what is on their plate this week.
A17: 13 | B17: Tasks | C17: Manager assigns general tasks to reports (General & admin project) | D17: /team-tasks?tab=assign | E17: Administrator, CEO, CTO, Project Manager, HR Manager, Sales Manager | F17: v3 business processes | G17: TSK-01 | H17: Non-project work is tracked with the same discipline as project work.
A18: 14 | B18: Tasks | C18: Submit task for review with note and proof link | D18: Task drawer → Submit for review | E18: Everyone (own data) | F18: v3 business processes | G18: TSK-04 | H18: 'Done' means reviewed and accepted, not self-declared.
A19: 15 | B19: Tasks | C19: Delay reason captured when a task is late | D19: Task drawer → Submit for review | E19: Everyone (own data) | F19: v3 business processes | G19: TSK-05 | H19: Shows why work slips, so causes can be fixed.
A20: 16 | B20: Tasks | C20: Approve task with quality rating (1–5) | D20: /inbox; /team-tasks?tab=review; task drawer | E20: Administrator, CEO, CTO, Project Manager, HR Manager, Sales Manager | F20: v3 business processes | G20: TSK-06 | H20: Adds a quality score to on-time delivery for appraisals.
A21: 17 | B21: Tasks | C21: Send back with reason (review rounds) | D21: /inbox; task drawer | E21: Administrator, CEO, CTO, Project Manager, HR Manager, Sales Manager | F21: v3 business processes | G21: TSK-07 | H21: Rework is visible and counted.
A22: 18 | B22: Tasks | C22: Reschedule a task with reason (target revisions) | D22: Task drawer | E22: Administrator, CEO, CTO, Project Manager | F22: v3 business processes | G22: TSK-08 | H22: Every date change is explained and kept.
A23: 19 | B23: Tasks | C23: Timeliness: early / on time / late in working days | D23: Computed (task lists, performance, appraisals) | E23: Everyone (own data) | F23: v3 business processes | G23: TSK-09 | H23: One fair, consistent measure of delivery for everyone.
A24: 20 | B24: Tasks | C24: Team task monitoring and review queue | D24: /team-tasks?tab=team; /team-tasks?tab=review | E24: Administrator, CEO, CTO, Project Manager, HR Manager, Sales Manager | F24: v3 business processes | G24: TSK-10 | H24: Line managers see all their reports' work in one place.
A25: 21 | B25: Tasks | C25: Team and company delivery performance (by person / project) | D25: /team-tasks?tab=performance; /home | E25: Administrator, CEO, CTO, Project Manager, HR Manager | F25: v3 business processes | G25: TSK-11 | H25: Spot who needs help and which projects slip most.
A26: 22 | B26: Tasks | C26: Extra task tags: Feature, Improvement, Documentation, Support, Meeting | D26: Task drawer; /tasks filter | E26: Administrator, CEO, CTO, Project Manager | F26: v5 parity extras | H26: Work can be sliced by type, not only bugs.
A27: 23 | B27: Tasks | C27: Task visibility: employees see own/covering/reviewer tasks; managers, HR, admins and CXOs see all with employee filter and By-employee view | D27: /tasks | E27: Administrator, CEO, CTO, Project Manager, HR Manager, HR Executive, Sales Manager | F27: v7 workflows, documents & invoicing | H27: People see what concerns them; leaders see everything and filter by person.
A28: 24 | B28: Tasks | C28: Create task everywhere with full fields (reviewer, concerned manager, project, milestone, start/end, priority, depends on, watchers, acceptance criteria, attachments, recurrence) | D28: /tasks/new; Tasks; My tasks; Team tasks; WBS; dashboards | E28: Everyone (own data) | F28: v7 workflows, documents & invoicing | H28: One professional task form wherever work is assigned.
A29: 25 | B29: Time & attendance | C29: Apply for leave (employee self-service) | D29: /leave | E29: Everyone (own data) | F29: v3 business processes | G29: TIM-06 | H29: Employees request leave themselves instead of asking HR.
A30: 26 | B30: Time & attendance | C30: Approve, reject or cancel leave | D30: /leave; /inbox | E30: Administrator, CEO, CTO, Project Manager, HR Manager, Sales Manager | F30: v3 business processes | G30: TIM-07 | H30: Leave goes through the reporting manager with a record.
A31: 27 | B31: Time & attendance | C31: Leave policy and balances | D31: /leave (Policy) | E31: Administrator, CEO, HR Manager | F31: v3 business processes | G31: TIM-08 | H31: Entitlements and balances are calculated, not tracked in spreadsheets.
A32: 28 | B32: Time & attendance | C32: Team page: workload, timesheets and availability of reports | D32: /team | E32: Administrator, CEO, CTO, Project Manager, HR Manager, Sales Manager | F32: v1 base | H32: Managers see who is free, overloaded or behind on timesheets.
A33: 29 | B33: Approvals & governance | C33: Approvals inbox: every approval in one place | D33: /inbox | E33: All roles | F33: v3 business processes | G33: GOV-03 | H33: Managers clear timesheets, leave, expenses, POs, bills, tasks, documents and changes from one queue.
A34: 30 | B34: Approvals & governance | C34: Audit trail (who changed what, when) | D34: /audit | E34: Administrator, CEO, CTO | F34: v3 business processes | G34: GOV-04 | H34: Full accountability and ISO 9001 evidence.
A35: 31 | B35: Approvals & governance | C35: Goals & OKRs: company, team and personal objectives | D35: /okrs | E35: All roles (view: everyone); full: Administrator, CEO | F35: v3 business processes | G35: GOV-01 | H35: Links daily work to company goals.
A36: 32 | B36: Approvals & governance | C36: Key results with automatic measures and check-ins | D36: /okrs | E36: All roles (check-ins: owners); full: Administrator, CEO | F36: v3 business processes | G36: GOV-02 | H36: Progress on goals updates itself from live data.
A37: 33 | B37: Approvals & governance | C37: Workflow designer: stages, assignee rules, per-stage reviewer fields with visibility, SLA, send back, completion actions | D37: /workflows/designer | E37: Administrator, CEO, HR Manager | F37: v7 workflows, documents & invoicing | H37: HR and admins can build their own approval processes without code.
A38: 34 | B38: Approvals & governance | C38: Workflow inbox and run page (waiting for me, started by me, about me), escalation on SLA breach | D38: /workflows; /workflows/run/:id | E38: Everyone (own data) | F38: v7 workflows, documents & invoicing | H38: Each reviewer sees only their step and the fields they are allowed to see.
A39: 35 | B39: Payroll | C39: Finalise payroll (lock run, post to ledger) | D39: /payroll/:id | E39: Administrator, CEO | F39: v1 base | G39: PAY-04 | H39: Paid months cannot change later and costs land in the books.
A40: 36 | B40: Sales | C40: Pipeline kanban board (drag deals between stages) | D40: /sales | E40: Administrator, CEO, Sales Manager, Sales Executive | F40: v1 base | G40: SAL-02 | H40: Fast stage updates alongside the funnel view.
A41: 37 | B41: Sales | C41: Sales home dashboard: target this month, deals needing action, pipeline by stage, recent activity | D41: /home → Sales | E41: Administrator, CEO, Sales Manager, Sales Executive | F41: v1 base | G41: ANA-03 | H41: Each salesperson starts the day with what needs action.
A42: 38 | B42: Clients & contracts | C42: Client master | D42: /clients; /clients/:id | E42: Administrator, CEO, Sales Manager, Sales Executive | F42: v3 business processes | G42: CLI-01 | H42: One record per client across sales, delivery and finance.
A43: 39 | B43: Clients & contracts | C43: Contract register | D43: /clients/:id | E43: Administrator, CEO, Sales Manager, Sales Executive | F43: v3 business processes | G43: CLI-02 | H43: Contract values, dates and terms in one place.
A44: 40 | B44: Clients & contracts | C44: Contract renewals | D44: /clients | E44: Administrator, CEO, Sales Manager, Sales Executive | F44: v3 business processes | G44: CLI-03 | H44: AMC and subscription renewals are never missed.
A45: 41 | B45: Clients & contracts | C45: Client health and 360 view | D45: /clients/:id | E45: Administrator, CEO, Sales Manager, Sales Executive | F45: v3 business processes | G45: CLI-04 | H45: Projects, invoices, dues and deals for a client on one page.
A46: 42 | B46: Finance | C46: Invoices list with receivables ageing and DSO | D46: /finance/invoices | E46: Administrator, CEO | F46: v1 base | G46: FIN-03 | H46: Shows who owes what and for how long.
A47: 43 | B47: Finance | C47: Record client payments (including part payments) | D47: /finance/invoices | E47: Administrator, CEO | F47: v1 base | G47: FIN-02 | H47: Cash received is tracked against each invoice.
A48: 44 | B48: Finance | C48: Cash runway | D48: /home → CEO; /finance/pnl | E48: Administrator, CEO | F48: v1 base | G48: FIN-06 | H48: How many months the company can run on current cash.
A49: 45 | B49: Finance | C49: GST tax invoice editor per project: seller and buyer GSTIN, place of supply, HSN/SAC lines, CGST+SGST or IGST, bank and IFSC, amount in words | D49: /finance/invoices/new | E49: Administrator, CEO | F49: v7 workflows, documents & invoicing | H49: Invoices are legally formatted and tie into milestones, ledger and margins.
A50: 46 | B50: Finance | C50: Invoice view, PDF, payments with TDS, email, cancel with credit note; revenue at taxable value | D50: /finance/invoices/:id | E50: Administrator, CEO | F50: v7 workflows, documents & invoicing | H50: Billing and collections stay accurate and auditable.
A51: 47 | B51: Spend & procurement | C51: Submit an expense claim | D51: /expenses | E51: Everyone (own data) | F51: v3 business processes | G51: SPD-01 | H51: Employees claim reimbursements with receipts in the app.
A52: 48 | B52: Spend & procurement | C52: Approve or reject expenses (two-step above Rs 25,000) | D52: /expenses?tab=approve; /inbox | E52: Administrator, CEO, CTO, Project Manager, HR Manager, Sales Manager | F52: v3 business processes | G52: SPD-02 | H52: Controls spend with an extra check on large claims.
A53: 49 | B53: Spend & procurement | C53: Reimburse an expense | D53: /expenses?tab=pay; /inbox | E53: Administrator, CEO, HR Manager | F53: v3 business processes | G53: SPD-03 | H53: Finance pays only approved claims and records it.
A54: 50 | B54: Spend & procurement | C54: Vendor master (onboard, block, unblock) | D54: /purchases (Vendors) | E54: Administrator, CEO, HR Manager | F54: v3 business processes | G54: ORG-04 | H54: One verified vendor list; bank detail changes are maker-checked.
A55: 51 | B55: Spend & procurement | C55: Raise a purchase order | D55: /purchases | E55: Administrator, CEO, HR Manager | F55: v3 business processes | G55: SPD-04 | H55: Spend is committed only with an approved PO.
A56: 52 | B56: Spend & procurement | C56: Approve, reject or close a purchase order | D56: /purchases; /inbox | E56: Administrator, CEO, HR Manager | F56: v3 business processes | G56: SPD-05 | H56: Purchases follow the approval workflow and budget.
A57: 53 | B57: Spend & procurement | C57: Book a vendor bill with PO match | D57: /purchases | E57: Administrator, CEO, HR Manager | F57: v3 business processes | G57: SPD-06 | H57: Bills are paid only against what was ordered.
A58: 54 | B58: Spend & procurement | C58: Approve, dispute and pay vendor bills | D58: /purchases; /inbox | E58: Administrator, CEO, HR Manager | F58: v3 business processes | G58: SPD-07 | H58: Payables under control, disputes recorded.
A59: 55 | B59: Spend & procurement | C59: Annual budget with monthly phasing | D59: /budgets | E59: Administrator, CEO | F59: v3 business processes | G59: SPD-08 | H59: Plans spend and revenue by month.
A60: 56 | B60: Spend & procurement | C60: Budget vs actual review | D60: /budgets | E60: Administrator, CEO | F60: v3 business processes | G60: SPD-09 | H60: Overspend is visible the month it happens.
A61: 57 | B61: Spend & procurement | C61: Unbudgeted / additional spend register | D61: /budgets | E61: Administrator, CEO | F61: v3 business processes | G61: SPD-10 | H61: Every out-of-plan spend is justified and approved.
A62: 58 | B62: Revenue assurance | C62: Lost revenue register and reporting | D62: /leakage | E62: Administrator, CEO, Sales Manager | F62: v3 business processes | G62: REV-01 | H62: Puts a rupee figure on revenue the company is losing.
... A83: 79 | B83: People & HR | C83: Apply appraisal increments to salary | D83: /appraisals/:id → /settings/cost-rates | E83: Administrator, CEO | F83: v3 business processes | G83: PAY-05 | H83: Increments flow into CTC and costing without re-entry (maker-checked).
A84: 80 | B84: People & HR | C84: Annual appraisal workflow: self > manager/TL > unit head > HR > finance > letter issued, email sent, CTC change via maker-checker | D84: /workflows; /appraisals | E84: Administrator, CEO, HR Manager, HR Executive | F84: v7 workflows, documents & invoicing | H84: Appraisals run end to end with letters generated automatically.
A85: 81 | B85: People & HR | C85: Ready-made workflows: probation confirmation, onboarding, exit clearance, promotion, document approval | D85: /workflows/designer | E85: Administrator, CEO, HR Manager | F85: v7 workflows, documents & invoicing | H85: Common HR processes work out of the box.
A86: 82 | B86: Documents | C86: Project documents: PM uploads and manages | D86: /projects/:id/documents | E86: Administrator, CEO, CTO, Project Manager | F86: v3 business processes | G86: DOC-01 | H86: Specs, SOWs and sign-offs live with the project.
A87: 83 | B87: Documents | C87: Employees access project documents | D87: /documents; /projects/:id/documents | E87: Everyone (own data) | F87: v3 business processes | G87: DOC-02 | H87: The team always works from the latest document.
A88: 84 | B88: Documents | C88: Document versions, archive and restore | D88: /documents | E88: Administrator, CEO, CTO, Project Manager | F88: v3 business processes | G88: DOC-03 | H88: No lost or overwritten versions.
A89: 85 | B89: Documents | C89: Must-read acknowledgements | D89: /inbox; /documents | E89: All roles (acknowledge: everyone); full: Administrator, CEO, CTO, Project Manager | F89: v3 business processes | G89: DOC-04 | H89: Proof that people read policies and specs.
A90: 86 | B90: Documents | C90: Company library and policies | D90: /documents | E90: All roles (read: everyone); full: Administrator, CEO, HR Manager, HR Executive | F90: v3 business processes | G90: DOC-05 | H90: One home for HR policies, templates and ISO documents.
A91: 87 | B91: Documents | C91: Documents hub: Templates, Issued documents, Policies, Employee documents, Project documents, My documents | D91: /documents | E91: Everyone (own data) | F91: v7 workflows, documents & invoicing | H91: One place for every office document.
A92: 88 | B92: Documents | C92: Letter templates with placeholders and letterhead; issue to one or many employees; PDF; acknowledgement | D92: /documents?tab=templates | E92: Administrator, CEO, HR Manager, HR Executive | F92: v7 workflows, documents & invoicing | H92: Offer, joining, appraisal, relieving and other letters are generated, not typed.
A93: 89 | B93: Documents | C93: Payslips issued automatically when payroll is finalised; joining letter on create employee | D93: /documents?tab=issued; /payroll | E93: Administrator, CEO, HR Manager, HR Executive | F93: v7 workflows, documents & invoicing | H93: Employees get payslips and letters without HR effort.
A94: 90 | B94: Documents | C94: Employee documents employee-wise with upload, verify and reject | D94: /documents?tab=employees; /documents/employees/:id | E94: Administrator, CEO, HR Manager, HR Executive | F94: v7 workflows, documents & invoicing | H94: HR sees every person's ID, education and bank documents in one place.
A95: 91 | B95: Insights, reports & AI | C95: Insights operational views: tasks at risk, blocked, overdue milestones, effort ratio, allocation, timesheet compliance, approval KPI, stale deals | D95: /insights/:view | E95: Administrator, CEO, CTO, Project Manager, HR Manager, Sales Manager, Sales Executive | F95: v1 base | G95: ANA-06, SAL-06 | H95: Eight ready-made management views beyond the guide's predictions.
A96: 92 | B96: Insights, reports & AI | C96: 'Ask AI' button on every insight view | D96: /insights/:view | E96: All roles | F96: v1 base | G96: ANA-08 | H96: Ask a follow-up question about any view in plain English.
A97: 93 | B97: Insights, reports & AI | C97: Standard reports library (templates, pinned, mine, shared) | D97: /reports | E97: Administrator, CEO, CTO, Project Manager, HR Manager, HR Executive, Sales Manager, Sales Executive | F97: v1 base | G97: ANA-07 | H97: Common reports ready to run, within each person's access.
A98: 94 | B98: Insights, reports & AI | C98: Custom report builder (datasets, measures, dimensions, filters, charts) | D98: /reports/new; /reports/:id/edit | E98: Administrator, CEO, CTO, Project Manager, HR Manager, Sales Manager, Sales Executive | F98: v1 base | G98: ANA-07 | H98: Managers build their own reports without IT.
A99: 95 | B99: Insights, reports & AI | C99: Saved and shared reports (duplicate, edit, delete) | D99: /reports/:id | E99: Administrator, CEO, CTO, Project Manager, HR Manager, HR Executive, Sales Manager, Sales Executive | F99: v1 base | G99: ANA-07 | H99: Good reports are reused across the team.
A100: 96 | B100: Insights, reports & AI | C100: Report datasets for all business processes (22 datasets) | D100: /reports/new; /ai | E100: Administrator, CEO, CTO, Project Manager, HR Manager, Sales Manager, Sales Executive | F100: v3 business processes | G100: ANA-10 | H100: Every area of the business can be reported on.
A101: 97 | B101: Insights, reports & AI | C101: Ask AI: plain-English questions answered from live data | D101: /ai | E101: All roles | F101: v1 base | G101: ANA-08 | H101: The CEO can ask a question and get a computed answer, not a guess.
A102: 98 | B102: Insights, reports & AI | C102: AI report studio (AI plans a report, engine computes every figure) | D102: /ai | E102: Administrator, CEO, CTO, Project Manager, HR Manager, Sales Manager, Sales Executive | F102: v1 base | G102: ANA-08 | H102: Turns a question into a saved, exportable report.
A103: 99 | B103: Insights, reports & AI | C103: AI assistant panel from any page | D103: Top bar / phone tab bar → Ask AI | E103: All roles | F103: v1 base | G103: ANA-08 | H103: Help is one click away on every screen.
A104: 100 | B104: Roles & controls | C104: Permission catalogue: 70+ permission keys in 9 modules | D104: /setup/roles | E104: Administrator, CEO, CTO, HR Manager | F104: v4 access & controls | G104: ACC-09 | H104: Access is granted capability by capability instead of five fixed roles.
A105: 101 | B105: Roles & controls | C105: Nine default roles shipped with every workspace | D105: /setup/roles | E105: Administrator, CEO, CTO, HR Manager | F105: v4 access & controls | G105: ACC-01 | H105: Administrator, CEO, CTO, PM, HR Manager, HR Executive, Sales Manager, Sales Executive, Employee work out of the box.
A106: 102 | B106: Roles & controls | C106: Role editor and permission matrix (custom roles) | D106: /setup/roles/:key | E106: Administrator, CEO | F106: v4 access & controls | G106: ACC-01 | H106: Each company can shape roles to its own structure without code changes.
... A133: 129 | B133: Settings & appearance | C133: Settings sections for timesheets, sales, notification times, security and AI | D133: /settings/company | E133: Administrator, CEO | F133: v1 base | G133: ORG-01 | H133: Every rule the system runs on is visible and adjustable by the company.
A134: 130 | B134: Settings & appearance | C134: Themes: presets, brand colours, radius, density, font, sidebar style, default mode | D134: /settings/appearance | E134: Administrator, CEO | F134: v1 base | H134: Each tenant can brand the product as its own.
A135: 131 | B135: Settings & appearance | C135: Personal light / dark mode | D135: /settings/appearance | E135: Everyone (own data) | F135: v1 base | H135: Comfort for each person without changing the company theme.
A136: 132 | B136: Workspace & access | C136: Company sign-up with 14-day trial (up to 25 people) | D136: /signup | E136: Anyone (new company); signer becomes Administrator | F136: v1 base | G136: WS-01 | H136: A new company gets its own workspace in minutes, without a sales call.
A137: 133 | B137: Workspace & access | C137: Getting-started onboarding checklist and sample data | D137: /onboarding; /home | E137: Administrator, CEO | F137: v1 base | G137: WS-02 | H137: Walks a new workspace to first value: rules, calendar, people, first project, first week.
A138: 134 | B138: Workspace & access | C138: Sign in, lockout and password reset | D138: /login; /reset-password | E138: Everyone (own data) | F138: v1 base | G138: WS-03 | H138: Secure self-service access; locked accounts and forgotten passwords need no admin.
A139: 135 | B139: Workspace & access | C139: Invite people (single or bulk CSV) and accept invitation | D139: /people; /invite/:token | E139: Administrator, CEO, HR Manager, HR Executive | F139: v1 base | G139: WS-04 | H139: Brings a whole team in at once from a spreadsheet.
A140: 136 | B140: Workspace & access | C140: Security: two-step verification and personal profile | D140: /settings/security; /settings/profile | E140: Everyone (own data) | F140: v1 base | G140: WS-08 | H140: Protects company and salary data with 2FA; each person keeps their own details current.
A141: 137 | B141: Workspace & access | C141: Full workspace data export | D141: /settings/data | E141: Administrator, CEO | F141: v1 base | G141: WS-10 | H141: The company owns its data and can take a complete copy at any time.
A142: 138 | B142: Workspace & access | C142: Subscription plan, seats and payment | D142: /billing | E142: Administrator, CEO | F142: v1 base | G142: WS-11 | H142: Self-service plan and seat management for the SaaS.
A143: 139 | B143: Workspace & access | C143: Multi-tenancy: isolated company workspaces (tenant-scoped data and cache) | D143: All screens | E143: Platform (every workspace) | F143: v1 base | H143: Each client company sees only its own data; the product can be sold to many companies.
A144: 140 | B144: Workspace & access | C144: Read-only workspace when a subscription lapses (billing stays open) | D144: All screens; /billing | E144: Platform (every workspace) | F144: v1 base | G144: WS-11 | H144: Protects data without locking customers out; they can pay and resume.
A145: 141 | B145: Workspace & access | C145: Platform super admin: tenants, trials and suspensions | D145: /admin | E145: Platform super admin only | F145: v1 base | G145: WS-12 | H145: Seereon can run the SaaS business: see tenants, extend trials, suspend accounts.
A146: 142 | B146: Workspace & access | C146: Privacy and terms pages | D146: /privacy; /terms | E146: Everyone (own data) | F146: v1 base | H146: Legal pages required for a public SaaS.
A147: 143 | B147: Platform & UX | C147: Command palette search (Ctrl/Cmd+K) | D147: Top bar (every page) | E147: Everyone (own data) | F147: v1 base | H147: Jump to any screen, project, task or person in two keystrokes.
...

Sheet Guide screenshots map
A1: Guide screenshots → build screens
A2: The 36 screenshots in the Feature Guide PDF (img-000 … img-035) and where the same screen lives in SeereonOS.
A4: Screenshot | B4: What it shows | C4: Guide page | D4: Equivalent screen in the build (route) | E4: G-IDs | F4: Image file
A5: 000 | B5: Header and role tabs (company name, week switcher, tabs, View as) | C5: 1 | D5: Top bar + left menu on every page; Dashboard (/home) | E5: G1.01, G1.02, G1.03, G1.04 | F5: docs/feature-guide-screens/img-000.jpg
A6: 001 | B6: Employee view (person picker, Tagged you, Covering, own numbers) | C6: 2 | D6: Dashboard › Employee (/home) | E6: G1.06 | F6: docs/feature-guide-screens/img-001.jpg
A7: 002 | B7: CEO dashboard: revenue and earnings, period table, 12-month chart, revenue by stream, revenue ahead | C7: 3 | D7: Dashboard › CEO › Overview (/home) | E7: G2.01, G2.02, G2.03, G2.04, G2.05, G2.08 | F7: docs/feature-guide-screens/img-002.jpg
A8: 003 | B8: CEO dashboard: delivery KPIs and milestones-and-cash | C8: 4 | D8: Dashboard › CEO › Overview (/home) | E8: G2.06, G2.07 | F8: docs/feature-guide-screens/img-003.jpg
A9: 004 | B9: Projects list (status chips, health, columns, inline expand) | C9: 4 | D9: Projects & WBS › All projects (/projects) | E9: G3.01, G3.02, G3.03, G3.04, G3.05, G3.06 | F9: docs/feature-guide-screens/img-004.jpg
A10: 005 | B10: Create project form incl. auto milestone setup, documents and project cost calculator | C10: 6 | D10: Projects & WBS › Create project (/projects/new) | E10: G3.07, G3.08, G3.09, G3.10, G3.11 | F10: docs/feature-guide-screens/img-005.jpg
A11: 006 | B11: Milestones table (numbering, deadline, status, progress, billing) | C11: 7 | D11: Projects & WBS › All projects › project › WBS (/projects/:id/wbs); direct: Projects & WBS › Milestones & billing / WBS (Milestones) | E11: G4.01, G4.02, G4.03, G4.04, G4.05, G4.06, G4.07, G4.08 | F11: docs/feature-guide-screens/img-006.jpg
A12: 007 | B12: WBS table (milestone rollups, task rows, dependencies, critical rows) | C12: 8 | D12: Projects & WBS › All projects › project › WBS (/projects/:id/wbs); direct: Projects & WBS › Milestones & billing / WBS | E12: G4.09, G7.07 | F12: docs/feature-guide-screens/img-007.jpg
A13: 008 | B13: Gantt schedule with critical path summary | C13: 9 | D13: Projects & WBS › All projects › project › Schedule (/projects/:id/schedule); direct: Projects & WBS › Schedule & critical path | E13: G5.01, G5.02 | F13: docs/feature-guide-screens/img-008.jpg
A14: 009 | B14: Critical path and breach risks list | C14: 10 | D14: Projects & WBS › All projects › project › Schedule (/projects/:id/schedule); direct: Projects & WBS › Schedule & critical path; Dashboard › Project manager | E14: G5.03 | F14: docs/feature-guide-screens/img-009.jpg
A15: 010 | B15: Change requests (KPIs, CR rows, approve / reject, raise form) | C15: 11 | D15: Projects & WBS › All projects › project › Changes (/projects/:id/changes); direct: Projects & WBS › Change requests | E15: G5.04 | F15: docs/feature-guide-screens/img-010.jpg
A16: 011 | B16: Costing and margin: planned / projected / actual, what moved the margin, milestone variance, resources allocated vs logged, planned costing | C16: 12 | D16: Projects & WBS › All projects › project › Costing & margin (/projects/:id/costing); direct: Projects & WBS › Costing & margin | E16: G6.01, G6.03, G6.04, G6.05, G6.06, G6.07, G6.08, G6.09 | F16: docs/feature-guide-screens/img-011.jpg
... A40: 035 | B40: Rules and KPI definitions | C40: 30 | D40: Company › Rules (/rules) | E40: G17.01, G17.02 | F40: docs/feature-guide-screens/img-035.jpg
