Workbook

Sheet Read me
A1: SeereonOS - Business Process Catalogue (v4)
A2: Seereon Consulting & IT Services Pvt. Ltd., Bhubaneswar | Prepared for Santosh Nayak, Founder & CEO | Version v4 | Version date: 1 Oct 2026
A4: Purpose
A5: This workbook is the master reference for how a company runs on SeereonOS: every business process, who does it, who approves it, which rules the system enforces, what data it captures, which KPIs it produces and which dashboards it feeds. The aim is a company that can run, grow and build itself on process and data: every task, appraisal, person's performance, revenue earned, revenue lost and additional expense tracked in one system.
A6: Status reflects the product as built on 1 Oct 2026 (release v4). Rows marked Planned are processes a complete company OS for an Indian IT services / SAP consulting firm (10-200 people) still needs, each with a one-line recommendation.
A8: What is new in v4
A9: - Maker-checker: sensitive changes (roles, user access, salaries / cost rates, payroll finalisation, vendor bank and tax details, approval workflows, organisation profile and more) are proposed by one person and applied only when a second person approves. See the Maker-checker sheet and processes MC-01..04.
A10: - Granular role-permission matrix: 72 permissions in 9 modules; roles are data per workspace. Default roles: Administrator, CEO, CTO, Project Manager, HR Manager, HR Executive, Sales Manager, Sales Executive, Employee. Per-person extra and revoked permissions on top of the role. See Roles & permissions and ACC-01..03.
A11: - One login: screens, actions and data scope follow effective permissions; the role's persona only picks the home dashboard (ACC-09). View as works for any role (ACC-08).
A12: - Admin-configurable master data: organisation profile, locations, departments, designations, grades & CTC bands, cost centres, shifts & assignment, email templates & sent log (ADM-01..06).
A13: - Configurable approval workflows for leave, expenses, purchase orders, vendor bills, timesheets and task reviews: steps, amount thresholds, SLA and escalation, with a test panel; defaults reproduce v3 (WF-01..03, Approval workflows sheet).
A14: - Onboarding flow: Administrator signs in > fills org master data > reviews roles & permissions > creates employees with role and reporting manager > welcome email with temporary credentials (outbox) > employee signs in, must set a password, sees their own portal (SET-01, ACC-04, ACC-05; Setup & onboarding flow sheet).
... A41: RACI legend
A42: R | B42: Responsible: does the work
A43: A | B43: Accountable / approves (shown in bold)
A44: C | B44: Consulted: gives input before or during
A45: I | B45: Informed: notified or sees the result
A46: (blank) | B46: Not involved
A48: Status legend
A49: Live | B49: In the product before v3
A50: Extended | B50: Existed and was extended in v3 or v4 (see the "v4:" note)
A51: New in v3 | B51: Added in v3
A52: New in v4 | B52: Added in v4
A53: Planned | B53: Not built yet; recommended
A55: Processes by domain and status (live formulas)
A56: Domain | B56: Live | C56: Extended | D56: New in v3 | E56: New in v4 | F56: Planned | G56: Total
A57: Workspace & access | B57: =COUNTIFS('Process catalogue'!$B$2:$B$186,$A57,'Process catalogue'!$AA$2:$AA$186,B$56) | C57: =COUNTIFS('Process catalogue'!$B$2:$B$186,$A57,'Process catalogue'!$AA$2:$AA$186,C$56) | D57: =COUNTIFS('Process catalogue'!$B$2:$B$186,$A57,'Process catalogue'!$AA$2:$AA$186,D$56) | E57: =COUNTIFS('Process catalogue'!$B$2:$B$186,$A57,'Process catalogue'!$AA$2:$AA$186,E$56) | F57: =COUNTIFS('Process catalogue'!$B$2:$B$186,$A57,'Process catalogue'!$AA$2:$AA$186,F$56) | G57: =SUM(B57:F57)
A58: Organisation & master data | B58: =COUNTIFS('Process catalogue'!$B$2:$B$186,$A58,'Process catalogue'!$AA$2:$AA$186,B$56) | C58: =COUNTIFS('Process catalogue'!$B$2:$B$186,$A58,'Process catalogue'!$AA$2:$AA$186,C$56) | D58: =COUNTIFS('Process catalogue'!$B$2:$B$186,$A58,'Process catalogue'!$AA$2:$AA$186,D$56) | E58: =COUNTIFS('Process catalogue'!$B$2:$B$186,$A58,'Process catalogue'!$AA$2:$AA$186,E$56) | F58: =COUNTIFS('Process catalogue'!$B$2:$B$186,$A58,'Process catalogue'!$AA$2:$AA$186,F$56) | G58: =SUM(B58:F58)
A59: Sales & CRM | B59: =COUNTIFS('Process catalogue'!$B$2:$B$186,$A59,'Process catalogue'!$AA$2:$AA$186,B$56) | C59: =COUNTIFS('Process catalogue'!$B$2:$B$186,$A59,'Process catalogue'!$AA$2:$AA$186,C$56) | D59: =COUNTIFS('Process catalogue'!$B$2:$B$186,$A59,'Process catalogue'!$AA$2:$AA$186,D$56) | E59: =COUNTIFS('Process catalogue'!$B$2:$B$186,$A59,'Process catalogue'!$AA$2:$AA$186,E$56) | F59: =COUNTIFS('Process catalogue'!$B$2:$B$186,$A59,'Process catalogue'!$AA$2:$AA$186,F$56) | G59: =SUM(B59:F59)
A60: Client & contract management | B60: =COUNTIFS('Process catalogue'!$B$2:$B$186,$A60,'Process catalogue'!$AA$2:$AA$186,B$56) | C60: =COUNTIFS('Process catalogue'!$B$2:$B$186,$A60,'Process catalogue'!$AA$2:$AA$186,C$56) | D60: =COUNTIFS('Process catalogue'!$B$2:$B$186,$A60,'Process catalogue'!$AA$2:$AA$186,D$56) | E60: =COUNTIFS('Process catalogue'!$B$2:$B$186,$A60,'Process catalogue'!$AA$2:$AA$186,E$56) | F60: =COUNTIFS('Process catalogue'!$B$2:$B$186,$A60,'Process catalogue'!$AA$2:$AA$186,F$56) | G60: =SUM(B60:F60)
A61: Project delivery | B61: =COUNTIFS('Process catalogue'!$B$2:$B$186,$A61,'Process catalogue'!$AA$2:$AA$186,B$56) | C61: =COUNTIFS('Process catalogue'!$B$2:$B$186,$A61,'Process catalogue'!$AA$2:$AA$186,C$56) | D61: =COUNTIFS('Process catalogue'!$B$2:$B$186,$A61,'Process catalogue'!$AA$2:$AA$186,D$56) | E61: =COUNTIFS('Process catalogue'!$B$2:$B$186,$A61,'Process catalogue'!$AA$2:$AA$186,E$56) | F61: =COUNTIFS('Process catalogue'!$B$2:$B$186,$A61,'Process catalogue'!$AA$2:$AA$186,F$56) | G61: =SUM(B61:F61)
A62: Task governance | B62: =COUNTIFS('Process catalogue'!$B$2:$B$186,$A62,'Process catalogue'!$AA$2:$AA$186,B$56) | C62: =COUNTIFS('Process catalogue'!$B$2:$B$186,$A62,'Process catalogue'!$AA$2:$AA$186,C$56) | D62: =COUNTIFS('Process catalogue'!$B$2:$B$186,$A62,'Process catalogue'!$AA$2:$AA$186,D$56) | E62: =COUNTIFS('Process catalogue'!$B$2:$B$186,$A62,'Process catalogue'!$AA$2:$AA$186,E$56) | F62: =COUNTIFS('Process catalogue'!$B$2:$B$186,$A62,'Process catalogue'!$AA$2:$AA$186,F$56) | G62: =SUM(B62:F62)
A63: Time & attendance | B63: =COUNTIFS('Process catalogue'!$B$2:$B$186,$A63,'Process catalogue'!$AA$2:$AA$186,B$56) | C63: =COUNTIFS('Process catalogue'!$B$2:$B$186,$A63,'Process catalogue'!$AA$2:$AA$186,C$56) | D63: =COUNTIFS('Process catalogue'!$B$2:$B$186,$A63,'Process catalogue'!$AA$2:$AA$186,D$56) | E63: =COUNTIFS('Process catalogue'!$B$2:$B$186,$A63,'Process catalogue'!$AA$2:$AA$186,E$56) | F63: =COUNTIFS('Process catalogue'!$B$2:$B$186,$A63,'Process catalogue'!$AA$2:$AA$186,F$56) | G63: =SUM(B63:F63)
A64: Documents & knowledge | B64: =COUNTIFS('Process catalogue'!$B$2:$B$186,$A64,'Process catalogue'!$AA$2:$AA$186,B$56) | C64: =COUNTIFS('Process catalogue'!$B$2:$B$186,$A64,'Process catalogue'!$AA$2:$AA$186,C$56) | D64: =COUNTIFS('Process catalogue'!$B$2:$B$186,$A64,'Process catalogue'!$AA$2:$AA$186,D$56) | E64: =COUNTIFS('Process catalogue'!$B$2:$B$186,$A64,'Process catalogue'!$AA$2:$AA$186,E$56) | F64: =COUNTIFS('Process catalogue'!$B$2:$B$186,$A64,'Process catalogue'!$AA$2:$AA$186,F$56) | G64: =SUM(B64:F64)
A65: People & HR | B65: =COUNTIFS('Process catalogue'!$B$2:$B$186,$A65,'Process catalogue'!$AA$2:$AA$186,B$56) | C65: =COUNTIFS('Process catalogue'!$B$2:$B$186,$A65,'Process catalogue'!$AA$2:$AA$186,C$56) | D65: =COUNTIFS('Process catalogue'!$B$2:$B$186,$A65,'Process catalogue'!$AA$2:$AA$186,D$56) | E65: =COUNTIFS('Process catalogue'!$B$2:$B$186,$A65,'Process catalogue'!$AA$2:$AA$186,E$56) | F65: =COUNTIFS('Process catalogue'!$B$2:$B$186,$A65,'Process catalogue'!$AA$2:$AA$186,F$56) | G65: =SUM(B65:F65)
A66: Payroll & compensation | B66: =COUNTIFS('Process catalogue'!$B$2:$B$186,$A66,'Process catalogue'!$AA$2:$AA$186,B$56) | C66: =COUNTIFS('Process catalogue'!$B$2:$B$186,$A66,'Process catalogue'!$AA$2:$AA$186,C$56) | D66: =COUNTIFS('Process catalogue'!$B$2:$B$186,$A66,'Process catalogue'!$AA$2:$AA$186,D$56) | E66: =COUNTIFS('Process catalogue'!$B$2:$B$186,$A66,'Process catalogue'!$AA$2:$AA$186,E$56) | F66: =COUNTIFS('Process catalogue'!$B$2:$B$186,$A66,'Process catalogue'!$AA$2:$AA$186,F$56) | G66: =SUM(B66:F66)
A67: Finance | B67: =COUNTIFS('Process catalogue'!$B$2:$B$186,$A67,'Process catalogue'!$AA$2:$AA$186,B$56) | C67: =COUNTIFS('Process catalogue'!$B$2:$B$186,$A67,'Process catalogue'!$AA$2:$AA$186,C$56) | D67: =COUNTIFS('Process catalogue'!$B$2:$B$186,$A67,'Process catalogue'!$AA$2:$AA$186,D$56) | E67: =COUNTIFS('Process catalogue'!$B$2:$B$186,$A67,'Process catalogue'!$AA$2:$AA$186,E$56) | F67: =COUNTIFS('Process catalogue'!$B$2:$B$186,$A67,'Process catalogue'!$AA$2:$AA$186,F$56) | G67: =SUM(B67:F67)
A68: Spend & procurement | B68: =COUNTIFS('Process catalogue'!$B$2:$B$186,$A68,'Process catalogue'!$AA$2:$AA$186,B$56) | C68: =COUNTIFS('Process catalogue'!$B$2:$B$186,$A68,'Process catalogue'!$AA$2:$AA$186,C$56) | D68: =COUNTIFS('Process catalogue'!$B$2:$B$186,$A68,'Process catalogue'!$AA$2:$AA$186,D$56) | E68: =COUNTIFS('Process catalogue'!$B$2:$B$186,$A68,'Process catalogue'!$AA$2:$AA$186,E$56) | F68: =COUNTIFS('Process catalogue'!$B$2:$B$186,$A68,'Process catalogue'!$AA$2:$AA$186,F$56) | G68: =SUM(B68:F68)
... A73: Access, master data & controls | B73: =COUNTIFS('Process catalogue'!$B$2:$B$186,$A73,'Process catalogue'!$AA$2:$AA$186,B$56) | C73: =COUNTIFS('Process catalogue'!$B$2:$B$186,$A73,'Process catalogue'!$AA$2:$AA$186,C$56) | D73: =COUNTIFS('Process catalogue'!$B$2:$B$186,$A73,'Process catalogue'!$AA$2:$AA$186,D$56) | E73: =COUNTIFS('Process catalogue'!$B$2:$B$186,$A73,'Process catalogue'!$AA$2:$AA$186,E$56) | F73: =COUNTIFS('Process catalogue'!$B$2:$B$186,$A73,'Process catalogue'!$AA$2:$AA$186,F$56) | G73: =SUM(B73:F73)
A74: Total | B74: =SUM(B57:B73) | C74: =SUM(C57:C73) | D74: =SUM(D57:D73) | E74: =SUM(E57:E73) | F74: =SUM(F57:F73) | G74: =SUM(G57:G73)
A75: Check: rows in Process catalogue | G75: =COUNTA('Process catalogue'!$A$2:$A$186)
A77: Involvement by role (live formulas)
A78: Role | B78: Involved | C78: Does (R) | D78: Approves (A) | E78: Consulted (C) | F78: Informed (I)
A79: Administrator | B79: =COUNTIF('Process catalogue'!$H$2:$H$186,"?") | C79: =COUNTIF('Process catalogue'!$H$2:$H$186,"R") | D79: =COUNTIF('Process catalogue'!$H$2:$H$186,"A") | E79: =COUNTIF('Process catalogue'!$H$2:$H$186,"C") | F79: =COUNTIF('Process catalogue'!$H$2:$H$186,"I")
A80: CEO | B80: =COUNTIF('Process catalogue'!$I$2:$I$186,"?") | C80: =COUNTIF('Process catalogue'!$I$2:$I$186,"R") | D80: =COUNTIF('Process catalogue'!$I$2:$I$186,"A") | E80: =COUNTIF('Process catalogue'!$I$2:$I$186,"C") | F80: =COUNTIF('Process catalogue'!$I$2:$I$186,"I")
A81: CTO | B81: =COUNTIF('Process catalogue'!$J$2:$J$186,"?") | C81: =COUNTIF('Process catalogue'!$J$2:$J$186,"R") | D81: =COUNTIF('Process catalogue'!$J$2:$J$186,"A") | E81: =COUNTIF('Process catalogue'!$J$2:$J$186,"C") | F81: =COUNTIF('Process catalogue'!$J$2:$J$186,"I")
A82: Project Manager | B82: =COUNTIF('Process catalogue'!$K$2:$K$186,"?") | C82: =COUNTIF('Process catalogue'!$K$2:$K$186,"R") | D82: =COUNTIF('Process catalogue'!$K$2:$K$186,"A") | E82: =COUNTIF('Process catalogue'!$K$2:$K$186,"C") | F82: =COUNTIF('Process catalogue'!$K$2:$K$186,"I")
A83: HR Manager | B83: =COUNTIF('Process catalogue'!$L$2:$L$186,"?") | C83: =COUNTIF('Process catalogue'!$L$2:$L$186,"R") | D83: =COUNTIF('Process catalogue'!$L$2:$L$186,"A") | E83: =COUNTIF('Process catalogue'!$L$2:$L$186,"C") | F83: =COUNTIF('Process catalogue'!$L$2:$L$186,"I")
A84: HR Executive | B84: =COUNTIF('Process catalogue'!$M$2:$M$186,"?") | C84: =COUNTIF('Process catalogue'!$M$2:$M$186,"R") | D84: =COUNTIF('Process catalogue'!$M$2:$M$186,"A") | E84: =COUNTIF('Process catalogue'!$M$2:$M$186,"C") | F84: =COUNTIF('Process catalogue'!$M$2:$M$186,"I")
A85: Sales Manager | B85: =COUNTIF('Process catalogue'!$N$2:$N$186,"?") | C85: =COUNTIF('Process catalogue'!$N$2:$N$186,"R") | D85: =COUNTIF('Process catalogue'!$N$2:$N$186,"A") | E85: =COUNTIF('Process catalogue'!$N$2:$N$186,"C") | F85: =COUNTIF('Process catalogue'!$N$2:$N$186,"I")
A86: Sales Executive | B86: =COUNTIF('Process catalogue'!$O$2:$O$186,"?") | C86: =COUNTIF('Process catalogue'!$O$2:$O$186,"R") | D86: =COUNTIF('Process catalogue'!$O$2:$O$186,"A") | E86: =COUNTIF('Process catalogue'!$O$2:$O$186,"C") | F86: =COUNTIF('Process catalogue'!$O$2:$O$186,"I")
A87: Employee | B87: =COUNTIF('Process catalogue'!$P$2:$P$186,"?") | C87: =COUNTIF('Process catalogue'!$P$2:$P$186,"R") | D87: =COUNTIF('Process catalogue'!$P$2:$P$186,"A") | E87: =COUNTIF('Process catalogue'!$P$2:$P$186,"C") | F87: =COUNTIF('Process catalogue'!$P$2:$P$186,"I")
A88: Line manager (any role with reports) | B88: =COUNTIF('Process catalogue'!$Q$2:$Q$186,"?") | C88: =COUNTIF('Process catalogue'!$Q$2:$Q$186,"R") | D88: =COUNTIF('Process catalogue'!$Q$2:$Q$186,"A") | E88: =COUNTIF('Process catalogue'!$Q$2:$Q$186,"C") | F88: =COUNTIF('Process catalogue'!$Q$2:$Q$186,"I")
A89: Platform super admin | B89: =COUNTIF('Process catalogue'!$R$2:$R$186,"?") | C89: =COUNTIF('Process catalogue'!$R$2:$R$186,"R") | D89: =COUNTIF('Process catalogue'!$R$2:$R$186,"A") | E89: =COUNTIF('Process catalogue'!$R$2:$R$186,"C") | F89: =COUNTIF('Process catalogue'!$R$2:$R$186,"I")
A90: Client (external) | B90: =COUNTIF('Process catalogue'!$S$2:$S$186,"?") | C90: =COUNTIF('Process catalogue'!$S$2:$S$186,"R") | D90: =COUNTIF('Process catalogue'!$S$2:$S$186,"A") | E90: =COUNTIF('Process catalogue'!$S$2:$S$186,"C") | F90: =COUNTIF('Process catalogue'!$S$2:$S$186,"I")
A92: Other sheets (rows)
A93: Role view | B93: =COUNTA('Role view'!$A$2:$A$957) | C93: rows
A94: Roles & permissions | B94: =COUNTA('Roles & permissions'!$B$2:$B$82) | C94: permissions
A95: Maker-checker | B95: =COUNTA('Maker-checker'!$A$2:$A$14) | C95: change types
A96: Approval workflows | B96: =COUNTA('Approval workflows'!$A$2:$A$8) | C96: workflow steps
A97: Setup & onboarding flow | B97: =COUNTA('Setup & onboarding flow'!$A$2:$A$15) | C97: steps
A98: Approvals & SLAs | B98: =COUNTA('Approvals & SLAs'!$A$2:$A$22) | C98: rows
A99: KPI dictionary | B99: =COUNTA('KPI dictionary'!$A$2:$A$50) | C99: rows
A100: Requested flows check | B100: =COUNTA('Requested flows check'!$A$2:$A$14) | C100: rows
A102: Sources
A103: Product code v4 (src/domain/permissionCatalog.ts PERMISSIONS and DEFAULT_ROLES, src/mock/makerChecker.ts, src/mock/workflows.ts, src/mock/seeds/access.ts, mock routes access / people / master, Setup screens, Create employee, First password and Changes screens) and specs (BRD/FSD business rules BR-01..27, settings, notifications NTF-01..17). The permission matrix and workflow chains were extracted by running the product code.
A104: Demo logins (password Seereon@123, all @seereon.co.in): santosh@ (CEO), debasish@ (Administrator), subhankar@ (Project Manager + margins.view, documents.view_all), priya@ (HR Manager), baishali@ (Sales Manager), subham@ (Sales Executive), hritesh@ and other developers (Employee). No demo user holds CTO or HR Executive.

Sheet Process catalogue
A1: ID | B1: Domain | C1: Sub-domain | D1: Process | E1: Purpose (why the business needs it) | F1: Trigger | G1: Steps | H1: Administrator | I1: CEO | J1: CTO | K1: Project Manager | L1: HR Manager | M1: HR Executive | N1: Sales Manager | O1: Sales Executive | P1: Employee | Q1: Line manager | R1: Platform SA | S1: Client | T1: Validations & business rules | U1: Data captured | V1: KPIs produced | W1: Dashboards / reports fed | X1: Notifications | Y1: Screen / route | Z1: Permission (v4) | AA1: Status | AB1: Notes / gaps
A2: WS-01 | B2: Workspace & access | C2: Tenancy | D2: Company sign-up and 14-day trial | E2: Lets a new company start using SeereonOS on its own, with its own isolated workspace. | F2: A company decides to try SeereonOS | G2: 1. Enter company name, your name, work email and password 2. Workspace is created with you as admin and a 14-day trial (up to 25 people) 3. Land on the onboarding checklist | H2: R | I2: I | R2: I | T2: Company and name required; valid work email; PASSWORD_WEAK (min 10 characters); USER_EMAIL_TAKEN. Trial = 14 days, 25-person cap. | U2: tenants, users, subscriptions (plan trial, status trialing) | V2: Tenant count, trials (platform) | W2: Platform tenant list | X2: NTF-11 trial ends in 3 days (catalogue only) | Y2: /signup | Z2: - | AA2: Extended | AB2: NTF-11 is defined in the spec but not raised by the product yet. v4: sign-up now provisions the nine default roles, organisation master data, the six approval workflows, system email templates and maker-checker (preselected, off) for the new workspace. The signer becomes Administrator.
A3: WS-02 | B3: Workspace & access | C3: Tenancy | D3: Onboarding checklist and sample data | E3: Gets a new workspace to first value fast: rules, calendar, people, first project, first timesheet week. | F3: First login after sign-up | G3: 1. Admin sees the checklist on Home: company settings, holidays, invite people, first project, first week 2. Optionally load sample data into an empty workspace 3. Dismiss or restore the checklist | H3: R | I3: I | L3: C | M3: I | T3: SAMPLE_NOT_EMPTY: sample data loads only into an empty workspace. | U3: onboarding state per tenant | V3: Setup completion | W3: CEO Home (onboarding card) | X3: - | Y3: /home, /onboarding | Z3: master.view | AA3: Extended | AB3: v4: superseded by the Setup checklist (SET-01, /setup) - org data, roles, workflows, people, emails.
A4: WS-03 | B4: Workspace & access | C4: Access | D4: Sign in, lockout and password reset | E4: Keeps accounts safe while letting people recover access themselves. | F4: Any user opens the app or forgets a password | G4: 1. Sign in with email and password 2. After 5 failed attempts the account locks for 15 minutes 3. Request a reset link (always accepted, link valid 60 minutes) 4. Set a new password | H4: R | I4: R | J4: R | K4: R | L4: R | M4: R | N4: R | O4: R | P4: R | R4: R | T4: LOGIN_FAILED (attempts left shown); LOGIN_LOCKED (security.lockout_attempts 5 / lockout_minutes 15); USER_DEACTIVATED; TENANT_SUSPENDED; RESET_EXPIRED; PASSWORD_WEAK (security.password_min_length 10). | U4: users.last_login_at, password reset tokens | V4: - | W4: - | X4: NTF-01 password reset (email) | Y4: /login, /reset-password | Z4: - | AA4: Extended | AB4: v4: one login for every role; screens and actions follow effective permissions (ACC-09). A temporary password forces a password change first (ACC-05, PASSWORD_CHANGE_REQUIRED).
A5: WS-04 | B5: Workspace & access | C5: People | D5: Invite people (single or bulk CSV) and accept invitation | E5: Brings every employee into the system with the right role and manager from day one. | F5: New joiner, or initial roll-out | G5: 1. Admin enters name, email, role and reports-to (or pastes CSV: name,email,role,reports_to_email; max 200 rows) 2. Invite link is emailed (valid 7 days); resend or revoke while pending 3. Invitee opens link, sets name and password, lands on their role dashboard | H5: R | I5: I | L5: A | M5: R | P5: R | Q5: I | T5: USER_EMAIL_TAKEN; SEATS_FULL (trial 25 people or paid seats); bulk import is all-or-nothing (any row error = nothing invited); INVITE_ACCEPTED (cannot revoke accepted); INVITE_EXPIRED; PASSWORD_WEAK. | U5: invites (email, name, role, reports_to_id, token, expires_at, accepted_at), users | V5: Headcount, pending invites | W5: People list; HR dashboard headcount | X5: NTF-02 invited (email) | Y5: /people, /invite/:token | Z5: R: (none); A: employees.create | AA5: Extended | AB5: Hiring a candidate creates the invite automatically (see HR-05). v4: superseded by Create employee (ACC-04) for single hires; invitations remain for bulk CSV and for hired candidates (HR-05). Gated by employees.create.
A6: WS-05 | B6: Workspace & access | C6: People | D6: Roles, reporting lines and access grants | E6: Decides who sees and approves what: the reports-to line drives timesheet, leave, expense and task approvals. | F6: Joiner, promotion, team change | G6: 1. Admin opens People and edits role (Admin, Project manager, Sales, HR & operations, Employee), reports-to and department 2. Optionally grant "margins" (PMs) or "salaries" (PMs, HR & operations) 3. Change takes effect immediately for approvals and visibility | H6: R | I6: A | J6: I | L6: C | P6: I | Q6: C | T6: LAST_ADMIN (at least one active admin); USER_REPORTS_LOOP (no self or circular reporting); GRANT_UNUSED warning; BR-07 approver = reports-to or active delegate; top person auto-approved. | U6: users (role, reports_to_id, department, grants) | V6: Span of control | W6: Team, Approvals inbox routing | X6: - | Y6: /people | Z6: users.manage | AA6: Extended | AB6: v4: the five hard-coded roles and grants are replaced by roles as data (ACC-01) and per-user extra / revoked permissions (ACC-03); grants "margins" / "salaries" became margins.view / cost_rates.view; LAST_ADMIN became LOCKOUT; role and access changes are maker-checked in Seereon.
A7: WS-06 | B7: Workspace & access | C7: People | D7: Approval delegation (cover during leave) | E7: Approvals never stall when a manager is away. | F7: Manager goes on leave or travel | G7: 1. Choose the delegate, from and to dates and a short reason 2. Delegate sees the manager's timesheet and leave approvals in their inbox for that period 3. Delete the delegation early if plans change | I7: R | J7: R | K7: R | Q7: R | T7: Admin, PM, HR & operations and Sales line managers can delegate (delegations.manage). Delegate must be active and not the delegator; both dates required; end on/after start and not in the past; reason min 3 characters; DELEGATION_OVERLAP. | U7: delegations (from_user_id, to_user_id, from_on, to_on, reason) | V7: Approval KPI stays clean | W7: Approvals inbox | X7: NTF-04 copies to delegate (leave) | Y7: /settings/delegations | Z7: delegations.manage | AA7: Extended | AB7: v3 opens delegation to HR & operations and Sales line managers (previously Admin and PM only).
A8: WS-07 | B8: Workspace & access | C8: People | D8: View as another role | E8: Lets the CEO check exactly what each role sees before rolling out. | F8: Admin wants to verify a role view | G8: 1. Admin picks "View as" a role or person 2. App shows that view with a read-only banner 3. Exit view-as to return | H8: R | I8: I | T8: All writes return 403 while view-as is active (enforced by the server). | U8: - | V8: - | W8: - | X8: - | Y8: Top bar (admin) | Z8: view_as | AA8: Extended | AB8: v4: any role, including custom roles, can be previewed; needs view_as (ACC-08).
A9: WS-08 | B9: Workspace & access | C9: Access | D9: Security, two-step verification and personal settings | E9: Protects admin accounts and lets each person manage their own profile and sessions. | F9: User setup or company security policy | G9: 1. Turn on two-step verification (TOTP) with a 6-digit code 2. Review and end other sessions 3. Change password, profile, avatar and theme preference 4. Admin can require 2FA for admins and set company theme/logo | H9: R | I9: A | J9: R | K9: R | L9: R | M9: R | N9: R | O9: R | P9: R | Q9: R | R9: R | T9: TWO_FACTOR_CODE; TWO_FACTOR_REQUIRED (security.require_2fa_admins); TWO_FACTOR_PENDING warning; PASSWORD_WRONG; session idle 60 min; logo PNG/SVG/JPG/WebP up to 1 MB (FILE_REJECTED); colours must be hex. | U9: users.two_factor, sessions, prefs, tenant.theme, logo | V9: - | W9: - | X9: - | Y9: /settings/security, /settings/profile, /settings/appearance | Z9: R: (none); A: settings.edit | AA9: Live | AB9: -
A10: WS-09 | B10: Workspace & access | C10: People | D10: Deactivate or reactivate a person | E10: Removes access on exit without losing their history, hours or approvals. | F10: Exit completed, or re-joining | G10: 1. Admin deactivates the person (or the exit checklist does it after the last day) 2. Their reports are flagged to be re-assigned 3. Reactivate if they return | H10: R | I10: I | L10: A | M10: C | Q10: C | T10: LAST_ADMIN (cannot deactivate yourself or the last admin); REPORTS_ORPHANED warning; deactivated users cannot sign in (USER_DEACTIVATED). | U10: users.status | V10: Headcount, attrition | W10: HR dashboard | X10: - | Y10: /people | Z10: employees.deactivate | AA10: Extended | AB10: v4: needs employees.deactivate; PERMISSION_ESCALATION and LOCKOUT protect access administrators; maker-checked when "Employee creation & deactivation" is on (ACC-07).
A11: WS-10 | B11: Workspace & access | C11: Data | D11: Full data export | E11: The company owns its data and can take a complete copy at any time. | F11: Audit, backup or migration | G11: 1. Admin requests an export 2. System prepares it and notifies when ready 3. Download within 24 hours | H11: R | I11: I | T11: RATE_LIMITED (several exports in a minute); EXPORT_EXPIRED after 24 hours. | U11: data_exports | V11: - | W11: - | X11: NTF-17 export ready | Y11: /settings/data | Z11: data.export | AA11: Live | AB11: -
A12: WS-11 | B12: Workspace & access | C12: Subscription | D12: Plan, seats and payment | E12: Pays for SeereonOS per user and keeps seats in line with headcount. | F12: Trial ending, or headcount change | G12: 1. Admin compares plans (Starter Rs 399, Growth Rs 499, Scale Rs 699 per user per month + 18% GST) 2. Choose seats and pay by card or UPI (Razorpay) 3. Add seats later; download billing invoices | H12: R | I12: I | R12: I | T12: SEATS_BELOW_USAGE (seats cannot be below people + pending invites); PLAN_LIMIT; PAYMENT_FAILED; read-only tenant can open Billing only, everything else returns 402 TENANT_READ_ONLY. | U12: subscriptions, billing_invoices | V12: Seat usage | W12: Billing | X12: NTF-16 payment failed | Y12: /billing | Z12: billing.manage | AA12: Live | AB12: -
A13: WS-12 | B13: Workspace & access | C13: Platform | D13: Platform tenant administration | E13: Lets SeereonOS operations support customers without ever seeing their business data. | F13: Support request, trial extension, non-payment | G13: 1. Platform admin opens the tenant list 2. Extend a trial by 1-30 days, suspend or reactivate with a reason 3. Every action is audited | R13: R | T13: Reason min 5 characters (audited); extend 1-30 days; TENANT_ACTIVE (paid tenants have no trial); TENANT_SUSPENDED. | U13: tenants.status, trial_ends_on | V13: Active tenants, trials | W13: Platform tenant list | X13: - | Y13: /admin | Z13: - | AA13: Live | AB13: -
A14: WS-13 | B14: Workspace & access | C14: Access | D14: Single sign-on and custom roles | E14: Larger customers expect Google / Microsoft login and roles beyond the five built-in ones. | F14: Enterprise customer onboarding | G14: 1. Admin connects Google Workspace or Microsoft Entra ID 2. People sign in with company accounts; password login optional 3. Admin clones a built-in role and adjusts permissions | H14: R | I14: I | L14: C | M14: I | P14: I | R14: C | T14: - | U14: - | V14: - | W14: - | X14: - | Y14: - | Z14: - (planned) | AA14: Planned | AB14: Recommendation: add Google/Microsoft SSO first (most Indian IT firms use Google Workspace); custom roles after (spec future scope). v4: custom roles are delivered (ACC-01, ACC-02). Recommendation stands for Google / Microsoft SSO.
A15: ORG-01 | B15: Organisation & master data | C15: Company rules | D15: Company rules and settings | E15: Sets the rules every calculation uses: working hours, approval SLA, margin floor, pay rules, security. | F15: Set-up, or a policy change | G15: 1. Admin opens Company settings 2. Edit company name, time zone, FY start, weekly off, Saturday rule, min/max hours, timesheet step, SLA, margin floor, stale-deal days, pay rules, AI on/off 3. Save (each setting shows its effect inline) | H15: R | I15: I | J15: C | K15: C | L15: C | M15: I | T15: Every setting has a fixed range (e.g. min hours 1-12, SLA 1-10 days, variable 0-50%); max hours >= min hours; Saturdays off must be 1st-5th; STALE if someone else saved first. | U15: tenant.settings (calendar.*, timesheet.*, approval.*, pay.*, projects.*, allocation.*, sales.*, security.*, ai.enabled) | V15: Drives all KPIs | W15: All | X15: - | Y15: /settings/company | Z15: settings.edit | AA15: Extended | AB15: v4: "Company settings" is listed as a maker-checker change type, but saving company settings applies directly in this build (not routed through propose).
A16: ORG-02 | B16: Organisation & master data | C16: Calendar | D16: Working calendar and holidays | E16: Defines working days, which drive costs, SLAs, timeliness, leave and pay. | F16: Start of year, or a new holiday announced | G16: 1. Admin adds holidays one by one or imports CSV (date,name[,optional]) 2. Edit or delete a holiday 3. Calendar applies to timesheets, SLA, payroll and task timeliness | H16: R | I16: I | L16: R | M16: I | P16: I | T16: BR-01 working day = not weekly off, not holiday, not approved leave; BR-02 Sunday off, Saturday rule; HOLIDAY_EXISTS; CSV import all-or-nothing; PAYROLL_FINAL warning if month already paid. | U16: holidays (date, name, optional) | V16: Working days per month | W16: Timesheet, Leave, Payroll | X16: - | Y16: /settings/holidays | Z16: holidays.edit | AA16: Extended | AB16: One calendar per company; location-wise calendars are future scope. v4: HR Manager can maintain holidays (holidays.edit).
A17: ORG-03 | B17: Organisation & master data | C17: Cost | D17: Cost rates (CTC history) | E17: Turns every approved hour into cost, so project margins and payroll are exact. | F17: Joining, increment (auto-created when an appraisal with an increment is completed), or correction | G17: 1. Admin adds a rate: monthly CTC, variable %, sales target, effective-from 2. History is append-only; the rate valid on each work date is used 3. Future rates can be removed | H17: C | I17: A | L17: C | T17: BR-23 cost/hour = monthly CTC / (working days x min hours); MONEY_INVALID; variable 0-50%; RATE_PERIOD_LOCKED (month already paid, or not after latest); RATE_EXISTS; RATE_BACKDATED warning. | U17: cost_rates (user_id, monthly_ctc_paise, variable_pct, sales_target_paise, effective_from) | V17: Cost per hour, project cost, margin | W17: Project money tab, P&L, Payroll | X17: - | Y17: /settings/cost-rates | Z17: cost_rates.edit | AA17: Extended | AB17: v4: visible to holders of cost_rates.view (CEO, Administrator, HR Manager by default). Salary / cost-rate changes are maker-checked in Seereon (entity cost_rate, needs cost_rates.edit). Only CEO and Administrator hold cost_rates.edit, so one proposes and the other checks. Create employee can carry a CTC (CTC_NEEDS_APPROVAL when salaries are checked).
A18: ORG-04 | B18: Organisation & master data | C18: Vendors | D18: Vendor master (onboard, block, unblock) | E18: One verified list of suppliers so purchases and bills are clean and GST-compliant. | F18: New supplier, or a supplier problem | G18: 1. Admin / HR & operations adds vendor: name, category, GSTIN, PAN, contact, payment terms 2. Block a vendor with a reason; unblock when resolved 3. Blocked vendors cannot get new POs | I18: A | L18: R | M18: I | T18: DUPLICATE_VENDOR; VAL_GSTIN (15 characters, valid structure); VAL_PAN (10 characters, must match GSTIN chars 3-12); payment terms 0-180 days; block reason min 5 characters. | U18: vendors (name, category, gstin, pan, contact, payment_terms_days, status) | V18: Vendor count, spend by vendor | W18: Purchases & vendors | X18: - | Y18: /purchases (Vendors tab) | Z18: procurement.manage | AA18: Extended | AB18: New in v3. v4: adding a vendor, or changing its tax or bank details, is maker-checked in Seereon (entity vendor, needs procurement.manage); other vendor edits apply directly.
A19: ORG-05 | B19: Organisation & master data | C19: Catalogues | D19: Product, category and service catalogue maintenance | E19: Lets each company define its own products, ledger categories and ops categories. | F19: New product launch or new cost head | G19: 1. Admin edits products used in Sales, ledger income/expense categories and ops areas 2. Retire old entries without breaking history | H19: R | I19: I | L19: C | M19: I | N19: C | O19: C | T19: - | U19: - | V19: - | W19: - | X19: - | Y19: - | Z19: - (planned) | AA19: Planned | AB19: Today products (EduReon, SeerHR, LeadSync, Munim AI, MineReon, SAP consulting, Custom software) and categories are fixed in code. Recommendation: make them tenant-editable (spec F-SET-03).
A20: ORG-06 | B20: Organisation & master data | C20: Entities | D20: Multi-entity and multi-currency | E20: Needed once Seereon bills overseas clients (AlUla, ZooPlus) in USD/SAR/EUR or opens a second legal entity. | F20: Foreign client or new entity | G20: 1. Define legal entities with their own GSTIN and books 2. Record invoices and payments in client currency with an exchange rate 3. Consolidate P&L in INR | I20: A | N20: C | O20: C | T20: - | U20: - | V20: - | W20: - | X20: - | Y20: - | Z20: - (planned) | AA20: Planned | AB20: Recommendation: start with currency on invoice + realised FX gain/loss; full multi-entity later (debt TD-A06).
A21: SAL-01 | B21: Sales & CRM | C21: Pipeline | D21: Lead capture | E21: Every opportunity is recorded with a value and an owner, so the pipeline is real. | F21: Enquiry, referral (e.g. BNI), event, cold call | G21: 1. Sales creates a deal: title, client, contact, product, source, value, MRR, expected close, owner 2. Deal starts in an open stage (Lead) 3. Client record is created automatically if new | I21: I | N21: A | O21: R | T21: Required fields; MONEY_INVALID (value >= 0); source and product from list; owner must be Sales or Admin; DEAL_STAGE (a new lead cannot start Won/Lost). | U21: deals (title, client, contact, phone, email, product, source, owner_id, stage, value_paise, mrr_paise, expected_close) | V21: Open value, new leads per week | W21: Sales Home, CEO Home, Scorecard (new leads) | X21: - | Y21: /sales | Z21: deals.edit_own | AA21: Live | AB21: -
A22: SAL-02 | B22: Sales & CRM | C22: Pipeline | D22: Qualification, demo, proposal and negotiation | E22: Moves deals through clear stages with a probability, so the forecast is weighted and honest. | F22: Deal progresses | G22: 1. Drag the deal on the kanban: Lead (10%) > Qualified (20%) > Demo (35%) > Proposal (50%) > Negotiation (70%) 2. Set the next step and date 3. Stage history is kept automatically | I22: I | N22: A | O22: R | S22: C | T22: DEAL_STAGE (valid stage); closed deals cannot be edited except by Admin. | U22: deals.stage, next_step_on; deal_stage_history | V22: Weighted pipeline, funnel | W22: Sales Home (pipeline by stage), CEO Home (revenue ahead) | X22: - | Y22: /sales, /sales/:id | Z22: deals.edit_own | AA22: Live | AB22: Proposals are logged as activities; there is no quotation document builder yet (see SAL-08).
A23: SAL-03 | B23: Sales & CRM | C23: Activity | D23: Log sales activities and next steps | E23: Proves follow-up effort and keeps deals from going quiet. | F23: Call, meeting, demo, email, proposal or follow-up done | G23: 1. Open the deal and log the activity type, date and what happened 2. Set the next step and its date 3. Last-activity date resets the stale clock | I23: I | N23: R | O23: R | T23: Type required; note min 3 characters; activities cannot be in the future (use next step for plans). | U23: deal_activities (deal_id, date, type, note, by) | V23: Activities per week (target 15), follow-ups overdue | W23: Sales Home (recent activity), Scorecard (activities, follow-ups) | X23: - | Y23: /sales/:id | Z23: deals.edit_own | AA23: Live | AB23: -
A24: SAL-04 | B24: Sales & CRM | C24: Closing | D24: Close won and create the project | E24: Hands a won deal straight to delivery with no re-typing, and credits the seller. | F24: Client confirms the order | G24: 1. Move the deal to Won (value must be above zero); won date is stamped 2. Click Create project: name, client, contract value, type, dates, PM 3. Project is linked to the deal; seller's achieved target updates | I24: I | J24: C | K24: C | N24: A | O24: R | T24: DEAL_STAGE (add value before Won); DEAL_HAS_PROJECT (one project per deal); only Admin can move a deal out of Won/Lost; BR-16 achieved = value of deals won that month by owner. | U24: deals.won_on, project_id; projects (deal_id) | V24: Won value, win rate, avg cycle days | W24: Sales Home, CEO Home, Compensation | X24: NTF-14 to PM (project assigned) | Y24: /sales/:id | Z24: deals.edit_own | AA24: Live | AB24: -
A25: SAL-05 | B25: Sales & CRM | C25: Closing | D25: Close lost with reason | E25: Every lost deal teaches something and is counted as lost revenue. | F25: Client declines or goes silent | G25: 1. Move the deal to Lost and record why 2. Deal value appears automatically in the Lost revenue register 3. Win rate updates | I25: I | N25: A | O25: R | T25: DEAL_STAGE: reason is mandatory ("that is how the win rate improves"); only Admin can reopen. | U25: deals.lost_on, lost_reason; deal_stage_history.reason | V25: Win rate = won / (won + lost); lost value by reason | W25: Sales performance, Lost revenue | X25: - | Y25: /sales | Z25: deals.edit_own | AA25: Extended | AB25: v3 adds the automatic lost-deal row in the Lost revenue register (REV-02).
A26: SAL-06 | B26: Sales & CRM | C26: Hygiene | D26: Stale deal follow-up | E26: Stops the pipeline from being inflated by dead deals. | F26: No activity for 14 days (sales.stale_deal_days) | G26: 1. System flags the deal stale and notifies the owner once a day 2. Owner logs an activity, or closes the deal 3. CEO sees stale deals and value at stake | I26: I | N26: R | O26: R | T26: Stale = open deal with no activity for sales.stale_deal_days (default 14). | U26: deals.last_activity_on | V26: Stale count, value at stake | W26: Insights > Stale deals, CEO Home, Sales Home (deals needing action) | X26: NTF-12 deal stale | Y26: /insights/stale_deals | Z26: deals.edit_own | AA26: Live | AB26: -
A27: SAL-07 | B27: Sales & CRM | C27: Performance | D27: Sales performance review | E27: Shows each seller's results against cost, so the sales team pays for itself. | F27: Monthly / quarterly review | G27: 1. Open Sales performance and choose the period 2. Review per person: open value, weighted value, won, win rate, days to close, activities, cost vs closed 3. Review 6-month target vs achieved | I27: I | N27: A | O27: R | Q27: C | T27: Admin sees all sellers; a seller sees only their own (sales.performance_own). | U27: deals, deal_activities, cost_rates | V27: Win rate, weighted pipeline, avg cycle days, cost vs closed, achievement % | W27: Sales performance, Sales Home | X27: - | Y27: /sales/performance | Z27: R: sales.performance_own; A: sales.performance_all | AA27: Live | AB27: -
A28: SAL-08 | B28: Sales & CRM | C28: Proposal | D28: Quotation and estimate builder | E28: Produces consistent, margin-safe quotes from a rate card and effort estimate. | F28: Deal reaches Proposal | G28: 1. Pick a template (fixed price, T&M, AMS retainer) and rate card 2. Estimate effort by phase/role; system shows cost, price and margin vs floor 3. Generate a branded PDF quote with GST; version it 4. On Won, convert the estimate into project milestones and budget | I28: I | J28: C | K28: C | N28: A | O28: R | S28: I | T28: - | U28: - | V28: - | W28: - | X28: - | Y28: - | Z28: - (planned) | AA28: Planned | AB28: Recommendation: high value for SAP consulting; reuse cost rates and the margin floor (25%) to block under-priced quotes.
A29: SAL-09 | B29: Sales & CRM | C29: Lead capture | D29: Web and email lead capture | E29: Captures website and email enquiries automatically so none are missed. | F29: Website form or enquiry email | G29: 1. Website form posts to SeereonOS 2. Lead created with source Website and auto-assigned owner 3. Owner notified to respond within a set time | I29: I | N29: R | O29: R | T29: - | U29: - | V29: - | W29: - | X29: - | Y29: - | Z29: - (planned) | AA29: Planned | AB29: Recommendation: a public form endpoint plus first-response SLA tracking.
A30: CLI-01 | B30: Client & contract management | C30: Clients | D30: Client master | E30: One record per client with commercial terms, so billing, health and history line up. | F30: Deal won, project created, or manual entry | G30: 1. Sales/Admin creates or edits the client: name, industry, country, GSTIN, billing address, contact, owner, payment terms 2. Clients are also created automatically from deals and projects 3. Status follows the data (prospect, active, dormant); churned is set by hand | I30: I | J30: I | K30: I | N30: A | O30: R | T30: VAL_REQUIRED name; DUPLICATE_CLIENT; VAL_GSTIN (15 characters, blank for overseas); VAL_EMAIL; payment terms 0-180 days; VAL_STATUS. | U30: clients (name, industry, country, gstin, billing_address, primary_contact, owner_id, status, payment_terms_days, health) | V30: Active clients, billed FY, outstanding | W30: Clients & contracts | X30: - | Y30: /clients, /clients/:id | Z30: clients.manage | AA30: New in v3 | AB30: -
A31: CLI-02 | B31: Client & contract management | C31: Contracts | D31: Contract register | E31: Keeps every MSA, SOW, AMC, licence, NDA and retainer with value, dates and file. | F31: Contract signed | G31: 1. Open the client and add a contract: title, type, value, start, end, renewal date, auto-renew, file 2. Link it to a project if relevant 3. Terminate when ended early; only drafts can be deleted | I31: I | J31: C | K31: C | N31: A | O31: R | S31: I | T31: Title and type required; VAL_AMOUNT >= 0; dates required; DATE_RANGE (end after start; renewal inside term); file up to 10 MB; CONTRACT_LOCKED (only drafts deleted); status draft/active/terminated, expiry computed. | U31: contracts (client_id, project_id, title, kind, value_paise, start_on, end_on, renewal_on, auto_renew, status, file_id) | V31: Contract value, renewals due | W31: Clients & contracts | X31: - | Y31: /clients/:id | Z31: clients.manage | AA31: New in v3 | AB31: -
A32: CLI-03 | B32: Client & contract management | C32: Contracts | D32: Contract renewal | E32: No AMC or licence renewal is missed: renewals are recurring revenue. | F32: Contract enters the 60-day renewal window | G32: 1. Contract shows as Expiring 60 days before renewal/end 2. Account owner is notified once 3. Renew for 1-60 months with new value (creates a linked new contract) or let it expire | I32: I | N32: A | O32: R | S32: C | T32: Renewal window 60 days; renew 1-60 months; INVALID_STATE (already renewed/terminated); VAL_AMOUNT. | U32: contracts (renewed_from, reminded_on) | V32: Renewals due in 60 days and their value | W32: Clients & contracts (renewals) | X32: NTF-13 contract renewal due | Y32: /clients | Z32: clients.manage | AA32: New in v3 | AB32: -
A33: CLI-04 | B33: Client & contract management | C33: Health | D33: Client health and 360 view | E33: Flags clients at risk before the relationship or the cash suffers. | F33: Continuous (recomputed on view) | G33: 1. System scores each client: overdue invoices + project health 2. Client page shows projects, invoices, billed FY, outstanding, overdue, contracts, deals and lost revenue 3. Owner acts on the reasons shown | I33: I | J33: I | K33: I | N33: A | O33: R | T33: At risk = invoice overdue > 60 days, or a project NPA / off track. Watch = any amount overdue, or a project at risk / on hold. Good otherwise. | U33: clients.health (computed), health_reasons | V33: Clients at risk, outstanding, leakage per client | W33: Clients & contracts, CEO (via clients) | X33: - | Y33: /clients/:id | Z33: clients.manage | AA33: New in v3 | AB33: -
A34: CLI-05 | B34: Client & contract management | C34: Client portal | D34: Client portal and deliverable sign-off | E34: Clients see progress and approve deliverables and change requests online, with a dated record. | F34: Milestone ready for acceptance, or CR raised | G34: 1. Client user logs in to a portal limited to their projects 2. Reviews milestone progress and documents 3. Accepts or rejects deliverables / CRs with comments; acceptance can trigger invoicing | I34: I | J34: R | K34: R | S34: R | T34: - | U34: - | V34: - | W34: - | X34: - | Y34: - | Z34: - (planned) | AA34: Planned | AB34: Today a money-free client view exists for the PM to share (DEL-10). Recommendation: extend it into a login-based portal with sign-off (spec future scope).
A35: CLI-06 | B35: Client & contract management | C35: Contracts | D35: Contract e-signature | E35: Speeds up SOW/NDA signing and stores the signed copy against the contract. | F35: Contract ready to sign | G35: 1. Send the contract for e-sign (Aadhaar e-sign / DocuSign-type provider) 2. Track status; signed PDF stored automatically 3. Contract becomes Active on signature | I35: I | N35: A | O35: R | S35: R | T35: - | U35: - | V35: - | W35: - | X35: - | Y35: - | Z35: - (planned) | AA35: Planned | AB35: Recommendation: integrate an Indian e-sign provider; keep the audit certificate with the contract.
A36: CLI-07 | B36: Client & contract management | C36: Satisfaction | D36: Customer satisfaction (CSAT / NPS) | E36: Measures how clients feel, not just what they pay; early warning for churn. | F36: Milestone accepted, project closed, or quarterly | G36: 1. System sends a short survey to the client contact 2. Scores and comments are stored on the client and project 3. Low scores alert the account owner and PM | I36: I | J36: C | K36: C | N36: R | O36: R | S36: R | T36: - | U36: - | V36: - | W36: - | X36: - | Y36: - | Z36: - (planned) | AA36: Planned | AB36: Recommendation: feed CSAT into client health and PM appraisals.
A37: DEL-01 | B37: Project delivery | C37: Set-up | D37: Create a project | E37: Every engagement gets a code, PM, value, billing model and plan, so hours and money link to it. | F37: Deal won, internal initiative, or AMS renewal | G37: 1. Admin/PM creates the project: name, client, type (Product, Service, SaaS, AMS), billing model (fixed, T&M, subscription, AMS retainer), revenue stream, PM, dates, contract value 2. Optionally add first milestones with end dates and billing amounts 3. Code is assigned automatically (PRJ-014 style) and the PM is notified | I37: I | J37: A | K37: R | N37: C | O37: C | T37: Type, billing model, stream, PM required; DATE_RANGE; milestone ends must run in order inside the project; MS_BILLING_OVER warning if milestone billing exceeds contract value; BR-18 types. | U37: projects (code, name, client, type, status, pm_id, start_on, end_on, contract_value_paise, billing_model, stream, deal_id, baseline_end_on) | V37: Active projects | W37: Projects list, CEO Home, PM Home | X37: NTF-14 "You manage PRJ-xxx" | Y37: /projects | Z37: projects.create | AA37: Live | AB37: -
A38: DEL-02 | B38: Project delivery | C38: Planning | D38: Milestones: plan, baseline and slip | E38: Milestones are the billing and delivery checkpoints; slips must be visible. | F38: Project planning or re-planning | G38: 1. PM adds milestones M1, M2... with planned start/end and billing amount 2. Baseline end is kept; moving a date shows the slip in days 3. Empty milestones are removed after 7 days unless invoiced | I38: I | J38: A | K38: R | P38: I | S38: I | T38: BR-19 numbering never reused; MS_OUTSIDE_PROJECT and MS_SLIP warnings; MS_BILLING_OVER warning; MS_INVOICED (billing amount fixed, cannot delete, BR-21); BR-20 empty milestone auto-deleted after projects.empty_milestone_days (7). | U38: milestones (no, name, planned_start, planned_end, baseline_end, billing_amount_paise, billing_status, achieved_on) | V38: Milestones on time %, slip days | W38: PM Home (upcoming milestones), CEO Home (milestones due 30 days) | X38: NTF-15 milestone auto-deleted / deleted | Y38: /projects/:id/wbs | Z38: projects.edit | AA38: Live | AB38: -
A39: DEL-03 | B39: Project delivery | C39: Planning | D39: Build the WBS (tasks, owners, estimates, dependencies) | E39: Breaks work into owned, estimated, dated tasks: the basis for timesheets, cost and timeliness. | F39: Project planning | G39: 1. PM adds tasks inline under a milestone (WBS code 2.3): title, owner, backup, estimate, start, due, complexity, priority, optional reviewer 2. Set dependencies between tasks 3. Owner is notified; tasks appear in My tasks | I39: I | J39: A | K39: R | P39: I | T39: Title under 200; estimate 0-999 h; DATE_RANGE; backup must differ from owner; TASK_SELF_REVIEW (reviewer is not the owner); DEP_CYCLE; dependencies same project; TASK_AFTER_MILESTONE warning; TASK_HAS_HOURS (cannot delete a task with logged hours). | U39: tasks (no, title, owner_id, backup_id, est_hours, start_on, due_on, complexity, priority, reviewer_id), task_dependencies | V39: Estimate, effort ratio, progress | W39: Project WBS, My tasks | X39: NTF-14 task assigned | Y39: /projects/:id/wbs | Z39: projects.edit|tasks.edit | AA39: Extended | AB39: v3 adds reviewer, priority and the review flow (TSK-05..10).
A40: DEL-04 | B40: Project delivery | C40: Planning | D40: Import a WBS from Excel/CSV | E40: Loads a full plan in minutes instead of typing it. | F40: New project with an existing plan | G40: 1. Download the template 2. Upload or paste the file; preview shows row errors 3. Commit: all rows or nothing; owners notified of their tasks | I40: I | J40: A | K40: R | P40: I | T40: WBS_INVALID (header missing, too many rows, preview expired, rows with errors); STALE if the WBS changed since preview. | U40: tasks, milestones | V40: - | W40: Project WBS | X40: NTF-14 (one per owner) | Y40: /projects/:id/import | Z40: projects.edit | AA40: Live | AB40: -
A41: DEL-05 | B41: Project delivery | C41: Resourcing | D41: Allocate people to milestones | E41: Plans who works where, at what %, so over- and under-loading is visible before it hurts. | F41: Planning or re-planning | G41: 1. PM adds allocation rows: person, milestone, %, from, to 2. System warns if a person goes above 100% on any day 3. Resource load for the next 10 working days updates | I41: I | J41: A | K41: R | P41: I | Q41: C | T41: BR-22 milestone, start and end required (ALLOC_INVALID); 1-100%; dates inside the project; ALLOC_OVER warning, or block when allocation.block_over is on. | U41: allocations (project_id, milestone_id, user_id, pct, from_on, to_on) | V41: Utilisation, allocation outliers (<80% / >110%) | W41: PM Home (resource load), Insights > Allocation, CEO Home (utilisation) | X41: - | Y41: /projects/:id/team | Z41: allocation.edit | AA41: Live | AB41: -
A42: DEL-06 | B42: Project delivery | C42: Scheduling | D42: Schedule, Gantt and critical path | E42: Shows which tasks really drive the end date and what is already breaching. | F42: Weekly PM review | G42: 1. Open the schedule: bars, dependency arrows, today line 2. Critical path and breach list with one-click actions (move, reassign, unblock) 3. Check P50/P80 finish predictions | I42: I | J42: I | K42: R | T42: Task cannot start while a dependency is open (TASK_BLOCKED). | U42: tasks, task_dependencies | V42: SPI, predicted finish (P50/P80), chance on time | W42: Project schedule, Insights > Predictions | X42: - | Y42: /projects/:id/schedule | Z42: projects.edit | AA42: Live | AB42: -
A43: DEL-07 | B43: Project delivery | C43: Governance | D43: Project status lifecycle | E43: Keeps an honest status with reasons and history (Initiated, Active, On hold, NPA, Completed, Closed). | F43: Project starts, pauses, stalls or ends | G43: 1. PM/Admin changes status from the status control 2. On hold, NPA and Closed need a reason 3. History is kept; hours cannot be booked after closure | I43: I | J43: A | K43: R | P43: I | T43: BR-17; BR_17_REASON_REQUIRED (min 5 characters); SAME_STATUS; TS_PROJECT_CLOSED (no hours after the closed date). | U43: projects.status, project_status_history (from, to, reason, changed_by, changed_at) | V43: Active / on-hold / NPA counts | W43: Projects list, CEO project health strip | X43: NTF-14 status changed (to PM) | Y43: /projects/:id | Z43: projects.edit | AA43: Live | AB43: -
A44: DEL-08 | B44: Project delivery | C44: Scope | D44: Change requests | E44: Paid scope changes are captured, estimated and approved, never done for free. | F44: Client asks for something outside scope | G44: 1. PM raises the CR: title, description 2. Estimate hours and value 3. Admin/PM approves (adds value to the contract and can create a new milestone) or rejects 4. Mark Done when delivered | I44: I | J44: A | K44: R | S44: C | T44: CR_STATUS (Raised > Estimated > Approved/Rejected > Done); CR_DECIDED (decided CRs cannot change); hours >= 0; a CR rejected after work started is logged as scope creep in Lost revenue. | U44: change_requests (title, description, hours, value_paise, status, raised_by, milestone_id, decided_by) | V44: CR value approved, scope creep | W44: PM Home (change requests), Approvals inbox (change_request), Lost revenue | X44: NTF-14 CR approved (to raiser) | Y44: /projects/:id/changes | Z44: change_requests.manage | AA44: Extended | AB44: v3 routes CRs into the Approvals inbox and Lost revenue register.
A45: DEL-09 | B45: Project delivery | C45: Money | D45: Margin and health monitoring | E45: Shows planned, projected and actual margin and flags projects at risk early. | F45: Weekly review, or any change to hours, estimates or invoices | G45: 1. Open the Money tab: planned vs projected vs actual cost, revenue, margin and markup 2. Health is computed: On track / At risk / Off track 3. PM acts on red items; CEO sees the health strip | I45: I | J45: A | K45: I | T45: BR-23..BR-26; MARGIN_BELOW_FLOOR warning (projects.margin_floor_pct 25%); effort ratio alert 1.2; margins visible to Admin and PMs with the margins grant only. | U45: computed from tasks, cost rates, approved hours, invoices | V45: Margin %, markup %, effort ratio, SPI, health | W45: PM Home (delivery control), CEO Home (project health), Insights | X45: - | Y45: /projects/:id/money | Z45: margins.view | AA45: Live | AB45: -
A46: DEL-10 | B46: Project delivery | C46: Client | D46: Client status report (money-free view) | E46: Gives the client a clean progress view without exposing costs or margins. | F46: Weekly client call | G46: 1. PM opens the client view 2. Shares milestone progress, dates and status (no money) 3. Discusses slips and next steps | I46: I | J46: I | K46: R | S46: I | T46: No money fields are included. | U46: - | V46: Progress %, milestones achieved | W46: Client view page | X46: - | Y46: /projects/:id/client-view | Z46: projects.edit | AA46: Live | AB46: -
A47: DEL-11 | B47: Project delivery | C47: Closure | D47: Project closure | E47: Closes the books on a project: all billed, collected, documented and lessons captured. | F47: Last milestone achieved | G47: 1. Achieve the last milestone and raise the final invoice 2. Collect payment; resolve open tasks and CRs 3. Set status Completed, then Closed with a reason 4. Hours can no longer be booked | I47: I | J47: A | K47: R | P47: I | S47: C | T47: BR-17 reason for Closed; TS_PROJECT_CLOSED. | U47: projects.status, history | V47: Final margin, effort ratio | W47: Projects, P&L | X47: NTF-14 status changed | Y47: /projects/:id | Z47: projects.edit | AA47: Live | AB47: No closure checklist, client acceptance or lessons-learned record yet.
A48: DEL-12 | B48: Project delivery | C48: Resourcing | D48: Resource requisition | E48: PMs request people by skill and dates; HR fills from bench or hiring. | F48: Allocation gap on a project | G48: 1. PM raises a requisition: role/skill, %, dates, project 2. HR proposes bench people or opens a hiring opening 3. PM confirms; allocation is created | I48: I | J48: A | K48: R | L48: R | M48: I | T48: - | U48: - | V48: - | W48: - | X48: - | Y48: - | Z48: - (planned) | AA48: Planned | AB48: Openings exist (HR-01) but are not linked to allocation gaps. Recommendation: requisition > opening/allocation in one flow.
A49: DEL-13 | B49: Project delivery | C49: Resourcing | D49: Capacity planning and forecasting | E49: Sees 3-6 months ahead whether the team can deliver won and likely deals. | F49: Monthly planning | G49: 1. Combine allocations, weighted pipeline and leave 2. Show demand vs capacity by role per month 3. Decide hire, defer or decline | I49: I | J49: A | K49: R | L49: C | M49: I | N49: C | O49: C | T49: - | U49: - | V49: - | W49: - | X49: - | Y49: - | Z49: - (planned) | AA49: Planned | AB49: Recommendation: extend the 10-day resource load to a monthly forecast using pipeline probability.
A50: DEL-14 | B50: Project delivery | C50: Support | D50: Support / AMS ticketing with SLA | E50: AMS contracts are sold on response and resolution SLAs; they must be measured. | F50: Client raises an incident or service request | G50: 1. Client or PM logs a ticket with priority 2. SLA clock runs by priority and business hours 3. Consultant resolves and logs time; client confirms 4. Monthly SLA report per AMS client | I50: I | J50: A | K50: R | P50: R | S50: R | T50: - | U50: - | V50: - | W50: - | X50: - | Y50: - | Z50: - (planned) | AA50: Planned | AB50: Recommendation: essential for SAP AMS clients; link tickets to AMS retainer projects and timesheets.
A51: TSK-01 | B51: Task governance | C51: Assignment | D51: Manager assigns a task | E51: Any manager can give a dated, estimated task to their people, inside a project or as general work. | F51: Work to be done by a team member | G51: 1. Open Team tasks > Assign 2. Pick the person, project (or "General & admin"), milestone, title, description, start, due, estimate, priority and reviewer 3. Save: owner is notified and the task appears in My tasks | I51: I | J51: A | K51: R | L51: R | M51: I | N51: R | O51: I | P51: I | Q51: R | T51: Owner must be active; title 3-200; description up to 4,000; project must be Active or Initiated (or General & admin); allowed only for Admin, the project PM, or the owner's manager (reporting line) else 403; due date not in the past and not before start; NON_WORKING_DAY warning; estimate 0.5-200 h; reviewer active and not the owner (TASK_SELF_REVIEW); default reviewer = the assigner. | U51: tasks (kind project/general, assigned_by, reviewer_id, priority, est_hours, start_on, due_on) | V51: Tasks assigned per person | W51: Team tasks, My tasks, Employee Home (Today / This week) | X51: NTF-14 task assigned | Y51: /team-tasks?tab=assign | Z51: tasks.assign_team|tasks.edit | AA51: New in v3 | AB51: Built-in project GEN "General & admin" holds non-client work.
A52: TSK-02 | B52: Task governance | C52: Execution | D52: Work my tasks (start, progress, covering) | E52: Each person has one ordered list of what to do, with overdue and blocked items on top. | F52: Task assigned | G52: 1. Open My tasks: overdue (red), blocked first, then by due date; Covering list for tasks you back up 2. Move a task To do > In progress 3. Log hours against it in the timesheet | I52: I | J52: I | K52: C | L52: C | M52: I | N52: C | O52: C | P52: R | Q52: C | T52: TASK_BLOCKED (cannot start while a dependency is open); USE_REVIEW_FLOW (cannot set In review or Done directly; use Submit for review); backup covers when the owner is on leave. | U52: tasks.status | V52: Open, overdue, in review counts | W52: Employee Home (Today, Blockers, Others waiting on you) | X52: - | Y52: /my-tasks, task drawer | Z52: - | AA52: Live | AB52: -
A53: TSK-03 | B53: Task governance | C53: Execution | D53: Report a blocker; comments and @mentions | E53: Makes blockers and questions visible to the right person immediately. | F53: Work cannot proceed, or a question arises | G53: 1. Set the task to Blocked with the reason, or add a dependency 2. PM is notified; blocking task and its owner are shown 3. Discuss in comments; @mention people 4. When the blocking task is approved, the owner is told they can start | I53: I | J53: I | K53: A | P53: R | Q53: C | T53: Comment required, up to 4,000 characters; replies must be on the same task. | U53: tasks.blocked_reason, comments (body, mentions, parent_id) | V53: Blocked tasks, days blocked | W53: Insights > Blocked, PM Home (Blocked), Employee Home (Blockers) | X53: NTF-14 task blocked (to PM); NTF-03 mention; NTF-14 "You can start a task" | Y53: Task drawer | Z53: R: (none); A: tasks.edit|tasks.review | AA53: Live | AB53: -
A54: TSK-04 | B54: Task governance | C54: Review | D54: Submit task for review | E54: Work is "done" only when someone else checks it; the owner states what was delivered and gives proof. | F54: Owner finishes the work | G54: 1. Owner (or backup) clicks Submit for review 2. Writes what was delivered and adds an optional proof link 3. If past due: chooses a delay reason and explains it 4. Task goes In review; reviewer is notified and it appears in their Approvals inbox | I54: I | J54: I | K54: C | L54: C | M54: I | N54: C | O54: C | P54: R | Q54: C | T54: Note min 5, max 2,000 characters; proof link must start with https://; INVALID_STATE (already in review / approved); TASK_BLOCKED (open dependency); DELAY_REASON_REQUIRED when submitted after the due date. | U54: task_reviews (round, submitted_by, submitted_at, submission_note, proof_url, delay_reason_code, delay_reason); tasks.submitted_on, review_round | V54: In review count, rounds | W54: Approvals inbox (task_review), Team tasks > Review queue; Reports / Ask AI (task_reviews) | X54: NTF-04 task waiting for your review / resubmitted | Y54: Task drawer > Submit for review | Z54: - | AA54: New in v3 | AB54: -
A55: TSK-05 | B55: Task governance | C55: Review | D55: Delay reason capture | E55: Every late task carries a reason, so management fixes causes, not symptoms. | F55: Task submitted after its due date | G55: 1. System detects the submission is late 2. Owner must choose a reason: scope changed, waiting on another task, client delay, effort underestimated, leave/absence, re-prioritised, technical issue, resource shortage, other 3. Owner explains what happened and what they did (min 15 characters) 4. Reasons roll up by person, team and company | I55: I | J55: I | K55: I | L55: C | M55: I | N55: C | O55: C | P55: R | Q55: C | T55: DELAY_REASON_REQUIRED (code from the list + explanation min 15 characters); inbox warns "Submitted late without a delay reason" for older items. | U55: task_reviews.delay_reason_code / delay_reason; tasks.delay_reason_code / delay_reason | V55: Top delay reasons, count by reason | W55: Team tasks > Performance (top reasons), Approvals inbox, My performance; Reports / Ask AI (tasks, task_reviews) | X55: - | Y55: Task drawer > Submit for review | Z55: - | AA55: New in v3 | AB55: -
A56: TSK-06 | B56: Task governance | C56: Review | D56: Approve task with quality rating | E56: The reviewer confirms the work and rates its quality; the completion date and timeliness are fixed at this point. | F56: Task in review | G56: 1. Reviewer opens the item (inbox, review queue or task) 2. Checks the note and proof 3. Approves with a quality rating 1-5 and optional note 4. Task becomes Done; timeliness is stamped; dependants are unblocked; milestone progress updates | I56: I | J56: A | K56: R | L56: R | M56: I | N56: R | O56: I | P56: I | Q56: R | T56: Reviewer = task reviewer, else project PM (project tasks), else assigner / owner's manager (general tasks); never the owner unless top admin (TASK_SELF_REVIEW); Admin may always review; quality rating 1-5 required; note up to 1,000; INVALID_STATE if not in review; inbox SLA = approval.sla_working_days (default 2) from submission. | U56: tasks (status done, done_on = submission date, approved_by, approved_on, timeliness, variance_days, quality_rating); task_reviews.decision approved | V56: On-time %, avg quality, first-pass % | W56: CEO/PM/Employee Home (task delivery), Team tasks > Performance, My performance, Appraisal metrics, Scorecard; Reports / Ask AI (tasks, task_reviews) | X56: NTF-05 task approved (with rating and timeliness) | Y56: /inbox, /team-tasks?tab=review, task drawer | Z56: tasks.review | AA56: Extended | AB56: New in v3. v4: routed by the configurable "Task completion review" workflow (default: task reviewer) - WF-01 / WF-03.
A57: TSK-07 | B57: Task governance | C57: Review | D57: Send back with reason | E57: Rework is explicit, reasoned and counted, not a silent status change. | F57: Work not acceptable | G57: 1. Reviewer clicks Send back and writes what must change 2. Optionally sets a new due date (logged as a reschedule) 3. Task returns to In progress; review round increases; owner is notified | I57: I | J57: A | K57: R | L57: R | M57: I | N57: R | O57: I | P57: I | Q57: R | T57: Reason min 10, max 2,000 characters; INVALID_STATE (only tasks in review); new due date not in the past or before start; NON_WORKING_DAY warning. | U57: task_reviews (decision sent_back, decision_reason); activity log task.rescheduled | V57: Sent-back count, first-pass % | W57: Team tasks (sent-back count, last reason), My performance; Reports / Ask AI (task_reviews) | X57: NTF-06 task sent back | Y57: /inbox, task drawer | Z57: tasks.review | AA57: Extended | AB57: New in v3. v4: routed by the "Task completion review" workflow; send-back ends the chain and the next submission starts over.
A58: TSK-08 | B58: Task governance | C58: Planning | D58: Reschedule a task with reason | E58: Due dates cannot drift silently; every move is explained and kept. | F58: Due date needs to change | G58: 1. PM / manager edits the due date 2. Must say why (min 10 characters) 3. Change is logged in task history; owner notified; reschedule count shows in Team tasks | I58: I | J58: A | K58: R | P58: I | Q58: R | T58: DUE_REASON_REQUIRED; INVALID_STATE (approved tasks cannot change due date); DATE_RANGE. | U58: tasks.due_on; activity_log (task.rescheduled) | V58: Reschedule count per task/person | W58: Team tasks > Team | X58: NTF-14 due date changed | Y58: Task drawer | Z58: tasks.edit|tasks.review | AA58: New in v3 | AB58: -
A59: TSK-09 | B59: Task governance | C59: Measurement | D59: Timeliness: early, on time or late | E59: Turns every completed task into a fair, calendar-aware delivery record. | F59: Task approved | G59: 1. System counts working days between due date and the submission date 2. Negative = early, 0 = on time, positive = late 3. Stored on the task and rolled up per person, team, project and company | I59: I | J59: I | K59: I | L59: I | M59: I | N59: I | O59: I | P59: I | Q59: I | T59: Working days per BR-01 (weekends, holidays excluded); timeliness uses the date the work was submitted, not the approval date. | U59: tasks.timeliness, variance_days | V59: On-time % = (early + on time) / completed; avg variance days | W59: CEO Home, HR & operations Home, PM Home, Employee Home (task delivery panels), Team tasks > Performance, Scorecard, Appraisals, Reports / Ask AI (tasks.timeliness) | X59: - | Y59: Computed (performance.ts) | Z59: - | AA59: New in v3 | AB59: -
A60: TSK-10 | B60: Task governance | C60: Monitoring | D60: Team task monitoring | E60: Gives managers one live list of their team's work with the signals that matter. | F60: Daily stand-up / weekly review | G60: 1. Open Team tasks > Team 2. Filter by person, project, status 3. See overdue days, delay reason, sent-back count and last reason, reschedule count, quality | I60: I | J60: A | K60: R | L60: C | M60: I | N60: C | O60: C | Q60: R | T60: Scope: Admin and HR see all; managers see their team, tasks they assigned or review, and their projects. | U60: tasks, task_reviews, activity_log | V60: Overdue days, sent backs, reschedules | W60: Team tasks; Reports / Ask AI (tasks) | X60: - | Y60: /team-tasks?tab=team | Z60: team.view | AA60: New in v3 | AB60: -
A61: TSK-11 | B61: Task governance | C61: Monitoring | D61: Team and company delivery performance | E61: Shows who delivers on time and with quality, by person, project or manager. | F61: Weekly / monthly review, appraisal | G61: 1. Open Team tasks > Performance (or the Task delivery panel on Home) 2. Choose scope (me / team / company) and group (person / project / manager) 3. Review on-time %, early/on-time/late, avg variance, first-pass %, quality, top delay reasons | I61: I | J61: A | K61: R | L61: R | M61: I | N61: C | O61: C | P61: I | Q61: R | T61: Admin and HR & operations get company scope; managers get team; others only themselves. | U61: computed from tasks and task_reviews | V61: On-time %, avg variance, first-pass %, avg quality, delay reasons | W61: CEO Home and HR & operations Home (company, 90 days), PM Home (team), Employee Home (my delivery), CEO People panel (on-time %), Team tasks > Performance, Reports / Ask AI (tasks, task_reviews) | X61: - | Y61: /team-tasks?tab=performance, /home | Z61: tasks.analytics | AA61: New in v3 | AB61: -
A62: TIM-01 | B62: Time & attendance | C62: Timesheet | D62: Weekly timesheet entry | E62: Every hour is linked to a task, leave or internal activity: the basis for cost, billing and pay. | F62: Daily, during the week | G62: 1. Open the week grid (Mon-Sun) 2. Add rows for tasks, leave or internal activities; enter hours per day 3. Copy last week's rows if useful; save a draft any time | I62: I | L62: R | M62: R | N62: R | O62: R | P62: R | T62: TS_BAD_WEEK (Monday); TS_TASK_NOT_ALLOWED (only tasks you own, back up or are allocated to); TS_PROJECT_CLOSED; TS_NOTE_REQUIRED for internal rows; TS_BAD_STEP (0.5 h); TS_FUTURE; TS_OVER_MAX (16 h/day); LEAVE_INVALID on holidays/weekly offs; duplicate rows rejected; TS_LOCKED; TS_NOT_EDITABLE after submit; COPY_SKIPPED warning. | U62: timesheet_weeks, timesheet_entries (work_date, kind, task_id, internal_code, leave_type, hours, note) | V62: Hours logged, actual hours per task | W62: Employee Home (my timesheet), Scorecard (timesheet) | X62: - | Y62: /timesheet | Z62: timesheet.own | AA62: Live | AB62: All roles including PM and Admin log time (timesheet.own).
A63: TIM-02 | B63: Time & attendance | C63: Timesheet | D63: Submit the week | E63: Locks the week for approval and payroll. | F63: End of week (Friday nudge at 16:00) | G63: 1. Review day totals (minimum 9 h per working day) 2. Submit the week; it becomes read-only 3. Approver is notified; the top person is auto-approved | I63: I | L63: R | M63: R | N63: R | O63: R | P63: R | Q63: I | T63: TS_BAD_HOURS (log hours first); TS_FUTURE (week not started); TS_BELOW_MIN warning (days under calendar.min_hours_per_day); BR-05 read-only after submit; STALE. | U63: timesheet_weeks.status submitted, submitted_at, approver_id | V63: Timesheet compliance | W63: Insights > Timesheet compliance, HR Home (timesheets missing) | X63: NTF-04 timesheet submitted; NTF-09 Friday nudge | Y63: /timesheet | Z63: timesheet.own | AA63: Live | AB63: NTF-09 Friday nudge and NTF-10 overdue digest are in the catalogue but no scheduler sends them in the current build.
A64: TIM-03 | B64: Time & attendance | C64: Timesheet | D64: Timesheet approval and SLA | E64: Managers confirm hours within the approval SLA (default 2 working days); late approvals count against them. | F64: Week submitted | G64: 1. Approver opens Timesheet approvals or the Approvals inbox: hours, days below minimum, days waiting, overdue badge 2. Approve, or reject with a reason (week reopens) 3. Bulk-approve several weeks if enabled 4. Team grid shows 8 weeks of status per person | I64: A | L64: C | M64: I | P64: I | Q64: R | T64: BR-07 approver = reports-to or active delegate; TS_SELF_APPROVAL; TS_NOT_EDITABLE (only submitted weeks); BR-08 reject reason min 5 (TS_REASON_REQUIRED); TS_BULK_OFF; BR-10 SLA approval.sla_working_days (2); APPROVAL_LATE warning; BR-11 late decisions and pending past SLA count against the manager, never block. | U64: timesheet_weeks (decided_by, decided_at, late, reject_reason) | V64: Approval KPI = -(late + overdue pending); approval SLA % | W64: Approvals inbox (timesheet), PM Home (approvals for me), CEO Home (approvals by manager), Insights > Approval KPI, Team grid, Scorecard (approvals) | X64: NTF-05 approved; NTF-06 rejected; NTF-10 overdue digest | Y64: /approvals, /inbox, /team | Z64: approvals.act | AA64: Extended | AB64: v4: routed by the configurable "Weekly timesheets" workflow (default: reporting manager, SLA 2 days) - WF-01 / WF-03.
A65: TIM-04 | B65: Time & attendance | C65: Timesheet | D65: Weekly lock and unlock request | E65: Stops back-dated hour changes while allowing controlled fixes. | F65: Week ends unsubmitted (Monday 00:00) | G65: 1. Week locks automatically 2. Employee requests unlock with a reason 3. Approver unlocks for 1-7 days, or declines with a reason | I65: A | L65: R | M65: R | N65: R | O65: R | P65: R | Q65: R | T65: BR-06; TS_REASON_REQUIRED (min 5); TS_NOT_EDITABLE (only locked weeks); TS_UNLOCK_RANGE (1 to timesheet.unlock_max_days, default 7). | U65: timesheet_weeks (unlock_requested_at, unlock_reason, unlock_until) | V65: Locked weeks | W65: Approvals inbox (unlock) | X65: NTF-07 unlock requested; NTF-08 unlocked / declined | Y65: /timesheet, /approvals, /inbox | Z65: approvals.act | AA65: Live | AB65: -
A66: TIM-05 | B66: Time & attendance | C66: Daily | D66: Daily update with proof | E66: "No proof, no progress": each day ends with what was finished and a link that proves it. | F66: End of each working day | G66: 1. Write what you finished today 2. Add a proof link (commit, screenshot, demo URL), any blocker, and whether a demo was shown 3. Updates feed the weekly scorecard | I66: I | J66: C | K66: C | L66: R | M66: R | N66: R | O66: R | P66: R | Q66: C | T66: DU_PROOF_REQUIRED (daily.proof_required); link must start with http(s)://; no future days; this week only; text required. | U66: daily_updates (date, done, proof_url, blocker, demo_shown) | V66: Update days / working days; Friday demo | W66: Scorecard (updates, demo) | X66: - | Y66: /daily | Z66: daily_update.post | AA66: Live | AB66: -
A67: TIM-06 | B67: Time & attendance | C67: Leave | D67: Apply for leave | E67: Employees request leave in advance against a known balance. | F67: Employee plans time off | G67: 1. Choose type (casual, sick, earned, compensatory, LWP), dates, full or half day, and reason 2. System shows working days and balance 3. Request goes to the reports-to manager (and their delegate); top person is auto-approved | I67: I | L67: R | M67: R | N67: R | O67: R | P67: R | Q67: A | T67: Type and dates required; DATE_RANGE (max 60 days; more than 30 days in the past only via HR); reason min 5; LEAVE_INVALID (all days are offs/holidays); LEAVE_OVERLAP; LEAVE_BALANCE. | U67: leave_requests (user_id, from_on, to_on, type, portion, days, reason, status, approver_id) | V67: Leave taken, pending | W67: Leave page, Approvals inbox, HR Home (leave to approve); Reports / Ask AI (leave_requests) | X67: NTF-04 leave request (manager + delegate) | Y67: /leave | Z67: - | AA67: New in v3 | AB67: -
A68: TIM-07 | B68: Time & attendance | C68: Leave | D68: Approve, reject or cancel leave | E68: Managers decide quickly; approved leave flows into timesheets, working days and payroll. | F68: Leave request pending | G68: 1. Manager (or delegate, or Admin) opens the request in the inbox or Leave page 2. Approve: balance re-checked, leave days written into timesheets 3. Reject with a reason 4. Employee may cancel before the leave starts | I68: A | L68: C | M68: I | P68: I | Q68: R | T68: Only the person's manager, their delegate or Admin; cannot decide own leave; NOT_PENDING; LEAVE_BALANCE re-checked; reject reason min 5; LEAVE_STARTED (cannot cancel once started); LEAVE_WEEK_SUBMITTED warning; BR-09 leave appears in the timesheet; BR-01 approved leave is not a working day. | U68: leave_requests (decided_by, decided_at, decision_reason); leave (date, type, portion, source, approved_by); timesheet leave rows | V68: Leave days, LWP days (payroll) | W68: Approvals inbox (leave), HR Home (on leave today), Payroll; Reports / Ask AI (leave_requests) | X68: NTF-05 leave approved; NTF-06 leave not approved; NTF-04 leave cancelled | Y68: /leave, /inbox | Z68: leave.approve|approvals.act | AA68: Extended | AB68: New in v3. v4: routed by the configurable "Leave requests" workflow (default: reporting manager) - WF-01 / WF-03.
A69: TIM-08 | B69: Time & attendance | C69: Leave | D69: Leave policy and balances | E69: Sets entitlement per leave type so balances are automatic and fair. | F69: Policy set-up or annual change | G69: 1. HR sets annual days, carry-forward cap and accrual (upfront or monthly) per paid leave type 2. Balances are computed per person from joining date within the FY 3. Employees and managers see the balance when applying/deciding | I69: A | L69: R | M69: I | P69: I | Q69: I | T69: Paid leave types only; annual days 0-60 (half days allowed); carry-forward 0-60. | U69: leave_policies (type, annual_days, carry_forward_max, accrual) | V69: Balance = accrued (pro-rata) + carried - taken - pending | W69: Leave page | X69: - | Y69: /leave (policy) | Z69: people.manage | AA69: New in v3 | AB69: -
A70: TIM-09 | B70: Time & attendance | C70: Leave | D70: HR leave entry and leave in timesheet | E70: HR can record leave for anyone (sick days, back-dated leave), and leave typed in a timesheet becomes a leave record. | F70: Unplanned absence, or correction | G70: 1. HR/Admin records leave for a person: type, dates, half day 2. Or the employee adds a leave row in the timesheet 3. Leave register, timesheet and payroll stay in sync | I70: A | L70: R | M70: R | P70: I | Q70: I | T70: BR-09; person must be active; max 60 days; LEAVE_INVALID (half day = one date; not a working day); already on leave; TS_NOT_EDITABLE / TS_LOCKED if that week is approved or locked; LEAVE_SKIPPED_OFFS warning. | U70: leave (source hr / timesheet) | V70: Leave and LWP days | W70: Payroll, Team grid | X70: - | Y70: /leave, /timesheet | Z70: leave.hr_entry | AA70: Live | AB70: -
A71: TIM-10 | B71: Time & attendance | C71: Leave | D71: Compensatory off accrual | E71: Weekend or holiday work for clients (common in SAP go-lives) earns comp-off automatically. | F71: Approved hours on a weekly off or holiday | G71: 1. System detects approved hours on a non-working day 2. Manager confirms comp-off credit 3. Credit added to compensatory balance with an expiry | I71: A | L71: C | M71: I | P71: R | Q71: R | T71: - | U71: - | V71: - | W71: - | X71: - | Y71: - | Z71: - (planned) | AA71: Planned | AB71: Recommendation: compensatory leave type exists; add automatic accrual from approved weekend/holiday hours with 60-day expiry.
A72: TIM-11 | B72: Time & attendance | C72: Attendance | D72: Attendance capture (office / WFH / client site) | E72: Records where people work each day for client billing, travel claims and statutory attendance registers. | F72: Daily | G72: 1. Employee checks in (office, WFH, client site) from web or phone 2. Exceptions (missed check-in) go to the manager 3. Monthly attendance register for HR | I72: I | L72: R | M72: R | N72: R | O72: R | P72: R | Q72: A | T72: - | U72: - | V72: - | W72: - | X72: - | Y72: - | Z72: - (planned) | AA72: Planned | AB72: Recommendation: light check-in tied to the timesheet, not a biometric system; feeds Shops & Establishment registers.
A73: DOC-01 | B73: Documents & knowledge | C73: Project documents | D73: PM uploads a project document | E73: Requirements, designs, test plans and minutes live with the project and reach the right people. | F73: New or updated project artefact | G73: 1. PM (own project) or Admin opens Project > Documents and clicks Upload 2. Title, category, visibility (project team, managers only, company), tags; attach a file or paste an https link 3. Optionally mark Must read: the team is notified and asked to acknowledge | I73: I | J73: A | K73: R | L73: I | M73: I | P73: I | T73: Title 3-120 characters; category and visibility required; file OR link, not both; FILE_REJECTED (PDF, DOCX, XLSX, PPTX, PNG, JPG, CSV, TXT, MD; not empty; max 10 MB); link must start with https://; only Admin or the project's PM can change project documents. | U73: documents (project_id, title, category, visibility, must_read, tags, owner_id, current_version), document_versions (file, url, size, note, uploaded_by) | V73: Documents per project | W73: Project > Documents, Documents library; Reports / Ask AI (documents) | X73: NTF-14 must-read document (to audience) | Y73: /projects/:id/documents | Z73: documents.manage | AA73: New in v3 | AB73: -
A74: DOC-02 | B74: Documents & knowledge | C74: Project documents | D74: Employees access project documents | E74: Everyone on the project finds the latest version in one place, without email attachments. | F74: Employee needs a project artefact | G74: 1. Open Documents (or Project > Documents) 2. See documents of projects you work on, plus company documents 3. Open or download; views are recorded | I74: I | J74: I | K74: R | L74: R | M74: R | N74: R | O74: R | P74: R | T74: Visible if: visibility = company; or Admin/HR; or the project PM; or a project member (task owner, backup or allocated) when visibility = project. "Managers only" hides it from members. Anything else returns 404. | U74: document_views (document_id, user_id, at) | V74: Views per document | W74: Documents; Reports / Ask AI (documents) | X74: - | Y74: /documents, /projects/:id/documents | Z74: - | AA74: New in v3 | AB74: -
A75: DOC-03 | B75: Documents & knowledge | C75: Project documents | D75: New version, archive and restore | E75: Keeps one current version with full history; old documents are archived, not lost. | F75: Document revised or obsolete | G75: 1. Upload a new version with a note on what changed 2. If must-read, acknowledgements reset and the team is notified again 3. Archive obsolete documents; restore if needed | I75: I | J75: A | K75: R | L75: I | M75: I | P75: I | T75: Version note min 5 characters; ARCHIVED (restore before new version). | U75: document_versions, documents.archived | V75: - | W75: Documents | X75: NTF-14 must-read (new version) | Y75: /documents | Z75: documents.manage | AA75: New in v3 | AB75: -
A76: DOC-04 | B76: Documents & knowledge | C76: Compliance | D76: Must-read acknowledgement | E76: Proves people have read key documents (scope, test plan, policies). | F76: Must-read document published or updated | G76: 1. Document appears in the reader's Approvals inbox as "Read: ..." 2. Reader opens it and clicks Acknowledge 3. Owner sees acknowledged / total for the current version | I76: I | J76: A | K76: R | L76: R | M76: R | N76: R | O76: R | P76: R | Q76: I | T76: Required readers = project team (PM + members) or everyone for company documents; ARCHIVED documents need no acknowledgement; acknowledgement is per version. | U76: document_acks (document_id, version, user_id, at) | V76: Acknowledged % per document | W76: Approvals inbox (document), Documents; Reports / Ask AI (documents) | X76: NTF-14 must-read | Y76: /inbox, /documents | Z76: R: (none); A: documents.manage|documents.company | AA76: New in v3 | AB76: -
A77: DOC-05 | B77: Documents & knowledge | C77: Company library | D77: Company library and policies | E77: HR publishes the handbook, leave policy and other policies in one controlled place. | F77: Policy issued or revised | G77: 1. HR/Admin uploads to the company library (no project) 2. Sets visibility (usually company) and must-read 3. Everyone acknowledges; onboarding checklist includes policy acknowledgement | I77: A | L77: R | M77: R | N77: I | O77: I | P77: R | Q77: I | T77: Only Admin and HR & operations manage the company library (documents.company). | U77: documents (project_id null) | V77: Policy acknowledgement % | W77: Documents, Approvals inbox; Reports / Ask AI (documents) | X77: NTF-14 must-read | Y77: /documents | Z77: R: (none); A: documents.company | AA77: New in v3 | AB77: -
A78: DOC-06 | B78: Documents & knowledge | C78: Knowledge | D78: Knowledge base | E78: Reusable know-how (SAP solution notes, how-tos, code standards) searchable by everyone. | F78: Problem solved worth reusing | G78: 1. Author writes an article with tags and links to project/task 2. Peers review and publish 3. Search across articles and documents | I78: A | J78: C | K78: C | L78: C | M78: I | P78: R | T78: - | U78: - | V78: - | W78: - | X78: - | Y78: - | Z78: - (planned) | AA78: Planned | AB78: Recommendation: lightweight articles in the Documents module with full-text search; credit authors in appraisals.
A79: DOC-07 | B79: Documents & knowledge | C79: Compliance | D79: Policy attestation cycles | E79: Annual re-confirmation of key policies (code of conduct, POSH, data security) for ISO 9001 audits. | F79: Annual cycle or policy change | G79: 1. HR launches an attestation campaign with a due date 2. Everyone acknowledges; reminders to laggards 3. Completion report for the auditor | I79: A | L79: R | M79: R | N79: R | O79: R | P79: R | Q79: I | T79: - | U79: - | V79: - | W79: - | X79: - | Y79: - | Z79: - (planned) | AA79: Planned | AB79: Recommendation: build on must-read acknowledgements; add due dates, reminders and a campaign report.
A80: DOC-08 | B80: Documents & knowledge | C80: Communication | D80: Internal announcements | E80: One channel for company news (holidays, wins, policy changes) with read tracking. | F80: Company news | G80: 1. Admin/HR posts an announcement with audience 2. Shows on Home and as a notification 3. Read count visible | I80: R | L80: R | M80: I | N80: I | O80: I | P80: I | Q80: I | T80: - | U80: - | V80: - | W80: - | X80: - | Y80: - | Z80: - (planned) | AA80: Planned | AB80: Recommendation: a Home banner plus notification; reuse must-read for important ones.
A81: HR-01 | B81: People & HR | C81: Recruitment | D81: Hiring openings | E81: Every hiring need is visible with a count, owner and needed-by date. | F81: Allocation gap, growth plan or exit | G81: 1. Admin/PM/HR raises an opening: role, project, count, owner, needed by, notes 2. Status moves open > interviewing > offered > filled (or on hold) as candidates progress 3. Owner is notified | I81: A | J81: R | K81: R | L81: R | M81: R | T81: Count 1-50; valid status; owner required; needed-by must be a date. | U81: openings (role, project_id, count, status, owner_id, needed_by) | V81: Open positions | W81: HR Home (openings, hiring pipeline) | X81: NTF-14 opening assigned | Y81: /openings | Z81: openings.manage | AA81: Extended | AB81: v3 links openings to the candidate pipeline and updates status automatically.
A82: HR-02 | B82: People & HR | C82: Recruitment | D82: Candidate pipeline | E82: Tracks every applicant from application to decision, with CTC and notice data for offers. | F82: Application or referral received | G82: 1. HR adds the candidate to an opening: name, email, phone, source, experience, current/expected CTC, notice, rating, resume 2. Move through stages: applied > screening > interview > offer > hired (or rejected / withdrawn) 3. Opening status follows | I82: A | J82: C | K82: C | L82: R | M82: R | T82: Name and valid email; source required; experience 0-50 years; notice 0-180 days; rating 1-5; resume up to 5 MB (FILE_TOO_LARGE); DUPLICATE (same email on the opening); OPENING_FILLED; CANDIDATE_HIRED (edit in People instead). | U82: candidates (opening_id, name, email, source, stage, experience_years, current/expected_ctc_paise, notice_days, resume_file_id, rating) | V82: Candidates by stage, time to hire | W82: HR Home (hiring pipeline); Reports / Ask AI (candidates) | X82: - | Y82: /recruitment | Z82: recruitment.manage | AA82: New in v3 | AB82: -
A83: HR-03 | B83: People & HR | C83: Recruitment | D83: Interviews and feedback | E83: Structured rounds with a named interviewer, rating and written feedback. | F83: Candidate shortlisted | G83: 1. Schedule a round: type (technical, HR, manager, assignment, final), date/time, interviewer 2. Interviewer records result, rating 1-5 and feedback 3. Next round or decision | I83: A | J83: R | K83: R | L83: R | M83: R | Q83: R | T83: Type, date/time and an active interviewer required; result required; rating 1-5; feedback min 10 characters; CANDIDATE_CLOSED (no interviews once rejected/withdrawn/hired). | U83: interviews (candidate_id, round, kind, scheduled_at, interviewer_id, result, rating, feedback) | V83: Rounds per hire, pass rate | W83: Recruitment; Reports / Ask AI (candidates) | X83: - | Y83: /recruitment | Z83: R: recruitment.manage|team.view; A: recruitment.manage | AA83: New in v3 | AB83: -
A84: HR-04 | B84: People & HR | C84: Recruitment | D84: Make an offer, or reject a candidate | E84: Offers are made only after a passed interview, with the offered CTC on record. | F84: Interview passed | G84: 1. Move the candidate to Offer with the offered CTC 2. Opening moves to Offered 3. Or reject / mark withdrawn with a reason | I84: A | J84: C | K84: C | L84: R | M84: R | Q84: C | T84: NEEDS_PASSED_INTERVIEW; offered CTC required; rejection/withdrawal reason min 5 characters. | U84: candidates.offer_ctc_paise, rejected_reason | V84: Offers made, offer acceptance | W84: HR Home; Reports / Ask AI (candidates) | X84: - | Y84: /recruitment | Z84: recruitment.manage | AA84: New in v3 | AB84: No offer-letter document or approval of offers above budget yet.
A85: HR-05 | B85: People & HR | C85: Recruitment | D85: Hire: invite and start onboarding | E85: One click turns a hired candidate into a system user with an onboarding checklist. | F85: Candidate accepts the offer | G85: 1. Mark the candidate Hired with the joining date 2. System creates the invite (Employee role, reports-to), an onboarding checklist, and fills the opening when the count is reached 3. HR and the new manager are notified | I85: A | J85: I | K85: I | L85: R | M85: R | Q85: I | T85: NOT_OFFERED (must be in Offer); joining date required; USER_EMAIL_TAKEN. | U85: invites, lifecycle_checklists (kind onboarding), candidates.user_id, openings.status | V85: Joiners this quarter | W85: HR Home, People; Reports / Ask AI (candidates) | X85: NTF-14 new joiner (HR); NTF-14 new team member (manager) | Y85: /recruitment | Z85: recruitment.manage | AA85: New in v3 | AB85: -
A86: HR-06 | B86: People & HR | C86: Lifecycle | D86: Onboarding checklist | E86: Every joiner gets the same, complete start: paperwork, laptop, accounts, buddy, policies and check-ins. | F86: Hire or manual start | G86: 1. Checklist items with owner and due offset: offer signed (-7 days), documents ID/PAN/bank (-3), laptop issued, email & accounts, buddy (day 0), policy acknowledgements (+3), 30/60/90-day check-ins 2. Owners tick items done 3. Overdue items show on the HR dashboard | I86: A | L86: R | M86: R | P86: R | Q86: R | T86: DUPLICATE (one open checklist per person and kind); joining date required; NO_LAPTOP_ASSIGNED warning when ticking laptop without an asset. | U86: lifecycle_checklists (user_id, kind, status, start_on, items: label, owner_role, due_offset_days, done_on, done_by) | V86: Onboarding items overdue | W86: HR Home (onboarding & exits) | X86: - | Y86: /lifecycle | Z86: R: (none); A: people.manage | AA86: New in v3 | AB86: -
A87: HR-07 | B87: People & HR | C87: Assets | D87: Asset register: issue and return | E87: Knows who holds every laptop, monitor and licence, and gets it back on exit. | F87: Purchase, joiner, exit or replacement | G87: 1. HR adds the asset: tag, name, category, serial, purchase date and cost, warranty 2. Assign to a person; record the return 3. History per asset; assets due back from leavers | I87: A | L87: R | M87: I | P87: I | T87: Tag format like SEE-LAP-015, unique (ASSET_TAG_TAKEN); category; purchase date not in the future; cost; ASSET_NOT_AVAILABLE / ASSET_ASSIGNED (return first); ASSET_NOT_ASSIGNED; user must be active. | U87: assets (tag, name, category, serial, status, assigned_to, assigned_on, purchase_on, purchase_cost_paise, warranty_until) | V87: Assets assigned, due back | W87: HR Home (assets due back) | X87: - | Y87: /assets | Z87: people.manage | AA87: New in v3 | AB87: -
A88: HR-08 | B88: People & HR | C88: Performance | D88: Goals and KRAs | E88: Each person has weighted, measurable goals agreed with their manager for the cycle. | F88: Appraisal cycle starts | G88: 1. Employee (or manager) adds goals: title, KRA, weight, measure, target, unit, due date 2. Manager approves; agreed goals are locked 3. Employee logs progress through the cycle | I88: A | J88: I | K88: I | L88: R | M88: R | N88: R | O88: R | P88: R | Q88: A | T88: Title min 4; weight 5-100; target > 0; due date; GOAL_WEIGHTS (cycle total must be exactly 100%); CYCLE_CLOSED; GOAL_LOCKED (agreed goals change only via manager); GOAL_NOT_AGREED (progress after approval); only the manager (or HR) approves. | U88: goals (user_id, cycle_id, title, kra, weight, measure, target, current, unit, due_on, status, manager_approved) | V88: Goals score = weighted achievement (capped at 100% each) | W88: My performance, Appraisal | X88: NTF-05 goal approved | Y88: /performance | Z88: R: (none); A: team.view|people.manage | AA88: New in v3 | AB88: -
A89: HR-09 | B89: People & HR | C89: Performance | D89: Continuous feedback and praise | E89: Captures praise and improvement points through the year, not just at appraisal time. | F89: Anything worth recognising or correcting | G89: 1. Give feedback to a colleague: praise, improvement or 1:1 note 2. Choose visibility: private, manager, or public 3. Recipient is notified (unless manager-only) | I89: C | J89: C | K89: C | L89: R | M89: R | N89: R | O89: R | P89: R | Q89: R | T89: Not to yourself; kind and visibility required; min 10 characters. | U89: feedback (to_user_id, from_user_id, kind, body, visibility, at) | V89: Praise count | W89: My performance | X89: NTF-03 praise / new feedback | Y89: /performance | Z89: - | AA89: New in v3 | AB89: -
A90: HR-10 | B90: People & HR | C90: Appraisal | D90: Set up and launch an appraisal cycle | E90: Runs appraisals on a fixed calendar with transparent weights for goals, tasks, timesheets and behaviour. | F90: Half-yearly / annual appraisal | G90: 1. HR creates the cycle: name, period, self/manager/HR due dates, weights (goals, tasks, timesheets, behaviour = 100%) 2. Launch: an appraisal is created for everyone with a manager 3. Close when all HR reviews are done | I90: A | L90: R | M90: I | P90: I | Q90: I | T90: Unique name (DUPLICATE); all dates; DATE_RANGE (self < manager < HR due; self not before period start); APPRAISAL_WEIGHTS (0-100 each, total exactly 100); CYCLE_LAUNCHED; CYCLE_OPEN (one running cycle); NO_PEOPLE; CYCLE_DRAFT; APPRAISALS_OPEN (cannot close with open reviews). | U90: appraisal_cycles (name, period_from, period_to, status, self_due, manager_due, hr_due, weights), appraisals | V90: Cycle completion % | W90: HR Home (appraisal cycle), Appraisals; Reports / Ask AI (appraisals) | X90: - | Y90: /appraisals | Z90: appraisals.manage | AA90: New in v3 | AB90: -
A91: HR-11 | B91: People & HR | C91: Appraisal | D91: Self review | E91: The employee rates themselves and states what they delivered and want to grow in. | F91: Cycle launched | G91: 1. Open My appraisal: system metrics shown (on-time %, quality, timesheet compliance, goals) 2. Give a self rating 1-5 and comments 3. Submit; goes to the manager | I91: I | L91: R | M91: R | N91: R | O91: R | P91: R | Q91: I | T91: Rating 1-5 (half points if allowed); comments min 30 characters; APPRAISAL_STAGE (already submitted); CYCLE_CLOSED. | U91: appraisals.self_rating, self_comments, submitted_self_at | V91: - | W91: Appraisals; Reports / Ask AI (appraisals) | X91: - | Y91: /appraisals/:id | Z91: - | AA91: New in v3 | AB91: -
A92: HR-12 | B92: People & HR | C92: Appraisal | D92: Manager review | E92: Manager rates performance using system evidence, and gives a behaviour score. | F92: Self review submitted | G92: 1. Manager sees self review, system metrics and the system-suggested rating 2. Gives a rating 1-5 and comments with examples 3. Submits to HR (appears in the manager's inbox until done) | I92: A | J92: I | K92: I | L92: C | M92: I | P92: I | Q92: R | T92: APPRAISAL_STAGE (wait for self review; not twice); comments min 30 characters; manager rating is the behaviour component. | U92: appraisals.manager_rating, manager_comments, metrics snapshot | V92: System suggested rating | W92: Approvals inbox (appraisal), Appraisals; Reports / Ask AI (appraisals) | X92: - | Y92: /appraisals/:id | Z92: R: (none); A: appraisals.manage | AA92: New in v3 | AB92: -
A93: HR-13 | B93: People & HR | C93: Appraisal | D93: HR review, calibration and outcome | E93: HR finalises rating, increment and promotion consistently across the company. | F93: Manager review submitted | G93: 1. HR sees all inputs and the system suggestion 2. Sets final rating, increment % and promotion 3. Sends back to the manager if needed; completed appraisals are locked | I93: A | L93: R | M93: I | P93: I | Q93: C | T93: APPRAISAL_STAGE; increment 0-50%; RATING_DEVIATION (final differs from the suggestion by more than 1: explain in min 15 characters); send-back reason min 10. | U93: appraisals (hr_rating, hr_comments, final_rating, increment_pct, promotion_to, closed_at); cost_rates (new row on increment) | V93: Rating distribution, avg increment | W93: Appraisals, HR Home, Cost rates, Reports / Ask AI (appraisals) | X93: NTF-05 appraisal completed (employee and manager) | Y93: /appraisals/:id | Z93: appraisals.manage | AA93: New in v3 | AB93: Completing with an increment > 0 creates a new cost-rate row (CTC + increment %) effective the day after the cycle ends (PAY-05).
A94: HR-14 | B94: People & HR | C94: Performance | D94: Performance profile | E94: One page per person with delivery, discipline and goals data: the evidence base for coaching and appraisal. | F94: Any time | G94: 1. Open My performance, or a report's profile 2. Review on-time %, average variance, first-pass %, quality, timesheet compliance and late weeks, goals score, approval SLA (for managers), feedback 3. Change the period | I94: R | J94: C | K94: C | L94: R | M94: R | N94: R | O94: R | P94: R | Q94: R | T94: You see yourself and people below you in the reporting line; Admin and HR see everyone. | U94: computed (tasks, task_reviews, timesheet_weeks, goals, feedback) | V94: On-time %, first-pass %, avg quality, timesheet compliance, goals score, approval SLA % | W94: My performance | X94: - | Y94: /performance, /performance/:userId | Z94: - | AA94: New in v3 | AB94: -
A95: HR-15 | B95: People & HR | C95: Lifecycle | D95: Exit and offboarding | E95: Every exit is handled the same way: notice, knowledge transfer, assets, access and settlement. | F95: Resignation, termination, contract end or retirement | G95: 1. HR starts an exit: resignation date, last working day, exit type, reason 2. Checklist: resignation received, notice agreed, knowledge transfer, exit interview, asset return, access revoked, full & final (+30 days), experience letter (+7 days) 3. Person is deactivated after the last day | I95: A | L95: R | M95: I | P95: C | Q95: R | T95: Only people who have joined; DUPLICATE open exit; last day on/after resignation; exit type; reason min 5; ASSETS_OUTSTANDING (cannot complete while assets are assigned); EXIT_SCHEDULED / USER_DEACTIVATED. | U95: lifecycle_checklists (kind offboarding, last_day, exit_type, exit_reason, rehire_eligible) | V95: Exits this quarter, attrition % | W95: HR Home (onboarding & exits, assets due back), CEO People panel | X95: - | Y95: /lifecycle | Z95: R: people.manage|team.view; A: people.manage | AA95: New in v3 | AB95: -
A96: HR-16 | B96: People & HR | C96: Capability | D96: Skills matrix and bench management | E96: Knows who can do what (SAP ABAP, CPI, RAP, React, FastAPI) and who is free, before selling or staffing. | F96: Staffing, bidding, or quarterly review | G96: 1. Each person rates skills; manager validates 2. Bench view = people under 50% allocated in the next 4 weeks, with skills 3. Search by skill when staffing or bidding | I96: A | J96: R | K96: R | L96: R | M96: R | P96: R | Q96: R | T96: - | U96: - | V96: - | W96: - | X96: - | Y96: - | Z96: - (planned) | AA96: Planned | AB96: Recommendation: add skills to the person record and a bench view next to Allocation (spec future scope).
A97: HR-17 | B97: People & HR | C97: Capability | D97: Training and certification tracking | E97: Tracks courses and certifications (SAP, cloud) with expiry, a selling point for clients and ISO. | F97: Course completed or certificate earned | G97: 1. Employee records training/certificate with file and expiry 2. Manager approves; training spend links to the Training budget 3. Expiry reminders 60 days ahead | I97: A | J97: C | K97: C | L97: R | M97: R | N97: R | O97: R | P97: R | Q97: R | T97: - | U97: - | V97: - | W97: - | X97: - | Y97: - | Z97: - (planned) | AA97: Planned | AB97: Recommendation: link to expense category "Training" and the skills matrix.
A98: HR-18 | B98: People & HR | C98: Lifecycle | D98: Probation confirmation | E98: Confirms or extends probation on time with the manager's recommendation. | F98: Probation end date approaching | G98: 1. HR is reminded 15 days before probation ends 2. Manager recommends confirm / extend / exit with evidence from the performance profile 3. Confirmation letter issued | I98: A | L98: R | M98: I | P98: I | Q98: R | T98: - | U98: - | V98: - | W98: - | X98: - | Y98: - | Z98: - (planned) | AA98: Planned | AB98: Recommendation: add probation end date to the person and a step in the onboarding checklist (handbook policy).
A99: HR-19 | B99: People & HR | C99: Self-service | D99: Employee self-service letters | E99: Employees download standard letters (employment, address proof, experience, relieving) without waiting for HR. | F99: Employee request or exit | G99: 1. Employee requests a letter type 2. HR approves; letter generated from a template with company letterhead 3. Stored in the person's file | I99: A | L99: R | M99: R | N99: R | O99: R | P99: R | T99: - | U99: - | V99: - | W99: - | X99: - | Y99: - | Z99: - (planned) | AA99: Planned | AB99: Recommendation: template-based letters; experience letter already exists as an exit checklist item.
A100: HR-20 | B100: People & HR | C100: Talent | D100: Employee referral bonus | E100: Rewards employees who refer hires, a cheap and reliable source for a small firm. | F100: Referred candidate is hired and completes the qualifying period | G100: 1. Candidate source = Referral with the referrer named 2. Bonus becomes due after the qualifying period 3. Paid through payroll or reimbursement | I100: A | L100: R | M100: R | N100: R | O100: R | P100: R | T100: - | U100: - | V100: - | W100: - | X100: - | Y100: - | Z100: - (planned) | AA100: Planned | AB100: Recommendation: add "referred by" to candidates and a payroll addition line.
...

Sheet Role view
A1: Role | B1: Process ID | C1: Domain | D1: Process | E1: RACI | F1: What they actually do / see | G1: Screen / route | H1: Status
A2: Administrator | B2: WS-01 | C2: Workspace & access | D2: Company sign-up and 14-day trial | E2: R | F2: Does it: carries out "Company sign-up and 14-day trial" in /signup. | G2: /signup | H2: Extended
A3: Administrator | B3: WS-02 | C3: Workspace & access | D3: Onboarding checklist and sample data | E3: R | F3: Does it: carries out "Onboarding checklist and sample data" in /home, /onboarding. | G3: /home, /onboarding | H3: Extended
A4: Administrator | B4: WS-03 | C4: Workspace & access | D4: Sign in, lockout and password reset | E4: R | F4: Does it: carries out "Sign in, lockout and password reset" in /login, /reset-password. | G4: /login, /reset-password | H4: Extended
A5: Administrator | B5: WS-04 | C5: Workspace & access | D5: Invite people (single or bulk CSV) and accept invitation | E5: R | F5: Does it: carries out "Invite people (single or bulk CSV) and accept invitation" in /people, /invite/:token. | G5: /people, /invite/:token | H5: Extended
A6: Administrator | B6: WS-05 | C6: Workspace & access | D6: Roles, reporting lines and access grants | E6: R | F6: Does it: carries out "Roles, reporting lines and access grants" in /people. | G6: /people | H6: Extended
A7: Administrator | B7: WS-07 | C7: Workspace & access | D7: View as another role | E7: R | F7: Does it: carries out "View as another role" in Top bar (admin). | G7: Top bar (admin) | H7: Extended
A8: Administrator | B8: WS-08 | C8: Workspace & access | D8: Security, two-step verification and personal settings | E8: R | F8: Does it: carries out "Security, two-step verification and personal settings" in /settings/security, /settings/profile, /settings/appearance. | G8: /settings/security, /settings/profile, /settings/appearance | H8: Live
A9: Administrator | B9: WS-09 | C9: Workspace & access | D9: Deactivate or reactivate a person | E9: R | F9: Does it: carries out "Deactivate or reactivate a person" in /people. | G9: /people | H9: Extended
A10: Administrator | B10: WS-10 | C10: Workspace & access | D10: Full data export | E10: R | F10: Does it: carries out "Full data export" in /settings/data. | G10: /settings/data | H10: Live
A11: Administrator | B11: WS-11 | C11: Workspace & access | D11: Plan, seats and payment | E11: R | F11: Does it: carries out "Plan, seats and payment" in /billing. | G11: /billing | H11: Live
A12: Administrator | B12: WS-13 | C12: Workspace & access | D12: Single sign-on and custom roles | E12: R | F12: Planned (not built yet). Does it: carries out "Single sign-on and custom roles". | G12: - | H12: Planned
... A957: Client (external) | B957: OPS-04 | C957: Operations & compliance | D957: ISO 9001 non-conformance and CAPA | E957: C | F957: Planned (not built yet). Consulted: gives input, data or a decision when asked. | G957: - | H957: Planned

Sheet Roles & permissions
A1: Module | B1: Permission key | C1: Label | D1: Description | E1: Kind | F1: Sensitive | G1: Administrator | H1: CEO | I1: CTO | J1: Project Manager | K1: HR Manager | L1: HR Executive | M1: Sales Manager | N1: Sales Executive | O1: Employee | P1: Roles holding it
A2: My work (4)
A3: My work | B3: timesheet.own | C3: Log own timesheet | D3: Fill and submit weekly timesheets. | E3: create | G3: ✓ | H3: ✓ | I3: ✓ | J3: ✓ | K3: ✓ | L3: ✓ | M3: ✓ | N3: ✓ | O3: ✓ | P3: =COUNTIF(G3:O3,"✓")
A4: My work | B4: daily_update.post | C4: Post daily updates | D4: Post the daily stand-up update with proof. | E4: create | G4: ✓ | H4: ✓ | I4: ✓ | J4: ✓ | K4: ✓ | L4: ✓ | M4: ✓ | N4: ✓ | O4: ✓ | P4: =COUNTIF(G4:O4,"✓")
A5: My work | B5: approvals.act | C5: Act on own approvals | D5: Approve items routed to them (reports-to and workflow scope still apply). | E5: approve | G5: ✓ | H5: ✓ | I5: ✓ | J5: ✓ | K5: ✓ | L5: ✓ | M5: ✓ | N5: ✓ | O5: ✓ | P5: =COUNTIF(G5:O5,"✓")
A6: My work | B6: ai.use | C6: Use Ask AI | D6: Ask questions in plain language and build AI reports within their own data access. | E6: view | G6: ✓ | H6: ✓ | I6: ✓ | J6: ✓ | K6: ✓ | L6: ✓ | M6: ✓ | N6: ✓ | O6: ✓ | P6: =COUNTIF(G6:O6,"✓")
A7: Projects & delivery (11)
A8: Projects & delivery | B8: projects.view_all | C8: See all projects | D8: Every project in the company, not only the ones they work on. | E8: view | G8: ✓ | H8: ✓ | I8: ✓ | J8: ✓ | K8: ✓ | P8: =COUNTIF(G8:O8,"✓")
A9: Projects & delivery | B9: projects.create | C9: Create projects | D9: Start new projects and import a WBS. | E9: create | G9: ✓ | H9: ✓ | I9: ✓ | J9: ✓ | P9: =COUNTIF(G9:O9,"✓")
A10: Projects & delivery | B10: projects.edit | C10: Edit projects they manage | D10: Plan, milestones, status and team of projects where they are the PM. | E10: edit | G10: ✓ | H10: ✓ | I10: ✓ | J10: ✓ | P10: =COUNTIF(G10:O10,"✓")
A11: Projects & delivery | B11: projects.manage_all | C11: Manage every project | D11: Edit any project and its tasks, and hand a project to another project manager. | E11: manage | G11: ✓ | H11: ✓ | I11: ✓ | P11: =COUNTIF(G11:O11,"✓")
A12: Projects & delivery | B12: tasks.edit | C12: Plan and edit tasks | D12: Create, assign and reschedule project tasks. | E12: edit | G12: ✓ | H12: ✓ | I12: ✓ | J12: ✓ | P12: =COUNTIF(G12:O12,"✓")
A13: Projects & delivery | B13: tasks.status_any | C13: Change any task status | D13: Move tasks that are owned by someone else. | E13: edit | G13: ✓ | H13: ✓ | I13: ✓ | J13: ✓ | P13: =COUNTIF(G13:O13,"✓")
A14: Projects & delivery | B14: allocation.edit | C14: Allocate people | D14: Change allocation % of people on projects. | E14: edit | G14: ✓ | H14: ✓ | I14: ✓ | J14: ✓ | P14: =COUNTIF(G14:O14,"✓")
A15: Projects & delivery | B15: change_requests.manage | C15: Handle change requests | D15: Raise, price and close client change requests. | E15: manage | G15: ✓ | H15: ✓ | I15: ✓ | J15: ✓ | P15: =COUNTIF(G15:O15,"✓")
A16: Projects & delivery | B16: documents.manage | C16: Manage project documents | D16: Upload, version and archive project documents. | E16: manage | G16: ✓ | H16: ✓ | I16: ✓ | J16: ✓ | P16: =COUNTIF(G16:O16,"✓")
A17: Projects & delivery | B17: documents.view_all | C17: See all project documents | D17: Open documents of projects they are not on. | E17: view | G17: ✓ | H17: ✓ | I17: ✓ | P17: =COUNTIF(G17:O17,"✓")
A18: Projects & delivery | B18: openings.manage | C18: Manage openings | D18: Raise and track staffing openings. | E18: manage | G18: ✓ | H18: ✓ | I18: ✓ | J18: ✓ | K18: ✓ | L18: ✓ | P18: =COUNTIF(G18:O18,"✓")
A19: Team & performance (6)
A20: Team & performance | B20: team.view | C20: See team pages | D20: Team workload, timesheets and availability of their reports. | E20: view | G20: ✓ | H20: ✓ | I20: ✓ | J20: ✓ | K20: ✓ | M20: ✓ | P20: =COUNTIF(G20:O20,"✓")
A21: Team & performance | B21: tasks.assign_team | C21: Assign tasks to reports | D21: Give general tasks to people who report to them. | E21: create | G21: ✓ | H21: ✓ | I21: ✓ | J21: ✓ | K21: ✓ | M21: ✓ | P21: =COUNTIF(G21:O21,"✓")
A22: Team & performance | B22: tasks.review | C22: Review submitted tasks | D22: Approve or send back tasks where they are the reviewer. | E22: approve | G22: ✓ | H22: ✓ | I22: ✓ | J22: ✓ | K22: ✓ | M22: ✓ | P22: =COUNTIF(G22:O22,"✓")
A23: Team & performance | B23: tasks.analytics | C23: Task timeliness analytics | D23: Early / on-time / late completion and delay reasons across people. | E23: view | G23: ✓ | H23: ✓ | I23: ✓ | J23: ✓ | K23: ✓ | P23: =COUNTIF(G23:O23,"✓")
A24: Team & performance | B24: insights.view | C24: Insights & scorecards | D24: Manager dashboards and scorecards. | E24: view | G24: ✓ | H24: ✓ | I24: ✓ | J24: ✓ | K24: ✓ | M24: ✓ | N24: ✓ | P24: =COUNTIF(G24:O24,"✓")
A25: Team & performance | B25: delegations.manage | C25: Delegate approvals | D25: Hand approvals to someone else while away. | E25: manage | G25: ✓ | H25: ✓ | I25: ✓ | J25: ✓ | K25: ✓ | M25: ✓ | P25: =COUNTIF(G25:O25,"✓")
A26: People & HR (10)
A27: People & HR | B27: people.view_all | C27: See everyone’s HR records | D27: Profiles, leave and lifecycle of all employees. | E27: view | G27: ✓ | H27: ✓ | I27: ✓ | K27: ✓ | L27: ✓ | P27: =COUNTIF(G27:O27,"✓")
A28: People & HR | B28: people.manage | C28: Manage HR operations | D28: Lifecycle checklists, assets and leave policy. | E28: manage | G28: ✓ | H28: ✓ | K28: ✓ | P28: =COUNTIF(G28:O28,"✓")
A29: People & HR | B29: leave.approve | C29: Approve leave | D29: Approve leave for people in their approval scope. | E29: approve | G29: ✓ | H29: ✓ | I29: ✓ | J29: ✓ | K29: ✓ | M29: ✓ | P29: =COUNTIF(G29:O29,"✓")
A30: People & HR | B30: leave.hr_entry | C30: Record leave for others | D30: Enter leave on behalf of employees. | E30: edit | G30: ✓ | H30: ✓ | K30: ✓ | L30: ✓ | P30: =COUNTIF(G30:O30,"✓")
A31: People & HR | B31: appraisals.manage | C31: Run appraisals | D31: Open cycles, calibrate and close appraisals. | E31: manage | G31: ✓ | H31: ✓ | K31: ✓ | P31: =COUNTIF(G31:O31,"✓")
A32: People & HR | B32: recruitment.manage | C32: Recruitment | D32: Candidates, interviews and offers. | E32: manage | G32: ✓ | H32: ✓ | I32: ✓ | J32: ✓ | K32: ✓ | L32: ✓ | P32: =COUNTIF(G32:O32,"✓")
A33: People & HR | B33: cost_rates.view | C33: See salaries & cost rates | D33: CTC and cost per hour (read-only). | E33: sensitive | F33: Yes | G33: ✓ | H33: ✓ | K33: ✓ | P33: =COUNTIF(G33:O33,"✓")
A34: People & HR | B34: cost_rates.edit | C34: Change salaries & cost rates | D34: Set CTC and cost per hour. | E34: sensitive | F34: Yes | G34: ✓ | H34: ✓ | P34: =COUNTIF(G34:O34,"✓")
A35: People & HR | B35: payroll.run | C35: Prepare payroll | D35: Create and calculate monthly payroll runs. | E35: sensitive | F35: Yes | G35: ✓ | H35: ✓ | K35: ✓ | P35: =COUNTIF(G35:O35,"✓")
A36: People & HR | B36: payroll.finalise | C36: Finalise payroll | D36: Lock a payroll run and post it to the ledger. | E36: sensitive | F36: Yes | G36: ✓ | H36: ✓ | P36: =COUNTIF(G36:O36,"✓")
A37: Sales & clients (6)
A38: Sales & clients | B38: deals.view_all | C38: See all deals | D38: The whole pipeline, not only deals they own. | E38: view | G38: ✓ | H38: ✓ | M38: ✓ | P38: =COUNTIF(G38:O38,"✓")
A39: Sales & clients | B39: deals.edit_own | C39: Work own deals | D39: Create deals and move deals they own. | E39: edit | G39: ✓ | H39: ✓ | M39: ✓ | N39: ✓ | P39: =COUNTIF(G39:O39,"✓")
A40: Sales & clients | B40: deals.edit_all | C40: Edit any deal | D40: Reassign and edit anyone’s deals. | E40: manage | G40: ✓ | H40: ✓ | M40: ✓ | P40: =COUNTIF(G40:O40,"✓")
A41: Sales & clients | B41: sales.performance_own | C41: Own sales performance | D41: Their own targets, attainment and incentives. | E41: view | G41: ✓ | H41: ✓ | M41: ✓ | N41: ✓ | P41: =COUNTIF(G41:O41,"✓")
A42: Sales & clients | B42: sales.performance_all | C42: Team sales performance | D42: Targets and attainment of the whole sales team. | E42: view | G42: ✓ | H42: ✓ | M42: ✓ | P42: =COUNTIF(G42:O42,"✓")
A43: Sales & clients | B43: clients.manage | C43: Manage clients & contracts | D43: Client master, contracts and renewals. | E43: manage | G43: ✓ | H43: ✓ | M43: ✓ | N43: ✓ | P43: =COUNTIF(G43:O43,"✓")
A44: Finance & spend (10)
A45: Finance & spend | B45: finance.view | C45: See finance | D45: Invoices, payments, revenue and the CEO dashboard. | E45: view | F45: Yes | G45: ✓ | H45: ✓ | P45: =COUNTIF(G45:O45,"✓")
A46: Finance & spend | B46: finance.edit | C46: Raise invoices & record payments | D46: Create invoices and record receipts. | E46: edit | F46: Yes | G46: ✓ | H46: ✓ | P46: =COUNTIF(G46:O46,"✓")
A47: Finance & spend | B47: margins.view | C47: See project margins | D47: Revenue, cost and margin of projects they can see. | E47: sensitive | F47: Yes | G47: ✓ | H47: ✓ | I47: ✓ | P47: =COUNTIF(G47:O47,"✓")
A48: Finance & spend | B48: ledger.view | C48: See the ledger | D48: Company income and expense ledger. | E48: view | G48: ✓ | H48: ✓ | K48: ✓ | P48: =COUNTIF(G48:O48,"✓")
A49: Finance & spend | B49: ops.manage | C49: Operations register | D49: Recurring company costs, renewals and compliance items. | E49: manage | G49: ✓ | H49: ✓ | K49: ✓ | L49: ✓ | P49: =COUNTIF(G49:O49,"✓")
A50: Finance & spend | B50: expenses.approve | C50: Approve expense claims | D50: Approve claims in their workflow step. | E50: approve | G50: ✓ | H50: ✓ | I50: ✓ | J50: ✓ | K50: ✓ | M50: ✓ | P50: =COUNTIF(G50:O50,"✓")
A51: Finance & spend | B51: expenses.pay | C51: Pay expense claims | D51: Mark approved claims as reimbursed. | E51: sensitive | F51: Yes | G51: ✓ | H51: ✓ | K51: ✓ | P51: =COUNTIF(G51:O51,"✓")
A52: Finance & spend | B52: procurement.manage | C52: Procurement | D52: Vendors, purchase orders and vendor bills. | E52: manage | G52: ✓ | H52: ✓ | K52: ✓ | P52: =COUNTIF(G52:O52,"✓")
A53: Finance & spend | B53: budgets.manage | C53: Budgets | D53: Set department and project budgets. | E53: manage | G53: ✓ | H53: ✓ | P53: =COUNTIF(G53:O53,"✓")
A54: Finance & spend | B54: leakage.view | C54: Revenue leakage | D54: Lost and unbilled revenue analysis. | E54: view | F54: Yes | G54: ✓ | H54: ✓ | M54: ✓ | P54: =COUNTIF(G54:O54,"✓")
A55: Reports & company (6)
A56: Reports & company | B56: reports.view | C56: Open reports | D56: Standard and saved reports within their data access. | E56: view | G56: ✓ | H56: ✓ | I56: ✓ | J56: ✓ | K56: ✓ | L56: ✓ | M56: ✓ | N56: ✓ | P56: =COUNTIF(G56:O56,"✓")
A57: Reports & company | B57: reports.build | C57: Build custom reports | D57: Custom report builder and AI report studio. | E57: create | G57: ✓ | H57: ✓ | I57: ✓ | J57: ✓ | K57: ✓ | M57: ✓ | N57: ✓ | P57: =COUNTIF(G57:O57,"✓")
A58: Reports & company | B58: okrs.manage | C58: Company OKRs | D58: Set objectives and key results. | E58: manage | G58: ✓ | H58: ✓ | P58: =COUNTIF(G58:O58,"✓")
A59: Reports & company | B59: documents.company | C59: Company library | D59: Manage policies and company-wide documents. | E59: manage | G59: ✓ | H59: ✓ | K59: ✓ | L59: ✓ | P59: =COUNTIF(G59:O59,"✓")
A60: Reports & company | B60: audit.view | C60: Audit trail | D60: Who changed what, and when. | E60: view | G60: ✓ | H60: ✓ | I60: ✓ | P60: =COUNTIF(G60:O60,"✓")
A61: Reports & company | B61: data.export | C61: Export all data | D61: Full workspace data export. | E61: sensitive | F61: Yes | G61: ✓ | H61: ✓ | P61: =COUNTIF(G61:O61,"✓")
A62: Workspace administration (9)
A63: Workspace administration | B63: settings.edit | C63: Company settings | D63: Calendar, timesheet, pay and project rules. | E63: manage | G63: ✓ | H63: ✓ | P63: =COUNTIF(G63:O63,"✓")
A64: Workspace administration | B64: theme.edit | C64: Brand & appearance | D64: Workspace colours, fonts and logo. | E64: manage | G64: ✓ | H64: ✓ | P64: =COUNTIF(G64:O64,"✓")
A65: Workspace administration | B65: holidays.edit | C65: Holiday calendar | D65: Add and remove company holidays. | E65: manage | G65: ✓ | H65: ✓ | K65: ✓ | P65: =COUNTIF(G65:O65,"✓")
A66: Workspace administration | B66: master.view | C66: See master data | D66: Org profile, locations, departments, designations, grades and shifts. | E66: view | G66: ✓ | H66: ✓ | I66: ✓ | K66: ✓ | L66: ✓ | P66: =COUNTIF(G66:O66,"✓")
A67: Workspace administration | B67: master.edit | C67: Edit master data | D67: Change the organisation’s master data. | E67: manage | G67: ✓ | H67: ✓ | K67: ✓ | P67: =COUNTIF(G67:O67,"✓")
A68: Workspace administration | B68: shifts.manage | C68: Shifts | D68: Create shifts and assign people to them. | E68: manage | G68: ✓ | H68: ✓ | K68: ✓ | P68: =COUNTIF(G68:O68,"✓")
A69: Workspace administration | B69: workflows.manage | C69: Approval workflows | D69: Who approves what, in which order, with SLAs. | E69: manage | G69: ✓ | H69: ✓ | P69: =COUNTIF(G69:O69,"✓")
A70: Workspace administration | B70: emails.view | C70: Email templates & outbox | D70: Edit templates and see emails the system sent. | E70: manage | G70: ✓ | H70: ✓ | K70: ✓ | L70: ✓ | P70: =COUNTIF(G70:O70,"✓")
A71: Workspace administration | B71: billing.manage | C71: Billing & plan | D71: Subscription, seats and invoices for SeereonOS. | E71: manage | G71: ✓ | H71: ✓ | P71: =COUNTIF(G71:O71,"✓")
A72: Users, roles & controls (10)
A73: Users, roles & controls | B73: users.view | C73: See users | D73: The user list with roles and status. | E73: view | G73: ✓ | H73: ✓ | I73: ✓ | K73: ✓ | L73: ✓ | P73: =COUNTIF(G73:O73,"✓")
A74: Users, roles & controls | B74: users.manage | C74: Manage user access | D74: Change a user’s role, reporting line and extra permissions. | E74: sensitive | F74: Yes | G74: ✓ | H74: ✓ | P74: =COUNTIF(G74:O74,"✓")
A75: Users, roles & controls | B75: employees.create | C75: Create employees | D75: Onboard a new employee and send the welcome email. | E75: create | G75: ✓ | H75: ✓ | K75: ✓ | L75: ✓ | P75: =COUNTIF(G75:O75,"✓")
A76: Users, roles & controls | B76: employees.edit | C76: Edit employee records | D76: Job details, department, designation, shift. | E76: edit | G76: ✓ | H76: ✓ | K76: ✓ | L76: ✓ | P76: =COUNTIF(G76:O76,"✓")
A77: Users, roles & controls | B77: employees.deactivate | C77: Deactivate employees | D77: Turn off access when someone leaves. | E77: sensitive | F77: Yes | G77: ✓ | H77: ✓ | K77: ✓ | P77: =COUNTIF(G77:O77,"✓")
A78: Users, roles & controls | B78: roles.view | C78: See roles | D78: Roles and their permission matrix. | E78: view | G78: ✓ | H78: ✓ | I78: ✓ | K78: ✓ | P78: =COUNTIF(G78:O78,"✓")
A79: Users, roles & controls | B79: roles.manage | C79: Manage roles | D79: Create roles and change what each role can do. | E79: sensitive | F79: Yes | G79: ✓ | H79: ✓ | P79: =COUNTIF(G79:O79,"✓")
A80: Users, roles & controls | B80: makerchecker.check | C80: Check changes (maker-checker) | D80: Approve or reject sensitive changes made by someone else. | E80: approve | G80: ✓ | H80: ✓ | I80: ✓ | K80: ✓ | P80: =COUNTIF(G80:O80,"✓")
A81: Users, roles & controls | B81: makerchecker.configure | C81: Configure maker-checker | D81: Choose which changes need a second person. | E81: sensitive | F81: Yes | G81: ✓ | H81: ✓ | P81: =COUNTIF(G81:O81,"✓")
A82: Users, roles & controls | B82: view_as | C82: View as another role | D82: Preview the product as any role (read-only). | E82: view | G82: ✓ | H82: ✓ | P82: =COUNTIF(G82:O82,"✓")
A83: Permissions per role | E83: Total keys | F83: =COUNTA(B2:B82) | G83: =COUNTIF(G2:G82,"✓") | H83: =COUNTIF(H2:H82,"✓") | I83: =COUNTIF(I2:I82,"✓") | J83: =COUNTIF(J2:J82,"✓") | K83: =COUNTIF(K2:K82,"✓") | L83: =COUNTIF(L2:L82,"✓") | M83: =COUNTIF(M2:M82,"✓") | N83: =COUNTIF(N2:N82,"✓") | O83: =COUNTIF(O2:O82,"✓")
A86: Default roles: persona (home dashboard), description and demo users
A87: Role | B87: Role key | C87: Persona / home dashboard | D87: Description | E87: Locked | F87: Demo user(s) in Seereon | G87: Permissions
A88: Administrator | B88: administrator | C88: admin - Leadership dashboard | D88: Sets up the workspace: master data, users, roles and controls. Full access. | E88: Yes (keeps role & user management) | F88: Debasish Mishra (debasish@) | G88: =G83
A89: CEO | B89: ceo | C89: admin - Leadership dashboard | D89: Runs the company. Sees every number and is the final approver. | E89: No | F89: Santosh Nayak (santosh@) | G89: =H83
A90: CTO | B90: cto | C90: pm - Delivery dashboard | D90: Owns delivery and technology across all projects, without company finance. | E90: No | F90: None in the demo (assign under People) | G90: =I83
A91: Project Manager | B91: project_manager | C91: pm - Delivery dashboard | D91: Plans and delivers projects, assigns and reviews the team’s work. | E91: No | F91: Subhankar Rout (subhankar@) + margins.view, documents.view_all | G91: =J83
A92: HR Manager | B92: hr_manager | C92: ops - HR & operations dashboard | D92: Owns people operations: onboarding, leave, appraisals, payroll preparation and procurement. | E92: No | F92: Priya Mohapatra (priya@) + documents.view_all | G92: =K83
A93: HR Executive | B93: hr_executive | C93: ops - HR & operations dashboard | D93: Day-to-day HR: onboards employees, records leave, runs recruitment. Sensitive changes go to the HR Manager. | E93: No | F93: None in the demo (assign under People) | G93: =L83
A94: Sales Manager | B94: sales_manager | C94: sales - Sales dashboard | D94: Runs the sales team and the whole pipeline. | E94: No | F94: Baishali Rout (baishali@) | G94: =M83
A95: Sales Executive | B95: sales_executive | C95: sales - Sales dashboard | D95: Works their own deals and clients. | E95: No | F95: Subham Mohanty (subham@) | G95: =N83
A96: Employee | B96: employee | C96: employee - Employee home | D96: Self-service: tasks, timesheets, leave, expenses, documents and appraisal. | E96: No | F96: Hritesh Panda (hritesh@); Bijaya Jena (bijaya@); Jagannath Nayak (jagannath@); Jayashree Dash (jayashree@); Pragyasmita Pallai (pragyasmita@) | G96: =O83
A98: Effective permissions of a person = role permissions + extra permissions - revoked permissions. Persona only picks the home dashboard; every screen and action is decided by permission. ✓ = included in the default role as shipped (roles are editable per workspace).

Sheet Maker-checker
A1: Change entity | B1: What it covers | C1: Group | D1: Required permission (checker also needs it) | E1: Who can make it (default roles) | F1: Who can check by default (Check changes + required permission) | G1: Seereon checkers today | H1: On in Seereon | I1: New tenants | J1: Recommended | K1: What is applied on approval | L1: Failure modes (approval fails or is refused) | M1: Screen
A2: Roles & permissions (role) | B2: Roles and their permission matrix | C2: Access | D2: roles.manage - Manage roles | E2: Administrator, CEO | F2: Administrator, CEO | G2: Debasish Mishra, Santosh Nayak | H2: Yes | I2: Preselected (maker-checker starts off) | J2: Yes | K2: Role created, edited (permissions, persona, name, active) or deleted; everyone holding it gets the new screens on their next request. | L2: STALE (role changed after proposal); ROLE_LOCKED; ROLE_IN_USE (delete / deactivate); LOCKOUT re-checked; ROLE_NAME_TAKEN. | M2: /setup/roles
A3: User access (role, extra permissions) (user_access) | B3: A person's role and extra / revoked permissions | C3: Access | D3: users.manage - Manage user access | E3: Administrator, CEO | F3: Administrator, CEO | G3: Debasish Mishra, Santosh Nayak | H3: Yes | I3: Preselected (maker-checker starts off) | J3: Yes | K3: Person's role, extra permissions and revoked permissions; effective permissions recomputed. | L3: STALE (their access changed meanwhile); role no longer exists; LOCKOUT; PERMISSION_ESCALATION at proposal. | M3: /people
A4: Employee creation & deactivation (employee) | B4: Creating an employee (with welcome email) and deactivating one | C4: Access | D4: employees.create - Create employees | E4: create: Administrator, CEO, HR Manager, HR Executive; deactivate: Administrator, CEO, HR Manager | F4: Administrator, CEO, HR Manager | G4: Debasish Mishra, Priya Mohapatra, Santosh Nayak | H4: No | I4: Not preselected | J4: No | K4: Create: user with employee code, temporary password, welcome email, CTC (if given). Deactivate: status deactivated, reports flagged. | L4: USER_EMAIL_TAKEN (created meanwhile); role inactive; SEATS_FULL; manager inactive; LOCKOUT on deactivation. | M4: /people/new, /people
A5: Salaries & cost rates (cost_rate) | B5: Monthly CTC, variable %, sales target | C5: Money | D5: cost_rates.edit - Change salaries & cost rates | E5: Administrator, CEO | F5: Administrator, CEO | G5: Debasish Mishra, Santosh Nayak | H5: Yes | I5: Preselected (maker-checker starts off) | J5: Yes | K5: CTC / variable % / sales target row added from its effective date, or a future row removed. | L5: STALE (rate history changed); RATE_PERIOD_LOCKED (month paid); RATE_EXISTS. | M5: /settings/cost-rates
A6: Payroll finalisation (payroll_finalise) | B6: Locking a monthly payroll run | C6: Money | D6: payroll.finalise - Finalise payroll | E6: Administrator, CEO, HR Manager | F6: Administrator, CEO | G6: Debasish Mishra, Santosh Nayak | H6: Yes | I6: Preselected (maker-checker starts off) | J6: Yes | K6: Run recomputed one last time, lines frozen, month locked for rates and holidays. | L6: STALE (run changed after the request); PAY_FINAL (already final). | M6: /payroll/:id
A7: Vendor bank & tax details (vendor) | B7: New vendors; vendor GSTIN, PAN and bank account | C7: Money | D7: procurement.manage - Procurement | E7: Administrator, CEO, HR Manager | F7: Administrator, CEO, HR Manager | G7: Debasish Mishra, Priya Mohapatra, Santosh Nayak | H7: Yes | I7: Preselected (maker-checker starts off) | J7: Yes | K7: New vendor, or a change of GSTIN, PAN or bank details (other vendor fields apply directly). | L7: STALE; DUPLICATE_VENDOR; VAL_GSTIN / VAL_PAN. | M7: /purchases (Vendors)
A8: Budgets (budget) | B8: Department / category budgets | C8: Money | D8: budgets.manage - Budgets | E8: Administrator, CEO | F8: Administrator, CEO | G8: Debasish Mishra, Santosh Nayak | H8: No | I8: Not preselected | J8: No | K8: Budget line set, deleted, or a year copied. | L8: STALE (budget changed meanwhile). | M8: /budgets
A9: Approval workflows (workflow) | B9: Approval workflow steps | C9: Configuration | D9: workflows.manage - Approval workflows | E9: Administrator, CEO | F9: Administrator, CEO | G9: Debasish Mishra, Santosh Nayak | H9: Yes | I9: Preselected (maker-checker starts off) | J9: Yes | K9: New steps for the process (or reset to default); requests already waiting keep their chain. | L9: STALE (workflow edited after proposal). | M9: /setup/workflows
A10: Organisation profile (org_profile) | B10: Legal identity, tax IDs, bank, employee code format | C10: Configuration | D10: master.edit - Edit master data | E10: Administrator, CEO, HR Manager | F10: Administrator, CEO, HR Manager | G10: Debasish Mishra, Priya Mohapatra, Santosh Nayak | H10: Yes | I10: Preselected (maker-checker starts off) | J10: Yes | K10: Organisation profile fields (legal, tax, address, bank, employee code). | L10: STALE; EMPLOYEE_CODE_TAKEN. | M10: /setup/org
A11: Master data (departments, grades…) (master_record) | B11: Locations, departments, designations, grades, cost centres | C11: Configuration | D11: master.edit - Edit master data | E11: Administrator, CEO, HR Manager | F11: Administrator, CEO, HR Manager | G11: Debasish Mishra, Priya Mohapatra, Santosh Nayak | H11: No | I11: Not preselected | J11: No | K11: Location, department, designation, grade or cost centre created, edited, (de)activated or deleted. | L11: STALE; DUPLICATE; IN_USE; HEAD_OFFICE_REQUIRED; DEPARTMENT_CYCLE. | M11: /setup/locations ... /setup/cost-centres
A12: Shifts (shift) | B12: Shifts and shift assignment | C12: Configuration | D12: shifts.manage - Shifts | E12: Administrator, CEO, HR Manager | F12: Administrator, CEO, HR Manager | G12: Debasish Mishra, Priya Mohapatra, Santosh Nayak | H12: No | I12: Not preselected | J12: No | K12: Shift created / edited / deleted, or people moved to a shift. | L12: STALE; INACTIVE shift; DEFAULT_SHIFT_REQUIRED; person deactivated meanwhile. | M12: /setup/shifts
... A14: Maker-checker settings (makerchecker_config) | B14: Maker-checker itself | C14: Configuration | D14: makerchecker.configure - Configure maker-checker | E14: Administrator, CEO | F14: Administrator, CEO | G14: Debasish Mishra, Santosh Nayak | H14: Yes (always while maker-checker is on) | I14: Always checked once enabled | J14: Yes | K14: Maker-checker on / off, checked change types and SLA. | L14: NO_CHECKER (no other person with Check changes). | M14: /setup/maker-checker
A17: Integrity rules
A18: # | B18: Integrity rule | C18: Error / warning code | D18: Where enforced
A19: 1 | B19: The maker can never check their own change. | C19: MAKER_CANNOT_CHECK (409) | D19: Changes > approve / reject
A20: 2 | B20: A checker needs "Check changes" (makerchecker.check) AND the change's required permission - you can only check what you could have done. | C20: FORBIDDEN (403) | D20: Changes > approve / reject; can_check flag
A21: 3 | B21: Only one pending change per record; withdraw or decide it first. | C21: CHANGE_PENDING (409) | D21: Every guarded write (propose)
A22: 4 | B22: A record that changed after the proposal is not overwritten: approval fails and the change is marked failed; the maker is told. | C22: STALE (409) -> status failed, NTF-05 | D22: Appliers (base_version check)
A23: 5 | B23: Rejection needs a reason of at least 10 characters. | C23: REASON_REQUIRED (422) | D23: Changes > reject
A24: 6 | B24: If nobody other than the maker is eligible to check, the change is refused - never silently self-approved. | C24: NO_CHECKER (409); NO_CHECKER_FOR warning in settings | D24: propose(); maker-checker settings
A25: 7 | B25: Maker-checker cannot be switched on unless at least one other person has Check changes; the settings themselves are always checked while it is on. | C25: NO_CHECKER (409) | D25: Setup > Maker-checker
A26: 8 | B26: The Administrator role always keeps roles.view, roles.manage, users.view, users.manage and the leadership home. | C26: ROLE_LOCKED (409) | D26: Role edits
A27: 9 | B27: At least one active person must always keep both "Manage roles" and "Manage user access". | C27: LOCKOUT (409) | D27: Role edits, user access changes, deactivation
A28: 10 | B28: Nobody can grant a permission they do not hold; only users.manage holders can give a role that manages roles or users, or deactivate an access administrator. | C28: PERMISSION_ESCALATION (403) | D28: Create employee, user access, deactivate
A29: 11 | B29: Built-in roles cannot be deleted or deactivated; roles in use cannot be deactivated or deleted. | C29: ROLE_SYSTEM / ROLE_IN_USE (409) | D29: Role edits
A30: 12 | B30: In the Seereon workspace these need a checker: roles & permissions, user access, salaries & cost rates, approval workflows, payroll finalisation, vendor bank & tax details, organisation profile (and maker-checker settings). | C30: Tenant config maker_checker | D30: Seed: seeds/access.ts
... A32: 14 | B32: Changes waiting longer than the SLA (default 2 working days, 1-10) are flagged overdue. | C32: - | D32: Changes > To check
A34: Maker-checker SLA in Seereon: 2 working days. Seereon checks: Roles & permissions, User access (role, extra permissions), Salaries & cost rates, Approval workflows, Payroll finalisation, Vendor bank & tax details, Organisation profile. New tenants: maker-checker off, preselected: Roles & permissions, User access (role, extra permissions), Salaries & cost rates, Approval workflows, Payroll finalisation, Vendor bank & tax details, Organisation profile.

Sheet Approval workflows
A1: Process | B1: Workflow (default) | C1: Step | D1: Step name | E1: Approver type | F1: Role / person | G1: Amount threshold | H1: SLA (working days) | I1: Escalation | J1: v3 behaviour it reproduces | K1: What an admin can configure | L1: Example chain (demo request) | M1: Screens
A2: Leave requests | B2: Leave approval: The reporting manager (or their delegate) decides leave. | C2: 1 | D2: Manager approval | E2: Reporting manager | F2: - | G2: - | H2: 2 | I2: None by default (configurable) | J2: Reporting manager (or active delegate) decides; top person's own leave auto-approved (APR-04). | K2: 1-5 steps; per step: name, approver type, role or person, SLA 1-15 working days, escalation target, allow self-approval; reject-reason required; notify requester; reset to default; test with a sample request. | L2: Hritesh Panda (Employee) applies for leave: Manager approval: Subhankar Rout (Delivery Head, SLA 2d) | M2: /leave, /inbox
A3: Expense claims | B3: Expense claim approval: Project manager (or reporting manager) approves; claims above ₹25,000 also need the CEO. | C3: 1 | D3: Manager / PM approval | E3: Project manager, else reporting manager | F3: - | G3: - | H3: 2 | I3: None by default (configurable) | J3: Project PM if the claim is on a project and PM is not the claimant, else reporting manager; above Rs 25,000 the CEO approves as a second step (APR-05, APR-06). | K3: 1-5 steps; per step: name, approver type, role or person, SLA 1-15 working days, escalation target, allow self-approval; reject-reason required; notify requester; reset to default; test with a sample request. Amount thresholds (rising per step). Project approvers allowed. | L3: Hritesh Panda claims Rs 30,000 on a project: Manager / PM approval: Subhankar Rout (Delivery Head, SLA 2d) > CEO approval above ₹25,000: Santosh Nayak (Founder & CEO, SLA 2d) | M3: /expenses, /inbox
A4: Expense claims | B4: Expense claim approval: Project manager (or reporting manager) approves; claims above ₹25,000 also need the CEO. | C4: 2 | D4: CEO approval above ₹25,000 | E4: Anyone with a role | F4: CEO | G4: Above Rs 25,000 | H4: 2 | I4: None by default (configurable) | J4: (same workflow) | K4: (same workflow) | L4: (see step 1) | M4: /expenses, /inbox
A5: Purchase orders | B5: Purchase order approval: Every purchase order is approved by the CEO before it is issued. | C5: 1 | D5: CEO approval | E5: Anyone with a role | F5: CEO | G5: - | H5: 2 | I5: None by default (configurable) | J5: Every PO approved by the CEO (APR-08). | K5: 1-5 steps; per step: name, approver type, role or person, SLA 1-15 working days, escalation target, allow self-approval; reject-reason required; notify requester; reset to default; test with a sample request. Amount thresholds (rising per step). Project approvers allowed. | L5: Priya Mohapatra (HR Manager) raises a PO for Rs 1,50,000: CEO approval: Santosh Nayak (Founder & CEO, SLA 2d) | M5: /purchases, /inbox
A6: Vendor bills | B6: Vendor bill approval: The CEO approves vendor bills for payment. | C6: 1 | D6: CEO approval | E6: Anyone with a role | F6: CEO | G6: - | H6: 2 | I6: None by default (configurable) | J6: Vendor bills approved by the CEO for payment (APR-09). | K6: 1-5 steps; per step: name, approver type, role or person, SLA 1-15 working days, escalation target, allow self-approval; reject-reason required; notify requester; reset to default; test with a sample request. Amount thresholds (rising per step). | L6: Priya Mohapatra books a vendor bill of Rs 80,000: CEO approval: Santosh Nayak (Founder & CEO, SLA 2d) | M6: /purchases, /inbox
A7: Weekly timesheets | B7: Timesheet approval: Weekly timesheets are approved by the reporting manager. | C7: 1 | D7: Manager approval | E7: Reporting manager | F7: - | G7: - | H7: 2 | I7: None by default (configurable) | J7: Reporting manager approves the week; top person auto-approved (APR-01). | K7: 1-5 steps; per step: name, approver type, role or person, SLA 1-15 working days, escalation target, allow self-approval; reject-reason required; notify requester; reset to default; test with a sample request. | L7: Hritesh Panda submits his week: Manager approval: Subhankar Rout (Delivery Head, SLA 2d) | M7: /timesheet, /approvals, /inbox
A8: Task completion review | B8: Task review: Submitted tasks are reviewed by the task reviewer (PM, or the assigning manager). | C8: 1 | D8: Reviewer approval | E8: Task reviewer (set on the task) | F8: - | G8: - | H8: 2 | I8: None by default (configurable) | J8: Task reviewer > project PM > assigner / owner's manager; never self (APR-03). | K8: 1-5 steps; per step: name, approver type, role or person, SLA 1-15 working days, escalation target, allow self-approval; reject-reason required; notify requester; reset to default; test with a sample request. "Task reviewer" approver and project approvers allowed. | L8: Hritesh Panda submits a task for review: Reviewer approval: Subhankar Rout (Delivery Head, SLA 2d) | M8: Task drawer, /team-tasks?tab=review, /inbox
A11: Approver types
A12: Approver type | B12: Key | C12: Resolves to | D12: Allowed for
A13: Reporting manager | B13: reports_to | C13: The requester's reporting manager (if active) | D13: All processes
A14: Manager’s manager | B14: skip_level | C14: The reporting manager's manager | D14: All processes
A15: Anyone with a role | B15: role | C15: First active holder of the chosen role (earliest joiner), other than the requester | D15: All processes
A16: A specific person | B16: user | C16: A named active person | D16: All processes
A17: Project manager of the project | B17: project_pm | C17: PM of the request's project | D17: Expense claims, purchase orders, task reviews
A18: Project manager, else reporting manager | B18: project_pm_or_manager | C18: Project PM unless they are the requester, else reporting manager | D18: Expense claims, purchase orders, task reviews
A19: Head of the requester’s department | B19: department_head | C19: Head of the requester's department, else reporting manager | D19: All processes
A20: Task reviewer (set on the task) | B20: task_reviewer | C20: Reviewer set on the task | D20: Task completion review only; not as an escalation target
A23: Routing and configuration rules
A24: # | B24: Routing / configuration rule | C24: Code
A25: 1 | B25: The chain is resolved and frozen on the request at submission; editing a workflow never re-routes requests already waiting. | C25: -
A26: 2 | B26: A step applies only when the amount is strictly above its threshold; thresholds must rise from step to step. | C26: WF_AMOUNT_ORDER
A27: 3 | B27: A step that resolves to the requester is skipped (no self-approval) unless "allow self" is ticked; consecutive steps with the same approver collapse into one. | C27: -
A28: 4 | B28: If no step can name an approver the CEO (top approver) decides; the top person's own leave and timesheets are approved automatically. | C28: -
A29: 5 | B29: Past a step's SLA the item escalates to the escalation target (once); approver and target are notified. | C29: NTF-04
A30: 6 | B30: An approver who also holds the next step approves both in one act (e.g. CEO as manager on a claim that also needs the CEO). | C30: -
A31: 7 | B31: 1-5 steps; SLA 1-15 working days; escalation must differ from the approver; every-step-has-a-threshold needs explicit acknowledgement. | C31: WF_STEPS, WF_SLA, WF_ESCALATION, WF_NO_BASE_STEP
A32: 8 | B32: Workflow changes are maker-checked in Seereon (entity workflow). | C32: Maker-checker

Sheet Setup & onboarding flow
A1: # | B1: Actor | C1: Step | D1: Screen / route | E1: Permission required | F1: What the system does and checks | G1: Done when / result
A2: A1 | B2: Administrator | C2: Sign up (new company) or sign in (debasish@seereon.co.in in the demo) | D2: /signup, /login | E2: - (signer becomes Administrator) | F2: New workspace gets nine default roles, master data, six default workflows, system email templates and maker-checker preselected (off). | G2: Lands on Home; Setup checklist card links to /setup
A3: A2 | B3: Administrator | C3: Open the setup checklist | D3: /setup | E3: any of master.view, roles.view, employees.create, workflows.manage, makerchecker.configure, emails.view | F3: Seven steps with progress; links shown only for screens the viewer may open. | G3: Progress "n of 7"
A4: A3 | B4: Administrator | C4: Organisation profile | D4: /setup/org | E4: master.view to see, master.edit to change | F4: Legal / brand name, CIN, GSTIN (matches PAN), PAN, TAN, addresses, bank (masked), employee code prefix and next number. Maker-checked in Seereon. | G4: Legal name + GSTIN or PAN + an address
A5: A4 | B5: Administrator / HR Manager | C5: Locations and shifts | D5: /setup/locations, /setup/shifts | E5: master.edit; shifts.manage | F5: One head office; shift timings, break, grace, working days, minimum hours; one default shift. | G5: >= 1 active location and >= 1 active shift
A6: A5 | B6: Administrator / HR Manager | C6: Departments, designations, grades (and cost centres) | D6: /setup/departments, /setup/designations, /setup/grades, /setup/cost-centres | E6: master.edit | F6: Department heads and parents (no cycles), cost centres, grades with CTC bands, designations with default role. | G6: >= 1 department, designation and grade
A7: A6 | B7: Administrator | C7: Review roles and permissions | D7: /setup/roles, /setup/roles/:key, ?tab=compare | E7: roles.view to see, roles.manage to change | F7: Nine roles ready; adjust the matrix, duplicate or create roles; Administrator locked; LOCKOUT protection. Maker-checked in Seereon. | G7: Any role edited / created, or a role change proposed
A8: A7 | B8: Administrator | C8: Approval workflows and maker-checker | D8: /setup/workflows, /setup/maker-checker | E8: workflows.manage; makerchecker.configure | F8: Steps, thresholds, SLA, escalation, test panel; choose change types that need a second person and the SLA. | G8: Maker-checker on, or a workflow edited
A9: A8 | B9: Administrator / HR | C9: Create employees (role + reporting manager) | D9: /people/new | E9: employees.create (+ users.manage for extra permissions, cost_rates.edit for CTC) | F9: Employee code assigned, temporary password generated, must_change_password set, manager notified (NTF-14). | G9: >= 3 active people
A10: A9 | B10: System | C10: Welcome email with temporary credentials | D10: /setup/emails?tab=sent (outbox) | E10: emails.view to see the outbox | F10: Renders the "Welcome & login details" template into the outbox (email delivery simulated in this build); the success screen shows exactly what the person received. | G10: Email in Sent
A11: A10 | B11: Administrator | C11: Check email templates | D11: /setup/emails | E11: emails.view | F11: Edit wording with placeholder chips; welcome / password-reset must keep {{username}}, {{temp_password}}, {{login_url}}. | G11: A template edited or an email sent
A12: E1 | B12: New employee | C12: Open the welcome email | D12: Email (outbox in the demo) | E12: - | F12: Contains sign-in link, username (work email), temporary password, role, reporting manager, joining date. | G12: -
... A15: E4 | B15: New employee | C15: Land on their own portal | D15: /home | E15: Role permissions (e.g. Employee: timesheet.own, daily_update.post, approvals.act, ai.use) | F15: Home dashboard chosen by the role persona; navigation shows only permitted screens: My tasks, Timesheet, Daily update, Leave, Expenses, Documents, My performance, Ask AI. | G15: Working in SeereonOS
A18: Welcome email placeholders
A19: Placeholder | B19: Meaning | C19: Filled from | D19: Required in welcome email
A20: {{employee_name}} | B20: Employee name | C20: Create employee > Full name | D20: No
A21: {{company}} | B21: Company | C21: Organisation profile > brand name | D21: No
A22: {{username}} | B22: Username | C22: Work email | D22: Yes
A23: {{temp_password}} | B23: Temporary password | C23: Generated (length = security.password_min_length) | D23: Yes
A24: {{login_url}} | B24: Login link | C24: Workspace sign-in link | D24: Yes
A25: {{role_name}} | B25: Role | C25: Chosen role | D25: No
A26: {{manager_name}} | B26: Manager | C26: Reporting manager | D26: No
A27: {{joining_date}} | B27: Joining date | C27: Joining date (e.g. 1 October 2026) | D27: No
A28: {{employee_code}} | B28: Employee code | C28: Org prefix + next number | D28: No
A29: {{designation}} | B29: Designation | C29: Designation | D29: No
A30: {{department}} | B30: Department | C30: Department | D30: No
A33: Default welcome email (template "welcome")
A34: Subject: Welcome to {{company}}, {{employee_name}} — your SeereonOS login Hi {{employee_name}}, Welcome to {{company}}! Your SeereonOS account is ready. Sign in: {{login_url}} Username: {{username}} Temporary password: {{temp_password}} You will be asked to set your own password the first time you sign in. Your role: {{role_name}} Reporting manager: {{manager_name}} Joining date: {{joining_date}} See you on day one, {{company}} HR

Sheet Approvals & SLAs
A1: ID | B1: What is approved | C1: Requester | D1: Approver resolution rule | E1: Delegation / cover | F1: SLA | G1: On approve | H1: On reject / send back | I1: Mandatory reason or input | J1: Escalation / overdue handling | K1: Inbox kind | L1: Screen | M1: Process ID | N1: Status
A2: APR-01 | B2: Weekly timesheet | C2: Every person (all roles) | D2: Reports-to manager (BR-07); top person (admin with no manager) is auto-approved; Admin can act on all. v4: routed by the "Weekly timesheets" workflow (default reproduces this rule); SLA and escalation per step. | E2: Active delegate of the approver | F2: approval.sla_working_days from submission (company setting, default 2, range 1-10) | G2: Week approved and frozen; hours count for cost, billing and pay; NTF-05 | H2: Week reopens for the person to fix and resubmit; NTF-06 | I2: Reject reason min 5 characters (TS_REASON_REQUIRED); cannot approve own week (TS_SELF_APPROVAL) | J2: Late approval flagged (APPROVAL_LATE) and counted in the manager's Approval KPI = -(late + overdue pending) (BR-11); never blocks; NTF-10 digest defined | K2: timesheet (bulk approve if approval.bulk_approve) | L2: /approvals, /inbox | M2: TIM-03 | N2: Extended
A3: APR-02 | B3: Timesheet unlock request | C3: Person whose week locked unsubmitted | D3: Same approver as the timesheet; Admin | E3: Active delegate | F3: approval.sla_working_days from request | G3: Week editable for 1-7 days (timesheet.unlock_max_days); NTF-08 | H3: Request declined, week stays locked; NTF-08 | I3: Request reason min 5; decline reason min 5; TS_UNLOCK_RANGE | J3: Overdue badge in inbox | K3: unlock | L3: /approvals, /inbox | M3: TIM-04 | N3: Live
A4: APR-03 | B4: Task completion (review) | C4: Task owner or backup | D4: Task reviewer if set; else project PM (project tasks); else the assigner, then owner's manager (general tasks); never the owner unless top admin; Admin always. v4: routed by the "Task completion review" workflow (default: task reviewer). | E4: Delegate of the reviewer sees it in the inbox | F4: approval.sla_working_days from submission | G4: Task Done with quality 1-5; done date = submission date; timeliness early / on time / late stamped; dependants unblocked; NTF-05 | H4: Send back: task returns to In progress, round +1, optional new due date (logged as reschedule); NTF-06 | I4: Submit: note min 5; delay reason code + 15-character explanation if late (DELAY_REASON_REQUIRED). Approve: quality rating 1-5. Send back: reason min 10 | J4: Overdue badge; inbox warns if submitted late without a reason | K4: task_review | L4: /inbox, /team-tasks?tab=review, task drawer | M4: TSK-04, TSK-06, TSK-07 | N4: Extended
A5: APR-04 | B5: Leave request | C5: Employee (any role) | D5: Reports-to manager; auto-approved when there is no manager; Admin can decide any. v4: routed by the "Leave requests" workflow (default: reporting manager). | E5: Active delegate of the manager (also notified) | F5: approval.sla_working_days from request | G5: Balance re-checked; leave days written to the timesheet and leave register; NTF-05 | H5: Request rejected; NTF-06 | I5: Request reason min 5; reject reason min 5; cannot decide own leave | J5: Overdue badge; HR Home lists pending leave company-wide | K5: leave | L5: /leave, /inbox | M5: TIM-06, TIM-07 | N5: Extended
A6: APR-05 | B6: Expense claim (up to Rs 25,000) | C6: Employee (any role) | D6: Project PM if the claim is on a project (and PM is not the claimant); else reports-to manager; else Admin. v4: routed by the "Expense claims" workflow, step 1 (PM else reporting manager). | E6: Delegate of the approver | F6: approval.sla_working_days from submission | G6: Approved; checked against the month's category budget (outside budget = unbudgeted spend, OVER_BUDGET); goes to To pay; NTF-05 | H6: Rejected; claimant can edit and resubmit; NTF-06 | I6: Reject reason min 5 (REASON_REQUIRED); no self-approval (SELF_APPROVAL) | J6: Overdue badge | K6: expense (approve) | L6: /expenses?tab=approve, /inbox | M6: SPD-02 | N6: Extended
A7: APR-06 | B7: Expense claim above Rs 25,000 (second step) | C7: Employee | D7: First approval by PM / manager as above, then Admin (CEO) for final approval. v4: step 2 of the "Expense claims" workflow (CEO role, above Rs 25,000); threshold configurable. | E7: - | F7: approval.sla_working_days per step | G7: As APR-05 after Admin approval | H7: As APR-05 | I7: As APR-05 | J7: SECOND_APPROVAL warning tells the first approver it moved to the Admin | K7: expense (approve) | L7: /expenses, /inbox | M7: SPD-02 | N7: Extended
A8: APR-07 | B8: Expense reimbursement (payment) | C8: System (approved claim) | D8: Admin or HR & operations (expenses.pay) | E8: - | F8: approval.sla_working_days from approval | G8: Paid; locked ledger expense row created; NTF-05 reimbursed | H8: - | I8: Payment date (not future) | J8: Overdue badge | K8: expense (pay) | L8: /expenses?tab=pay, /inbox | M8: SPD-03 | N8: New in v3
A9: APR-08 | B9: Purchase order | C9: Admin or HR & operations | D9: Admin (CEO) only. v4: routed by the "Purchase orders" workflow (default: CEO role). | E9: - | F9: approval.sla_working_days from submission | G9: PO approved: commits budget; bills can be booked against it; NTF-05 | H9: PO rejected; NTF-06 | I9: Justification min 15 when over budget (JUSTIFICATION_REQUIRED); reject reason min 5 | J9: Overdue badge; over-budget flag shown to approver | K9: purchase_order | L9: /purchases, /inbox | M9: SPD-04, SPD-05 | N9: Extended
A10: APR-09 | B10: Vendor bill approval | C10: Admin or HR & operations (booking) | D10: Admin (CEO) only. v4: routed by the "Vendor bills" workflow (default: CEO role). | E10: - | F10: approval.sla_working_days from bill date | G10: Approved for payment by due date; NTF-05 | H10: Dispute with reason (min 10); resolve before approving | I10: Must match an approved PO within +5% (BILL_EXCEEDS_PO) | J10: Inbox warns: no PO linked / bill higher than PO | K10: vendor_bill (approve) | L10: /purchases, /inbox | M10: SPD-06, SPD-07 | N10: Extended
A11: APR-10 | B11: Vendor bill payment | C11: System (approved bill) | D11: Admin or HR & operations | E11: - | F11: Bill due date (vendor payment terms) | G11: Paid; ledger expense row; payables ageing updates | H11: - | I11: Payment date (not future) | J11: Overdue after due date | K11: vendor_bill (pay) | L11: /purchases, /inbox | M11: SPD-07 | N11: New in v3
A12: APR-11 | B12: Appraisal - manager review | C12: Employee (self review submitted) | D12: The appraisal's manager (reports-to at launch) | E12: Active delegate of the manager | F12: Cycle manager due date | G12: Goes to HR review | H12: HR can send back to the manager | I12: Rating 1-5; comments min 30 | J12: Overdue badge after the cycle date | K12: appraisal | L12: /appraisals/:id, /inbox | M12: HR-12 | N12: New in v3
... A22: APR-20 | B22: Travel request and advance | C22: Employee | D22: Project PM, else reports-to manager; Admin above a limit | E22: Delegate | F22: 2 working days (recommended) | G22: Travel booked, advance paid | H22: Rejected with reason | I22: Purpose, project, estimate | J22: Inbox overdue | K22: travel (proposed) | L22: - | M22: SPD-11 | N22: Planned

Sheet KPI dictionary
A1: KPI | B1: Definition | C1: Formula (as computed) | D1: Source data | E1: Frequency / window | F1: Owner role | G1: Where shown | H1: Target / threshold setting | I1: Status
A2: Task on-time % | B2: Share of completed tasks finished on or before the due date | C2: (early + on time) / completed tasks in the window | D2: tasks (status done, timeliness) | E2: Last 90 days on dashboards; any period in Team tasks | F2: Line manager / PM | G2: CEO, HR & operations, PM, Employee Home (task delivery); CEO People panel; Reports / Ask AI; Team tasks > Performance; My performance; Appraisal | H2: Tone: green / amber / red bands on panels | I2: New in v3
A3: Timeliness (early / on time / late) | B3: Classification of each completed task | C3: variance = signed working days between due date and submission date (weekends, holidays excluded); < 0 early, = 0 on time, > 0 late | D3: tasks.due_on, submission date, calendar | E3: Per task | F3: Reviewer | G3: Task drawer, Team tasks, inbox | H3: - | I3: New in v3
A4: Average variance (days) | B4: How early or late work lands on average | C4: sum(variance days) / completed tasks | D4: tasks.variance_days | E4: Period | F4: Line manager | G4: Team tasks > Performance, My performance | H4: 0 or negative is good | I4: New in v3
A5: First-pass approval % | B5: Share of reviewed tasks approved without a send-back | C5: done tasks with reviews and no "sent back" decision / done tasks with reviews | D5: task_reviews | E5: Period | F5: Line manager | G5: Team tasks > Performance, My performance, Appraisal | H5: - | I5: New in v3
A6: Average quality rating | B6: Reviewer's quality score of approved work | C6: mean(quality_rating 1-5) over completed tasks | D6: tasks.quality_rating | E6: Period | F6: Reviewer | G6: Team tasks > Performance, My performance, Appraisal | H6: - | I6: New in v3
A7: Sent-back count | B7: Rework rounds | C7: count of task_reviews with decision = sent_back | D7: task_reviews | E7: Period | F7: Line manager | G7: Team tasks | H7: - | I7: New in v3
A8: Delay reasons | B8: Why tasks were late | C8: count of tasks by delay_reason_code (top 3 per person, top 9 overall) | D8: tasks.delay_reason_code | E8: Period | F8: Line manager | G8: Team tasks > Performance | H8: - | I8: New in v3
A9: Overdue open tasks | B9: Open work past its due date | C9: count(open tasks with due_on < today); overdue days = working days since due | D9: tasks | E9: Live | F9: PM / Line manager | G9: Employee Home, Team tasks, CEO delivery | H9: - | I9: Live
A10: Effort ratio | B10: How long work takes vs estimate (BR-26) | C10: actual hours / estimated hours (finished tasks with logged time; otherwise open work vs pro-rata estimate) | D10: timesheet_entries, tasks.est_hours | E10: Per task / project | F10: PM | G10: Project money tab, Insights > Effort overruns, Estimation accuracy | H10: projects.effort_ratio_alert = 1.2 | I10: Live
A11: SPI (schedule performance) | B11: Earned vs planned progress by today | C11: earned / planned, capped at 2; earned = estimate of done tasks + 50% of logged (capped) on open tasks; planned = estimate due by today, linear over each task window | D11: tasks, hours | E11: Live | F11: PM | G11: CEO delivery, PM delivery control, project | H11: SPI < 0.8 on an active project turns health At risk | I11: Live
A12: Project health | B12: On track / At risk / Off track | C12: Off track if projected margin < 0, or (margin below floor AND effort ratio > alert), or 2+ overdue milestones; At risk if margin below floor, or effort ratio > alert, or 1 overdue milestone, or SPI < 0.8 | D12: project metrics | E12: Live | F12: PM | G12: CEO project health strip, PM delivery control, Projects list | H12: projects.margin_floor_pct 25%, effort_ratio_alert 1.2 | I12: Live
... A50: Setup completion | B50: How far a workspace is through setup | C50: steps done / 7 (org, places, structure, roles, controls, people, emails) | D50: master data, roles, change_sets, workflows, templates, outbox | E50: Live | F50: Administrator | G50: Setup checklist (/setup) | H50: All 7 done | I50: New in v4

Sheet Requested flows check
A1: # | B1: Release | C1: Requested flow | D1: Status before | E1: What was built | F1: Where it appears (screens / dashboards) | G1: Rules and validations | H1: How to demo (login and steps) | I1: Status | J1: Remaining gaps
A2: 1 | B2: v3 | C2: Managers assign tasks to employees | D2: Only Admin and PMs could create tasks, and only inside project WBS. Line managers outside projects (Sales, HR) had no way to assign work. | E2: Team tasks > Assign: any manager assigns a task to people in their reporting line, or anyone on a project they manage, under a client project or the built-in "General & admin" project (GEN). Captures priority, estimate, start, due, reviewer (default = assigner). | F2: Team tasks (/team-tasks?tab=assign, Team tab); employee's My tasks and Home (Today / This week); notification bell. | G2: Owner active; title 3-200; project Active/Initiated or GEN; 403 if the person is not in your line or project; due date today or later and not before start; NON_WORKING_DAY warning; estimate 0.5-200 h; reviewer active and not the owner (TASK_SELF_REVIEW). NTF-14 to the owner. | H2: Log in as subhankar@seereon.co.in (PM) / Seereon@123 > Team tasks > Assign > pick Hritesh, project or General & admin, title, due date, estimate > Assign. Then log in as hritesh@seereon.co.in: the task is in My tasks and the bell shows "Task assigned to you". | I2: Delivered | J2: None open.
A3: 2 | B3: v3 | C3: Manager approval of tasks, with validations and reasons | D3: Employees could move their own task straight to Done; no review step, no quality score, no reason trail. | E3: Review flow: Submit for review (note + optional proof link) > reviewer Approves with a 1-5 quality rating, or Sends back with a reason (optional new due date). Rounds and decisions are kept per task. Direct Done is blocked (USE_REVIEW_FLOW). Due-date changes need a reason (DUE_REASON_REQUIRED). | F3: Approvals inbox (task_review), Team tasks > Review queue, task drawer review history; Team tab shows sent-back count and last reason. | G3: Reviewer resolution: task reviewer > project PM > assigner / owner's manager; never self (TASK_SELF_REVIEW) except top admin. Submit note min 5; proof https only; approve rating 1-5; send-back reason min 10; reschedule reason min 10; inbox SLA approval.sla_working_days (default 2). NTF-04 / 05 / 06. | H3: As hritesh@: open a task > Submit for review with a note. As subhankar@: Approvals inbox > the task > Approve with 4 stars (or Send back with a reason). As hritesh@: see the NTF-05 / NTF-06 notification and the review history in the task. | I3: Delivered | J3: None open. (General tasks without a stored reviewer route to the assigner; inbox SLA follows approval.sla_working_days.)
A4: 3 | B4: v3 | C4: Completion on time / early / late reflected on Admin, HR and CEO dashboards | D4: Dashboards showed a simple "tasks on time" share (done_on <= due_on, calendar days) on the CEO delivery tile only. | E4: Calendar-aware timeliness stamped on approval: early / on time / late with working-day variance, based on the submission date. Shared calculation (performance.ts) feeds: Task delivery panel (CEO and HR & operations = company, PM = team, Employee = me, last 90 days: on-time / early / late, slip, first-pass, delay reasons), CEO People panel (on-time %), Team tasks > Performance (by person / project / manager), My performance, appraisal system score, OKR auto metric, report builder / Ask AI (tasks and task_reviews datasets). | F4: CEO / Admin Home (Task delivery + People panel); HR & operations Home (Task delivery, company); PM Home; Employee Home (My delivery); Team tasks > Performance (company scope for Admin and HR & operations); My performance /performance/:userId; Appraisals. | G4: Working days per BR-01; on-time % = (early + on time) / completed; avg variance; first-pass %; quality; delay reasons. | H4: As santosh@ (CEO): Home > Task delivery (company) and People panel. As priya@ (HR & ops): Home > Task delivery (company), then Team tasks > Performance (group by person or manager). As hritesh@: Home > My delivery. | I4: Delivered | J4: None open.
A5: 4 | B5: v3 | C5: Employee delay reasons | D5: No delay reason existed; late tasks carried no explanation. | E5: When a task is submitted after its due date, the owner must pick a reason (scope changed, waiting on another task, client delay, effort underestimated, leave/absence, re-prioritised, technical issue, resource shortage, other) and explain it. Reasons are stored on the review round and the task and aggregated. | F5: Task drawer (submit dialog), Approvals inbox (shown to the reviewer; warns if missing on older items), Team tasks (reason per task; top reasons in Performance), My performance. | G5: DELAY_REASON_REQUIRED: code from the list + explanation min 15 characters ("what happened and what you did about it"). | H5: As hritesh@: open an overdue task > Submit for review: the dialog requires a delay reason. As subhankar@: the inbox item shows the reason; Team tasks > Performance lists top delay reasons. | I5: Delivered | J5: None open. Delay reasons are also reportable in the report builder and Ask AI (tasks, task_reviews).
A6: 5 | B6: v3 | C6: PM uploads project documents that employees can access | D6: No document management; documents lived in email / drives. | E6: Documents module: PM (own projects) or Admin uploads files (max 10 MB) or links with category, visibility (project team / managers only / company), tags, versions with change notes, archive/restore, must-read with acknowledgement tracking. Company library managed by HR & ops. | F6: Project > Documents tab (/projects/:id/documents); Documents library (/documents); Approvals inbox ("Read: ..." for must-read); acknowledgement counts for owners. | G6: Title 3-120; category and visibility required; file OR https link; allowed types PDF, DOCX, XLSX, PPTX, PNG, JPG, CSV, TXT, MD; only Admin or the project PM change project documents; members (task owner, backup, allocated) see "project" documents, others get 404; version note min 5; NTF-14 to required readers of must-read documents. | H6: As subhankar@: open a project > Documents > Upload, tick Must read. As hritesh@ (a member of that project): Documents shows it and the Approvals inbox has "Read: ..."; open and Acknowledge. As subhankar@: see acknowledged / total. | I6: Delivered | J6: Non-must-read uploads do not notify the team; no full-text search inside files yet.
A7: 6 | B7: v4 | C7: Maker-checker process | D7: Every change applied by the person who made it; payroll finalisation was self-approved by the Admin. | E7: Guarded writes become change sets with before / after; a second person approves (applied) or rejects with a reason; maker can withdraw. 13 change types in Access, Money and Configuration groups; configurable per workspace with an SLA. | F7: Changes (/changes: To check, My changes, History); Setup > Maker-checker; "waiting for approval" banners on records; notifications; Audit trail. | G7: Maker <> checker; checker needs Check changes + the change's permission; one pending change per record; STALE -> failed; reject reason >= 10; NO_CHECKER refusal. | H7: As debasish@ (Administrator): Setup > Roles > HR Executive > tick "Pay expense claims" > Save: "Sent for approval". As santosh@ (CEO): Changes > To check > Approve. As debasish@: My changes shows Approved. | I7: Delivered | J7: Company settings appear as a change type but save directly.
A8: 7 | B8: v4 | C8: Granular role-permission matrix (roles as data) | D8: Five hard-coded roles (Admin, PM, Sales, HR & ops, Employee) plus two grants. | E8: 72 permissions in 9 modules; roles are tenant data with a persona; matrix editor, duplicate, compare, create custom roles. | F8: Setup > Roles & permissions (/setup/roles, /setup/roles/:key, Compare tab); Roles & permissions sheet in this workbook. | G8: Dependent permissions auto-added; ROLE_LOCKED; ROLE_SYSTEM; ROLE_IN_USE; LOCKOUT; maker-checked. | H8: As debasish@: Setup > Roles & permissions > open Project Manager > see the matrix; Compare roles tab. | I8: Delivered | J8: -
A9: 8 | B9: v4 | C9: Roles drive which screens people see (one login) | D9: Menus and data decided by the hard-coded role. | E9: One sign-in; navigation, buttons and server checks all use effective permissions; persona only picks the home dashboard; data scope by *_view_all permissions. | F9: Every screen; View as (read-only preview of any role). | G9: FORBIDDEN on actions without permission; VIEW_AS_READ_ONLY. | H9: Sign in as hritesh@ (Employee) and as priya@ (HR Manager): compare the menus. As santosh@: View as > Sales Executive. | I9: Delivered | J9: -
A10: 9 | B10: v4 | C10: Admin-configurable master data | D10: Company settings and holidays only; departments were fixed values. | E10: Organisation profile, locations, departments, designations, grades & CTC bands, cost centres, shifts & assignment, email templates & sent log. | F10: Setup (/setup/org ... /setup/emails); used by Create employee and approval workflows (department head). | G10: Format checks (GSTIN / PAN / CIN / TAN / IFSC / pincode), DUPLICATE, IN_USE, HEAD_OFFICE_REQUIRED, DEFAULT_SHIFT_REQUIRED, DEPARTMENT_CYCLE, GRADE_BAND, SHIFT_BREAK, SHIFT_MIN_HOURS. | H10: As debasish@: Setup > Departments > add one; Setup > Shifts > assign people. | I10: Delivered | J10: Holiday calendars are tenant-wide (a location names its calendar, but one holiday table applies).
A11: 10 | B11: v4 | C11: Admin flow: sign in > master data > create employee > welcome email > credentials > employee portal | D11: Admin invited people by link; invitee set their own password; no master data step. | E11: Setup checklist (7 steps); Create employee with role and reporting manager; temporary password; welcome email in the outbox; forced password change on first sign-in; employee lands on their portal. | F11: /setup, /people/new, /setup/emails?tab=sent, /login, /welcome/password, /home. See the Setup & onboarding flow sheet. | G11: See Setup & onboarding flow sheet; PASSWORD_CHANGE_REQUIRED; REQUIRED_PLACEHOLDER on the welcome template. | H11: As debasish@: /people/new > create "Ritu Das", Employee, reports to Subhankar > the success screen shows the email. Sign in as ritu@ with the temporary password > set a password > Employee home. | I11: Delivered | J11: Email delivery is simulated (outbox). Recruitment "Hire" still sends an invitation instead of using Create employee.
A12: 11 | B12: v4 | C12: Default roles incl. CTO, HR Manager and HR Executive | D12: No CTO or HR split. | E12: Administrator, CEO, CTO, Project Manager, HR Manager, HR Executive, Sales Manager, Sales Executive, Employee; provisioned for every workspace. | F12: Setup > Roles; Roles & permissions sheet. | G12: Built-in roles editable, not deletable. | H12: As debasish@: Setup > Roles shows the nine roles with member counts. | I12: Delivered | J12: No demo user holds CTO or HR Executive yet; assign one to demo them.
A13: 12 | B13: v4 | C13: Extra permissions on top of roles | D13: Only two grants (margins, salaries). | E13: Per-person extra and revoked permissions; effective = role + extra - revoked; shown on People and Role members. | F13: People > person > Access; Role detail > Members (+extra / -removed). | G13: PERMISSION_ESCALATION; LOCKOUT; maker-checked (user access). | H13: As debasish@: People > Subhankar: Project Manager + margins.view, documents.view_all. | I13: Delivered | J13: -
A14: 13 | B14: v4 | C14: Configurable approval workflows | D14: Approver rules fixed in code per process. | E14: Leave, expense, purchase order, vendor bill, timesheet and task review workflows with steps, amount thresholds, SLA, escalation; defaults reproduce v3; test panel. | F14: Setup > Approval workflows; inbox "Step n of m"; Approval workflows sheet. | G14: See Approval workflows sheet (WF_* codes). | H14: As debasish@: Setup > Approval workflows > Expense claims > Test this workflow with Hritesh, Rs 30,000. | I14: Delivered | J14: Escalation runs when the inbox is read (no background scheduler).
